Workbook

Sheet User Guide
A1: How to set up a Project
A2: *If you need any assistanse contact Clay Scheller
A3: 1. Create a copy of the template to your desktop and rename it to the project's name… DO NOT MODIFY THE TEMPLATE
A4: 2. On the "Project Data" tab, enter your Project Name and Address in the highlighted boxes
A5: 2b. As you work through project takeoffs, be sure to get the required SF for the listed items on the "Project Data" sheet
A6: 2c. At the bottom of the "Project Data" sheet, input Contingency, insurance, Bond, and Fee % (this will automatically calculate on the "OVERALL" sheet)
A7: 3. Go through separate division tabs 02-48 (NOT THE OVERALL SHEET)
A8: 3.b Division tabs have been prepopulated for the most used CSI codes. If you need other codes, Un Filter the sheet to see all codes. When you need to enter project scope specific information, you can overwrite any unused CSI codes. DO NOT DELETE OR ADD ANY LINES!
A9: 3C. Insert a "1" in column A in the cell next to each CSI code you will be using for this project
A10: If you want to see a CSI code broken out on a division tab, but not on the overall sheet, put a "2" in column A
A11: 4. On the OVERALL tab, use the filter in the top left and select only "1"
A12: 5. After setting up the project reference the "Entering Bids and Selecting Subcontractors" instructions below
... A24: 5a. If you are bid leveling with multiple vendors and need to uses more than one vendor, you must populate the information into one vendor column. Example - you are using vendor 1 for structural steel and vendor 2 for Misc metals. See below.
A25: #VALUE!
A26: 6. Once you have selected a bid for all of the divisions you are using in the project, go to the OVERALL tab and refresh the filter.
A27: To refresh the filter click on the filter icon on the filter cell line 8 and click "OK"
A28: 7. Check to make sure you have a number in each division you will be using. Hide the rows of divisions that you will not be using.
A29: 8. GC/GR's - Enter the Project Start Date and the Project Substantial Completion Date. The duration will auto populate.
A30: 9. Adjust your staffing and GR's accordingly. (there are formulas in some of the cells, you can adjust them as needed)
A31: 10. Once GC's and GR's have been entered, make sure there are no values beyond the completion date. All totals will auto calculate and populate the OVERAll sheet.
A32: 11. You can hide any NA months once you have finised GC's.

Sheet OVERALL
A8: Filter
A9: 1 | B9: PROJECT: | K9: DATE:
A10: 1 | B10: ='Project Data'!B4 -> Josephine Apartments (3rd Ave.) | G10: ='Project Data'!B5 -> 3rd Avenue | K10: =TODAY() -> 46090
A11: 1 | B11: ITEM | D11: GMP 1.23.26 | E11: Cost Per GSF | F11: Review Adjustments | G11: Current Budget Date | H11: Cost Per GSF | I11: ERROR | J11: Difference | K11: Notes
B12: INITIAL SF BUDGET | G12: =SUM(G13:G16) -> 0
D13: Copy and Paste VALUES ONLY! | F13: Copy and Paste VALUES ONLY!
A17: 1 | B17: Div. 02 - General Requirements | D17: =D28+D29+D43+D47 -> 121952 | E17: =D17/'Project Data'!$D$22 -> 1.3627292 | F17: 0 | G17: {=_xlfn.IFNA(_xlfn.IFS('02-Existing Conditions'!F9="*",'02-Existing Conditions'!E9,'02-Existing Conditions'!H9="*",'02-Existing Conditions'!G9,'02-Existing Conditions'!J9="*",'02-Existing Conditions'!I9,'02-Existing Conditions'!L9="*",'02-Existing Conditions'!K9,'02-Existing Conditions'!N9="*",'02-Existing Conditions'!M9,'02-Existing Conditions'!P9="*",'02-Existing Conditions'!O9,'02-Existing Conditions'!R9="*",'02-Existing Conditions'!Q9,'02-Existing Conditions'!T9="*",'02-Existing Conditions'!S9,'02-Existing Conditions'!V9="*",'02-Existing Conditions'!U9),"")} -> 0 | H17: =G17/'Project Data'!$D$22 -> #VALUE! | I17: ='02-Existing Conditions'!XFC9 | J17: =IFERROR(G17-F17, "--") -> --
A18: ='02-Existing Conditions'!A11 -> 0 | B18: ='02-Existing Conditions'!B11 -> 02 00 00 Existing Conditions | D18: {=_xlfn.IFNA(_xlfn.IFS('02-Existing Conditions'!D11="*",'02-Existing Conditions'!C11,'02-Existing Conditions'!F11="*",'02-Existing Conditions'!E11,'02-Existing Conditions'!H11="*",'02-Existing Conditions'!G11,'02-Existing Conditions'!J11="*",'02-Existing Conditions'!I11,'02-Existing Conditions'!L11="*",'02-Existing Conditions'!K11,'02-Existing Conditions'!N11="*",'02-Existing Conditions'!M11,'02-Existing Conditions'!P11="*",'02-Existing Conditions'!O11,'02-Existing Conditions'!R11="*",'02-Existing Conditions'!Q11,'02-Existing Conditions'!T11="*",'02-Existing Conditions'!S11),"")} | E18: =D18/'Project Data'!$D$22 -> 0 | G18: {=_xlfn.IFNA(_xlfn.IFS('02-Existing Conditions'!F11="*",'02-Existing Conditions'!E11,'02-Existing Conditions'!H11="*",'02-Existing Conditions'!G11,'02-Existing Conditions'!J11="*",'02-Existing Conditions'!I11,'02-Existing Conditions'!L11="*",'02-Existing Conditions'!K11,'02-Existing Conditions'!N11="*",'02-Existing Conditions'!M11,'02-Existing Conditions'!P11="*",'02-Existing Conditions'!O11,'02-Existing Conditions'!R11="*",'02-Existing Conditions'!Q11,'02-Existing Conditions'!T11="*",'02-Existing Conditions'!S11,'02-Existing Conditions'!V11="*",'02-Existing Conditions'!U11),"")} | H18: =G18/'Project Data'!$D$22 -> #VALUE!
A19: ='02-Existing Conditions'!A12 -> 0 | B19: ='02-Existing Conditions'!B12 -> 02 03 00 Conservation Treatment for Existing Period Conditions | D19: {=_xlfn.IFNA(_xlfn.IFS('02-Existing Conditions'!D12="*",'02-Existing Conditions'!C12,'02-Existing Conditions'!F12="*",'02-Existing Conditions'!E12,'02-Existing Conditions'!H12="*",'02-Existing Conditions'!G12,'02-Existing Conditions'!J12="*",'02-Existing Conditions'!I12,'02-Existing Conditions'!L12="*",'02-Existing Conditions'!K12,'02-Existing Conditions'!N12="*",'02-Existing Conditions'!M12,'02-Existing Conditions'!P12="*",'02-Existing Conditions'!O12,'02-Existing Conditions'!R12="*",'02-Existing Conditions'!Q12,'02-Existing Conditions'!T12="*",'02-Existing Conditions'!S12),"")} -> 0 | E19: =D19/'Project Data'!$D$22 -> 0 | F19: 0 | G19: {=_xlfn.IFNA(_xlfn.IFS('02-Existing Conditions'!F12="*",'02-Existing Conditions'!E12,'02-Existing Conditions'!H12="*",'02-Existing Conditions'!G12,'02-Existing Conditions'!J12="*",'02-Existing Conditions'!I12,'02-Existing Conditions'!L12="*",'02-Existing Conditions'!K12,'02-Existing Conditions'!N12="*",'02-Existing Conditions'!M12,'02-Existing Conditions'!P12="*",'02-Existing Conditions'!O12,'02-Existing Conditions'!R12="*",'02-Existing Conditions'!Q12,'02-Existing Conditions'!T12="*",'02-Existing Conditions'!S12,'02-Existing Conditions'!V12="*",'02-Existing Conditions'!U12),"")} -> 0 | H19: =G19/'Project Data'!$D$22 -> #VALUE!
A20: ='02-Existing Conditions'!A13 -> 0 | B20: ='02-Existing Conditions'!B13 -> 02 05 00 Common Work Results for Existing Conditions | D20: {=_xlfn.IFNA(_xlfn.IFS('02-Existing Conditions'!D13="*",'02-Existing Conditions'!C13,'02-Existing Conditions'!F13="*",'02-Existing Conditions'!E13,'02-Existing Conditions'!H13="*",'02-Existing Conditions'!G13,'02-Existing Conditions'!J13="*",'02-Existing Conditions'!I13,'02-Existing Conditions'!L13="*",'02-Existing Conditions'!K13,'02-Existing Conditions'!N13="*",'02-Existing Conditions'!M13,'02-Existing Conditions'!P13="*",'02-Existing Conditions'!O13,'02-Existing Conditions'!R13="*",'02-Existing Conditions'!Q13,'02-Existing Conditions'!T13="*",'02-Existing Conditions'!S13),"")} -> 0 | E20: =D20/'Project Data'!$D$22 -> 0 | F20: 0 | G20: {=_xlfn.IFNA(_xlfn.IFS('02-Existing Conditions'!F13="*",'02-Existing Conditions'!E13,'02-Existing Conditions'!H13="*",'02-Existing Conditions'!G13,'02-Existing Conditions'!J13="*",'02-Existing Conditions'!I13,'02-Existing Conditions'!L13="*",'02-Existing Conditions'!K13,'02-Existing Conditions'!N13="*",'02-Existing Conditions'!M13,'02-Existing Conditions'!P13="*",'02-Existing Conditions'!O13,'02-Existing Conditions'!R13="*",'02-Existing Conditions'!Q13,'02-Existing Conditions'!T13="*",'02-Existing Conditions'!S13,'02-Existing Conditions'!V13="*",'02-Existing Conditions'!U13),"")} -> 0 | H20: =G20/'Project Data'!$D$22 -> #VALUE!
A21: ='02-Existing Conditions'!A14 -> 0 | B21: ='02-Existing Conditions'!B14 -> 02 06 00 Schedules for Existing Conditions | D21: {=_xlfn.IFNA(_xlfn.IFS('02-Existing Conditions'!D14="*",'02-Existing Conditions'!C14,'02-Existing Conditions'!F14="*",'02-Existing Conditions'!E14,'02-Existing Conditions'!H14="*",'02-Existing Conditions'!G14,'02-Existing Conditions'!J14="*",'02-Existing Conditions'!I14,'02-Existing Conditions'!L14="*",'02-Existing Conditions'!K14,'02-Existing Conditions'!N14="*",'02-Existing Conditions'!M14,'02-Existing Conditions'!P14="*",'02-Existing Conditions'!O14,'02-Existing Conditions'!R14="*",'02-Existing Conditions'!Q14,'02-Existing Conditions'!T14="*",'02-Existing Conditions'!S14),"")} -> 0 | E21: =D21/'Project Data'!$D$22 -> 0 | F21: 0 | G21: {=_xlfn.IFNA(_xlfn.IFS('02-Existing Conditions'!F14="*",'02-Existing Conditions'!E14,'02-Existing Conditions'!H14="*",'02-Existing Conditions'!G14,'02-Existing Conditions'!J14="*",'02-Existing Conditions'!I14,'02-Existing Conditions'!L14="*",'02-Existing Conditions'!K14,'02-Existing Conditions'!N14="*",'02-Existing Conditions'!M14,'02-Existing Conditions'!P14="*",'02-Existing Conditions'!O14,'02-Existing Conditions'!R14="*",'02-Existing Conditions'!Q14,'02-Existing Conditions'!T14="*",'02-Existing Conditions'!S14,'02-Existing Conditions'!V14="*",'02-Existing Conditions'!U14),"")} -> 0 | H21: =G21/'Project Data'!$D$22 -> #VALUE!
A22: ='02-Existing Conditions'!A15 -> 0 | B22: ='02-Existing Conditions'!B15 -> 02 06 30 Schedules for Subsurface Investigations | D22: {=_xlfn.IFNA(_xlfn.IFS('02-Existing Conditions'!D15="*",'02-Existing Conditions'!C15,'02-Existing Conditions'!F15="*",'02-Existing Conditions'!E15,'02-Existing Conditions'!H15="*",'02-Existing Conditions'!G15,'02-Existing Conditions'!J15="*",'02-Existing Conditions'!I15,'02-Existing Conditions'!L15="*",'02-Existing Conditions'!K15,'02-Existing Conditions'!N15="*",'02-Existing Conditions'!M15,'02-Existing Conditions'!P15="*",'02-Existing Conditions'!O15,'02-Existing Conditions'!R15="*",'02-Existing Conditions'!Q15,'02-Existing Conditions'!T15="*",'02-Existing Conditions'!S15),"")} -> 0 | E22: =D22/'Project Data'!$D$22 -> 0 | F22: 0 | G22: {=_xlfn.IFNA(_xlfn.IFS('02-Existing Conditions'!F15="*",'02-Existing Conditions'!E15,'02-Existing Conditions'!H15="*",'02-Existing Conditions'!G15,'02-Existing Conditions'!J15="*",'02-Existing Conditions'!I15,'02-Existing Conditions'!L15="*",'02-Existing Conditions'!K15,'02-Existing Conditions'!N15="*",'02-Existing Conditions'!M15,'02-Existing Conditions'!P15="*",'02-Existing Conditions'!O15,'02-Existing Conditions'!R15="*",'02-Existing Conditions'!Q15,'02-Existing Conditions'!T15="*",'02-Existing Conditions'!S15,'02-Existing Conditions'!V15="*",'02-Existing Conditions'!U15),"")} -> 0 | H22: =G22/'Project Data'!$D$22 -> #VALUE!
A23: ='02-Existing Conditions'!A16 -> 0 | B23: ='02-Existing Conditions'!B16 -> 02 06 30.13 Boring or Test Pit Log Schedule | D23: {=_xlfn.IFNA(_xlfn.IFS('02-Existing Conditions'!D16="*",'02-Existing Conditions'!C16,'02-Existing Conditions'!F16="*",'02-Existing Conditions'!E16,'02-Existing Conditions'!H16="*",'02-Existing Conditions'!G16,'02-Existing Conditions'!J16="*",'02-Existing Conditions'!I16,'02-Existing Conditions'!L16="*",'02-Existing Conditions'!K16,'02-Existing Conditions'!N16="*",'02-Existing Conditions'!M16,'02-Existing Conditions'!P16="*",'02-Existing Conditions'!O16,'02-Existing Conditions'!R16="*",'02-Existing Conditions'!Q16,'02-Existing Conditions'!T16="*",'02-Existing Conditions'!S16),"")} -> 0 | E23: =D23/'Project Data'!$D$22 -> 0 | F23: 0 | G23: {=_xlfn.IFNA(_xlfn.IFS('02-Existing Conditions'!F16="*",'02-Existing Conditions'!E16,'02-Existing Conditions'!H16="*",'02-Existing Conditions'!G16,'02-Existing Conditions'!J16="*",'02-Existing Conditions'!I16,'02-Existing Conditions'!L16="*",'02-Existing Conditions'!K16,'02-Existing Conditions'!N16="*",'02-Existing Conditions'!M16,'02-Existing Conditions'!P16="*",'02-Existing Conditions'!O16,'02-Existing Conditions'!R16="*",'02-Existing Conditions'!Q16,'02-Existing Conditions'!T16="*",'02-Existing Conditions'!S16,'02-Existing Conditions'!V16="*",'02-Existing Conditions'!U16),"")} -> 0 | H23: =G23/'Project Data'!$D$22 -> #VALUE!
A24: ='02-Existing Conditions'!A17 -> 0 | B24: ='02-Existing Conditions'!B17 -> 02 06 50 Schedules for Site Remediation | D24: {=_xlfn.IFNA(_xlfn.IFS('02-Existing Conditions'!D17="*",'02-Existing Conditions'!C17,'02-Existing Conditions'!F17="*",'02-Existing Conditions'!E17,'02-Existing Conditions'!H17="*",'02-Existing Conditions'!G17,'02-Existing Conditions'!J17="*",'02-Existing Conditions'!I17,'02-Existing Conditions'!L17="*",'02-Existing Conditions'!K17,'02-Existing Conditions'!N17="*",'02-Existing Conditions'!M17,'02-Existing Conditions'!P17="*",'02-Existing Conditions'!O17,'02-Existing Conditions'!R17="*",'02-Existing Conditions'!Q17,'02-Existing Conditions'!T17="*",'02-Existing Conditions'!S17),"")} -> 0 | E24: =D24/'Project Data'!$D$22 -> 0 | F24: 0 | G24: {=_xlfn.IFNA(_xlfn.IFS('02-Existing Conditions'!F17="*",'02-Existing Conditions'!E17,'02-Existing Conditions'!H17="*",'02-Existing Conditions'!G17,'02-Existing Conditions'!J17="*",'02-Existing Conditions'!I17,'02-Existing Conditions'!L17="*",'02-Existing Conditions'!K17,'02-Existing Conditions'!N17="*",'02-Existing Conditions'!M17,'02-Existing Conditions'!P17="*",'02-Existing Conditions'!O17,'02-Existing Conditions'!R17="*",'02-Existing Conditions'!Q17,'02-Existing Conditions'!T17="*",'02-Existing Conditions'!S17,'02-Existing Conditions'!V17="*",'02-Existing Conditions'!U17),"")} -> 0 | H24: =G24/'Project Data'!$D$22 -> #VALUE!
A25: ='02-Existing Conditions'!A18 -> 0 | B25: ='02-Existing Conditions'!B18 -> 02 06 65 Schedules for Underground Storage Tank Removal | D25: {=_xlfn.IFNA(_xlfn.IFS('02-Existing Conditions'!D18="*",'02-Existing Conditions'!C18,'02-Existing Conditions'!F18="*",'02-Existing Conditions'!E18,'02-Existing Conditions'!H18="*",'02-Existing Conditions'!G18,'02-Existing Conditions'!J18="*",'02-Existing Conditions'!I18,'02-Existing Conditions'!L18="*",'02-Existing Conditions'!K18,'02-Existing Conditions'!N18="*",'02-Existing Conditions'!M18,'02-Existing Conditions'!P18="*",'02-Existing Conditions'!O18,'02-Existing Conditions'!R18="*",'02-Existing Conditions'!Q18,'02-Existing Conditions'!T18="*",'02-Existing Conditions'!S18),"")} -> 0 | E25: =D25/'Project Data'!$D$22 -> 0 | F25: 0 | G25: {=_xlfn.IFNA(_xlfn.IFS('02-Existing Conditions'!F18="*",'02-Existing Conditions'!E18,'02-Existing Conditions'!H18="*",'02-Existing Conditions'!G18,'02-Existing Conditions'!J18="*",'02-Existing Conditions'!I18,'02-Existing Conditions'!L18="*",'02-Existing Conditions'!K18,'02-Existing Conditions'!N18="*",'02-Existing Conditions'!M18,'02-Existing Conditions'!P18="*",'02-Existing Conditions'!O18,'02-Existing Conditions'!R18="*",'02-Existing Conditions'!Q18,'02-Existing Conditions'!T18="*",'02-Existing Conditions'!S18,'02-Existing Conditions'!V18="*",'02-Existing Conditions'!U18),"")} -> 0 | H25: =G25/'Project Data'!$D$22 -> #VALUE!
A26: ='02-Existing Conditions'!A19 -> 0 | B26: ='02-Existing Conditions'!B19 -> 02 06 80 Schedules for Facility Remediation | D26: {=_xlfn.IFNA(_xlfn.IFS('02-Existing Conditions'!D19="*",'02-Existing Conditions'!C19,'02-Existing Conditions'!F19="*",'02-Existing Conditions'!E19,'02-Existing Conditions'!H19="*",'02-Existing Conditions'!G19,'02-Existing Conditions'!J19="*",'02-Existing Conditions'!I19,'02-Existing Conditions'!L19="*",'02-Existing Conditions'!K19,'02-Existing Conditions'!N19="*",'02-Existing Conditions'!M19,'02-Existing Conditions'!P19="*",'02-Existing Conditions'!O19,'02-Existing Conditions'!R19="*",'02-Existing Conditions'!Q19,'02-Existing Conditions'!T19="*",'02-Existing Conditions'!S19),"")} -> 0 | E26: =D26/'Project Data'!$D$22 -> 0 | F26: 0 | G26: {=_xlfn.IFNA(_xlfn.IFS('02-Existing Conditions'!F19="*",'02-Existing Conditions'!E19,'02-Existing Conditions'!H19="*",'02-Existing Conditions'!G19,'02-Existing Conditions'!J19="*",'02-Existing Conditions'!I19,'02-Existing Conditions'!L19="*",'02-Existing Conditions'!K19,'02-Existing Conditions'!N19="*",'02-Existing Conditions'!M19,'02-Existing Conditions'!P19="*",'02-Existing Conditions'!O19,'02-Existing Conditions'!R19="*",'02-Existing Conditions'!Q19,'02-Existing Conditions'!T19="*",'02-Existing Conditions'!S19,'02-Existing Conditions'!V19="*",'02-Existing Conditions'!U19),"")} -> 0 | H26: =G26/'Project Data'!$D$22 -> #VALUE!
A27: ='02-Existing Conditions'!A20 -> 0 | B27: ='02-Existing Conditions'!B20 -> 02 06 86 Schedules for Hazardous Waste Drum Handling | D27: {=_xlfn.IFNA(_xlfn.IFS('02-Existing Conditions'!D20="*",'02-Existing Conditions'!C20,'02-Existing Conditions'!F20="*",'02-Existing Conditions'!E20,'02-Existing Conditions'!H20="*",'02-Existing Conditions'!G20,'02-Existing Conditions'!J20="*",'02-Existing Conditions'!I20,'02-Existing Conditions'!L20="*",'02-Existing Conditions'!K20,'02-Existing Conditions'!N20="*",'02-Existing Conditions'!M20,'02-Existing Conditions'!P20="*",'02-Existing Conditions'!O20,'02-Existing Conditions'!R20="*",'02-Existing Conditions'!Q20,'02-Existing Conditions'!T20="*",'02-Existing Conditions'!S20),"")} -> 0 | E27: =D27/'Project Data'!$D$22 -> 0 | F27: 0 | G27: {=_xlfn.IFNA(_xlfn.IFS('02-Existing Conditions'!F20="*",'02-Existing Conditions'!E20,'02-Existing Conditions'!H20="*",'02-Existing Conditions'!G20,'02-Existing Conditions'!J20="*",'02-Existing Conditions'!I20,'02-Existing Conditions'!L20="*",'02-Existing Conditions'!K20,'02-Existing Conditions'!N20="*",'02-Existing Conditions'!M20,'02-Existing Conditions'!P20="*",'02-Existing Conditions'!O20,'02-Existing Conditions'!R20="*",'02-Existing Conditions'!Q20,'02-Existing Conditions'!T20="*",'02-Existing Conditions'!S20,'02-Existing Conditions'!V20="*",'02-Existing Conditions'!U20),"")} -> 0 | H27: =G27/'Project Data'!$D$22 -> #VALUE!
A28: ='02-Existing Conditions'!A21 -> 1 | B28: ='02-Existing Conditions'!B21 -> 02 21 00 Surveys | D28: {=_xlfn.IFNA(_xlfn.IFS('02-Existing Conditions'!D21="*",'02-Existing Conditions'!C21,'02-Existing Conditions'!F21="*",'02-Existing Conditions'!E21,'02-Existing Conditions'!H21="*",'02-Existing Conditions'!G21,'02-Existing Conditions'!J21="*",'02-Existing Conditions'!I21,'02-Existing Conditions'!L21="*",'02-Existing Conditions'!K21,'02-Existing Conditions'!N21="*",'02-Existing Conditions'!M21,'02-Existing Conditions'!P21="*",'02-Existing Conditions'!O21,'02-Existing Conditions'!R21="*",'02-Existing Conditions'!Q21,'02-Existing Conditions'!T21="*",'02-Existing Conditions'!S21),"")} -> 30000 | E28: =D28/'Project Data'!$D$22 -> 0.33522924 | F28: 30000 | G28: {=_xlfn.IFNA(_xlfn.IFS('02-Existing Conditions'!F21="*",'02-Existing Conditions'!E21,'02-Existing Conditions'!H21="*",'02-Existing Conditions'!G21,'02-Existing Conditions'!J21="*",'02-Existing Conditions'!I21,'02-Existing Conditions'!L21="*",'02-Existing Conditions'!K21,'02-Existing Conditions'!N21="*",'02-Existing Conditions'!M21,'02-Existing Conditions'!P21="*",'02-Existing Conditions'!O21,'02-Existing Conditions'!R21="*",'02-Existing Conditions'!Q21,'02-Existing Conditions'!T21="*",'02-Existing Conditions'!S21,'02-Existing Conditions'!V21="*",'02-Existing Conditions'!U21),"")} -> 30000 | H28: =G28/'Project Data'!$D$22 -> 0.33522924 | K28: Angleright
A29: ='02-Existing Conditions'!A22 -> 1 | B29: ='02-Existing Conditions'!B22 -> 02 21 13 Construction Security Cameras | D29: ='02-Existing Conditions'!E22 -> 29014 | E29: =D29/'Project Data'!$D$22 -> 0.32421137 | F29: 0 | G29: {=_xlfn.IFNA(_xlfn.IFS('02-Existing Conditions'!F22="*",'02-Existing Conditions'!E22,'02-Existing Conditions'!H22="*",'02-Existing Conditions'!G22,'02-Existing Conditions'!J22="*",'02-Existing Conditions'!I22,'02-Existing Conditions'!L22="*",'02-Existing Conditions'!K22,'02-Existing Conditions'!N22="*",'02-Existing Conditions'!M22,'02-Existing Conditions'!P22="*",'02-Existing Conditions'!O22,'02-Existing Conditions'!R22="*",'02-Existing Conditions'!Q22,'02-Existing Conditions'!T22="*",'02-Existing Conditions'!S22,'02-Existing Conditions'!V22="*",'02-Existing Conditions'!U22),"")} -> 0 | H29: =G29/'Project Data'!$D$22 -> #VALUE! | K29: Stallion
A30: ='02-Existing Conditions'!A23 -> 0 | B30: ='02-Existing Conditions'!B23 -> 02 21 13.13 Boundary and Survey Markers | D30: {=_xlfn.IFNA(_xlfn.IFS('02-Existing Conditions'!D23="*",'02-Existing Conditions'!C23,'02-Existing Conditions'!F23="*",'02-Existing Conditions'!E23,'02-Existing Conditions'!H23="*",'02-Existing Conditions'!G23,'02-Existing Conditions'!J23="*",'02-Existing Conditions'!I23,'02-Existing Conditions'!L23="*",'02-Existing Conditions'!K23,'02-Existing Conditions'!N23="*",'02-Existing Conditions'!M23,'02-Existing Conditions'!P23="*",'02-Existing Conditions'!O23,'02-Existing Conditions'!R23="*",'02-Existing Conditions'!Q23,'02-Existing Conditions'!T23="*",'02-Existing Conditions'!S23),"")} -> 0 | E30: =D30/'Project Data'!$D$22 -> 0 | F30: 0 | G30: {=_xlfn.IFNA(_xlfn.IFS('02-Existing Conditions'!F23="*",'02-Existing Conditions'!E23,'02-Existing Conditions'!H23="*",'02-Existing Conditions'!G23,'02-Existing Conditions'!J23="*",'02-Existing Conditions'!I23,'02-Existing Conditions'!L23="*",'02-Existing Conditions'!K23,'02-Existing Conditions'!N23="*",'02-Existing Conditions'!M23,'02-Existing Conditions'!P23="*",'02-Existing Conditions'!O23,'02-Existing Conditions'!R23="*",'02-Existing Conditions'!Q23,'02-Existing Conditions'!T23="*",'02-Existing Conditions'!S23,'02-Existing Conditions'!V23="*",'02-Existing Conditions'!U23),"")} -> 0 | H30: =G30/'Project Data'!$D$22 -> #VALUE!
A31: ='02-Existing Conditions'!A24 -> 0 | B31: ='02-Existing Conditions'!B24 -> 02 22 00 Existing Conditions Assessment | D31: {=_xlfn.IFNA(_xlfn.IFS('02-Existing Conditions'!D24="*",'02-Existing Conditions'!C24,'02-Existing Conditions'!F24="*",'02-Existing Conditions'!E24,'02-Existing Conditions'!H24="*",'02-Existing Conditions'!G24,'02-Existing Conditions'!J24="*",'02-Existing Conditions'!I24,'02-Existing Conditions'!L24="*",'02-Existing Conditions'!K24,'02-Existing Conditions'!N24="*",'02-Existing Conditions'!M24,'02-Existing Conditions'!P24="*",'02-Existing Conditions'!O24,'02-Existing Conditions'!R24="*",'02-Existing Conditions'!Q24,'02-Existing Conditions'!T24="*",'02-Existing Conditions'!S24),"")} -> 0 | E31: =D31/'Project Data'!$D$22 -> 0 | F31: 0 | G31: {=_xlfn.IFNA(_xlfn.IFS('02-Existing Conditions'!F24="*",'02-Existing Conditions'!E24,'02-Existing Conditions'!H24="*",'02-Existing Conditions'!G24,'02-Existing Conditions'!J24="*",'02-Existing Conditions'!I24,'02-Existing Conditions'!L24="*",'02-Existing Conditions'!K24,'02-Existing Conditions'!N24="*",'02-Existing Conditions'!M24,'02-Existing Conditions'!P24="*",'02-Existing Conditions'!O24,'02-Existing Conditions'!R24="*",'02-Existing Conditions'!Q24,'02-Existing Conditions'!T24="*",'02-Existing Conditions'!S24,'02-Existing Conditions'!V24="*",'02-Existing Conditions'!U24),"")} -> 0 | H31: =G31/'Project Data'!$D$22 -> #VALUE!
A32: ='02-Existing Conditions'!A25 -> 0 | B32: ='02-Existing Conditions'!B25 -> 02 22 13 Movement and Vibration Assessment | D32: {=_xlfn.IFNA(_xlfn.IFS('02-Existing Conditions'!D25="*",'02-Existing Conditions'!C25,'02-Existing Conditions'!F25="*",'02-Existing Conditions'!E25,'02-Existing Conditions'!H25="*",'02-Existing Conditions'!G25,'02-Existing Conditions'!J25="*",'02-Existing Conditions'!I25,'02-Existing Conditions'!L25="*",'02-Existing Conditions'!K25,'02-Existing Conditions'!N25="*",'02-Existing Conditions'!M25,'02-Existing Conditions'!P25="*",'02-Existing Conditions'!O25,'02-Existing Conditions'!R25="*",'02-Existing Conditions'!Q25,'02-Existing Conditions'!T25="*",'02-Existing Conditions'!S25),"")} -> 0 | E32: =D32/'Project Data'!$D$22 -> 0 | F32: 0 | G32: {=_xlfn.IFNA(_xlfn.IFS('02-Existing Conditions'!F25="*",'02-Existing Conditions'!E25,'02-Existing Conditions'!H25="*",'02-Existing Conditions'!G25,'02-Existing Conditions'!J25="*",'02-Existing Conditions'!I25,'02-Existing Conditions'!L25="*",'02-Existing Conditions'!K25,'02-Existing Conditions'!N25="*",'02-Existing Conditions'!M25,'02-Existing Conditions'!P25="*",'02-Existing Conditions'!O25,'02-Existing Conditions'!R25="*",'02-Existing Conditions'!Q25,'02-Existing Conditions'!T25="*",'02-Existing Conditions'!S25,'02-Existing Conditions'!V25="*",'02-Existing Conditions'!U25),"")} -> 0 | H32: =G32/'Project Data'!$D$22 -> #VALUE!
A33: ='02-Existing Conditions'!A26 -> 0 | B33: ='02-Existing Conditions'!B26 -> 02 22 16 Acoustic Assessment | D33: {=_xlfn.IFNA(_xlfn.IFS('02-Existing Conditions'!D26="*",'02-Existing Conditions'!C26,'02-Existing Conditions'!F26="*",'02-Existing Conditions'!E26,'02-Existing Conditions'!H26="*",'02-Existing Conditions'!G26,'02-Existing Conditions'!J26="*",'02-Existing Conditions'!I26,'02-Existing Conditions'!L26="*",'02-Existing Conditions'!K26,'02-Existing Conditions'!N26="*",'02-Existing Conditions'!M26,'02-Existing Conditions'!P26="*",'02-Existing Conditions'!O26,'02-Existing Conditions'!R26="*",'02-Existing Conditions'!Q26,'02-Existing Conditions'!T26="*",'02-Existing Conditions'!S26),"")} -> 0 | E33: =D33/'Project Data'!$D$22 -> 0 | F33: 0 | G33: {=_xlfn.IFNA(_xlfn.IFS('02-Existing Conditions'!F26="*",'02-Existing Conditions'!E26,'02-Existing Conditions'!H26="*",'02-Existing Conditions'!G26,'02-Existing Conditions'!J26="*",'02-Existing Conditions'!I26,'02-Existing Conditions'!L26="*",'02-Existing Conditions'!K26,'02-Existing Conditions'!N26="*",'02-Existing Conditions'!M26,'02-Existing Conditions'!P26="*",'02-Existing Conditions'!O26,'02-Existing Conditions'!R26="*",'02-Existing Conditions'!Q26,'02-Existing Conditions'!T26="*",'02-Existing Conditions'!S26,'02-Existing Conditions'!V26="*",'02-Existing Conditions'!U26),"")} -> 0 | H33: =G33/'Project Data'!$D$22 -> #VALUE!
A34: ='02-Existing Conditions'!A27 -> 0 | B34: ='02-Existing Conditions'!B27 -> 02 22 19 Traffic Assessment | D34: {=_xlfn.IFNA(_xlfn.IFS('02-Existing Conditions'!D27="*",'02-Existing Conditions'!C27,'02-Existing Conditions'!F27="*",'02-Existing Conditions'!E27,'02-Existing Conditions'!H27="*",'02-Existing Conditions'!G27,'02-Existing Conditions'!J27="*",'02-Existing Conditions'!I27,'02-Existing Conditions'!L27="*",'02-Existing Conditions'!K27,'02-Existing Conditions'!N27="*",'02-Existing Conditions'!M27,'02-Existing Conditions'!P27="*",'02-Existing Conditions'!O27,'02-Existing Conditions'!R27="*",'02-Existing Conditions'!Q27,'02-Existing Conditions'!T27="*",'02-Existing Conditions'!S27),"")} -> 0 | E34: =D34/'Project Data'!$D$22 -> 0 | F34: 0 | G34: {=_xlfn.IFNA(_xlfn.IFS('02-Existing Conditions'!F27="*",'02-Existing Conditions'!E27,'02-Existing Conditions'!H27="*",'02-Existing Conditions'!G27,'02-Existing Conditions'!J27="*",'02-Existing Conditions'!I27,'02-Existing Conditions'!L27="*",'02-Existing Conditions'!K27,'02-Existing Conditions'!N27="*",'02-Existing Conditions'!M27,'02-Existing Conditions'!P27="*",'02-Existing Conditions'!O27,'02-Existing Conditions'!R27="*",'02-Existing Conditions'!Q27,'02-Existing Conditions'!T27="*",'02-Existing Conditions'!S27,'02-Existing Conditions'!V27="*",'02-Existing Conditions'!U27),"")} -> 0 | H34: =G34/'Project Data'!$D$22 -> #VALUE!
A35: ='02-Existing Conditions'!A28 -> 0 | B35: ='02-Existing Conditions'!B28 -> 02 24 13.13 Air Assessment | D35: {=_xlfn.IFNA(_xlfn.IFS('02-Existing Conditions'!D28="*",'02-Existing Conditions'!C28,'02-Existing Conditions'!F28="*",'02-Existing Conditions'!E28,'02-Existing Conditions'!H28="*",'02-Existing Conditions'!G28,'02-Existing Conditions'!J28="*",'02-Existing Conditions'!I28,'02-Existing Conditions'!L28="*",'02-Existing Conditions'!K28,'02-Existing Conditions'!N28="*",'02-Existing Conditions'!M28,'02-Existing Conditions'!P28="*",'02-Existing Conditions'!O28,'02-Existing Conditions'!R28="*",'02-Existing Conditions'!Q28,'02-Existing Conditions'!T28="*",'02-Existing Conditions'!S28),"")} -> 0 | E35: =D35/'Project Data'!$D$22 -> 0 | F35: 0 | G35: {=_xlfn.IFNA(_xlfn.IFS('02-Existing Conditions'!F28="*",'02-Existing Conditions'!E28,'02-Existing Conditions'!H28="*",'02-Existing Conditions'!G28,'02-Existing Conditions'!J28="*",'02-Existing Conditions'!I28,'02-Existing Conditions'!L28="*",'02-Existing Conditions'!K28,'02-Existing Conditions'!N28="*",'02-Existing Conditions'!M28,'02-Existing Conditions'!P28="*",'02-Existing Conditions'!O28,'02-Existing Conditions'!R28="*",'02-Existing Conditions'!Q28,'02-Existing Conditions'!T28="*",'02-Existing Conditions'!S28,'02-Existing Conditions'!V28="*",'02-Existing Conditions'!U28),"")} -> 0 | H35: =G35/'Project Data'!$D$22 -> #VALUE!
A36: ='02-Existing Conditions'!A29 -> 0 | B36: ='02-Existing Conditions'!B29 -> 02 24 13.43 Water Assessment | D36: {=_xlfn.IFNA(_xlfn.IFS('02-Existing Conditions'!D29="*",'02-Existing Conditions'!C29,'02-Existing Conditions'!F29="*",'02-Existing Conditions'!E29,'02-Existing Conditions'!H29="*",'02-Existing Conditions'!G29,'02-Existing Conditions'!J29="*",'02-Existing Conditions'!I29,'02-Existing Conditions'!L29="*",'02-Existing Conditions'!K29,'02-Existing Conditions'!N29="*",'02-Existing Conditions'!M29,'02-Existing Conditions'!P29="*",'02-Existing Conditions'!O29,'02-Existing Conditions'!R29="*",'02-Existing Conditions'!Q29,'02-Existing Conditions'!T29="*",'02-Existing Conditions'!S29),"")} -> 0 | E36: =D36/'Project Data'!$D$22 -> 0 | F36: 0 | G36: {=_xlfn.IFNA(_xlfn.IFS('02-Existing Conditions'!F29="*",'02-Existing Conditions'!E29,'02-Existing Conditions'!H29="*",'02-Existing Conditions'!G29,'02-Existing Conditions'!J29="*",'02-Existing Conditions'!I29,'02-Existing Conditions'!L29="*",'02-Existing Conditions'!K29,'02-Existing Conditions'!N29="*",'02-Existing Conditions'!M29,'02-Existing Conditions'!P29="*",'02-Existing Conditions'!O29,'02-Existing Conditions'!R29="*",'02-Existing Conditions'!Q29,'02-Existing Conditions'!T29="*",'02-Existing Conditions'!S29,'02-Existing Conditions'!V29="*",'02-Existing Conditions'!U29),"")} -> 0 | H36: =G36/'Project Data'!$D$22 -> #VALUE!
A37: ='02-Existing Conditions'!A30 -> 0 | B37: ='02-Existing Conditions'!B30 -> 02 24 13.73 Land Assessment | D37: {=_xlfn.IFNA(_xlfn.IFS('02-Existing Conditions'!D30="*",'02-Existing Conditions'!C30,'02-Existing Conditions'!F30="*",'02-Existing Conditions'!E30,'02-Existing Conditions'!H30="*",'02-Existing Conditions'!G30,'02-Existing Conditions'!J30="*",'02-Existing Conditions'!I30,'02-Existing Conditions'!L30="*",'02-Existing Conditions'!K30,'02-Existing Conditions'!N30="*",'02-Existing Conditions'!M30,'02-Existing Conditions'!P30="*",'02-Existing Conditions'!O30,'02-Existing Conditions'!R30="*",'02-Existing Conditions'!Q30,'02-Existing Conditions'!T30="*",'02-Existing Conditions'!S30),"")} -> 0 | E37: =D37/'Project Data'!$D$22 -> 0 | F37: 0 | G37: {=_xlfn.IFNA(_xlfn.IFS('02-Existing Conditions'!F30="*",'02-Existing Conditions'!E30,'02-Existing Conditions'!H30="*",'02-Existing Conditions'!G30,'02-Existing Conditions'!J30="*",'02-Existing Conditions'!I30,'02-Existing Conditions'!L30="*",'02-Existing Conditions'!K30,'02-Existing Conditions'!N30="*",'02-Existing Conditions'!M30,'02-Existing Conditions'!P30="*",'02-Existing Conditions'!O30,'02-Existing Conditions'!R30="*",'02-Existing Conditions'!Q30,'02-Existing Conditions'!T30="*",'02-Existing Conditions'!S30,'02-Existing Conditions'!V30="*",'02-Existing Conditions'!U30),"")} -> 0 | H37: =G37/'Project Data'!$D$22 -> #VALUE!
A38: ='02-Existing Conditions'!A31 -> 0 | B38: ='02-Existing Conditions'!B31 -> 02 24 23 Chemical Sampling and Analysis of Soils | D38: {=_xlfn.IFNA(_xlfn.IFS('02-Existing Conditions'!D31="*",'02-Existing Conditions'!C31,'02-Existing Conditions'!F31="*",'02-Existing Conditions'!E31,'02-Existing Conditions'!H31="*",'02-Existing Conditions'!G31,'02-Existing Conditions'!J31="*",'02-Existing Conditions'!I31,'02-Existing Conditions'!L31="*",'02-Existing Conditions'!K31,'02-Existing Conditions'!N31="*",'02-Existing Conditions'!M31,'02-Existing Conditions'!P31="*",'02-Existing Conditions'!O31,'02-Existing Conditions'!R31="*",'02-Existing Conditions'!Q31,'02-Existing Conditions'!T31="*",'02-Existing Conditions'!S31),"")} -> 0 | E38: =D38/'Project Data'!$D$22 -> 0 | F38: 0 | G38: {=_xlfn.IFNA(_xlfn.IFS('02-Existing Conditions'!F31="*",'02-Existing Conditions'!E31,'02-Existing Conditions'!H31="*",'02-Existing Conditions'!G31,'02-Existing Conditions'!J31="*",'02-Existing Conditions'!I31,'02-Existing Conditions'!L31="*",'02-Existing Conditions'!K31,'02-Existing Conditions'!N31="*",'02-Existing Conditions'!M31,'02-Existing Conditions'!P31="*",'02-Existing Conditions'!O31,'02-Existing Conditions'!R31="*",'02-Existing Conditions'!Q31,'02-Existing Conditions'!T31="*",'02-Existing Conditions'!S31,'02-Existing Conditions'!V31="*",'02-Existing Conditions'!U31),"")} -> 0 | H38: =G38/'Project Data'!$D$22 -> #VALUE!
A39: ='02-Existing Conditions'!A32 -> 0 | B39: ='02-Existing Conditions'!B32 -> 02 25 00 Existing Material Assessment | D39: {=_xlfn.IFNA(_xlfn.IFS('02-Existing Conditions'!D32="*",'02-Existing Conditions'!C32,'02-Existing Conditions'!F32="*",'02-Existing Conditions'!E32,'02-Existing Conditions'!H32="*",'02-Existing Conditions'!G32,'02-Existing Conditions'!J32="*",'02-Existing Conditions'!I32,'02-Existing Conditions'!L32="*",'02-Existing Conditions'!K32,'02-Existing Conditions'!N32="*",'02-Existing Conditions'!M32,'02-Existing Conditions'!P32="*",'02-Existing Conditions'!O32,'02-Existing Conditions'!R32="*",'02-Existing Conditions'!Q32,'02-Existing Conditions'!T32="*",'02-Existing Conditions'!S32),"")} -> 0 | E39: =D39/'Project Data'!$D$22 -> 0 | F39: 0 | G39: {=_xlfn.IFNA(_xlfn.IFS('02-Existing Conditions'!F32="*",'02-Existing Conditions'!E32,'02-Existing Conditions'!H32="*",'02-Existing Conditions'!G32,'02-Existing Conditions'!J32="*",'02-Existing Conditions'!I32,'02-Existing Conditions'!L32="*",'02-Existing Conditions'!K32,'02-Existing Conditions'!N32="*",'02-Existing Conditions'!M32,'02-Existing Conditions'!P32="*",'02-Existing Conditions'!O32,'02-Existing Conditions'!R32="*",'02-Existing Conditions'!Q32,'02-Existing Conditions'!T32="*",'02-Existing Conditions'!S32,'02-Existing Conditions'!V32="*",'02-Existing Conditions'!U32),"")} -> 0 | H39: =G39/'Project Data'!$D$22 -> #VALUE!
A40: ='02-Existing Conditions'!A33 -> 0 | B40: ='02-Existing Conditions'!B33 -> 02 26 00 Hazardous Material Assessment | D40: {=_xlfn.IFNA(_xlfn.IFS('02-Existing Conditions'!D33="*",'02-Existing Conditions'!C33,'02-Existing Conditions'!F33="*",'02-Existing Conditions'!E33,'02-Existing Conditions'!H33="*",'02-Existing Conditions'!G33,'02-Existing Conditions'!J33="*",'02-Existing Conditions'!I33,'02-Existing Conditions'!L33="*",'02-Existing Conditions'!K33,'02-Existing Conditions'!N33="*",'02-Existing Conditions'!M33,'02-Existing Conditions'!P33="*",'02-Existing Conditions'!O33,'02-Existing Conditions'!R33="*",'02-Existing Conditions'!Q33,'02-Existing Conditions'!T33="*",'02-Existing Conditions'!S33),"")} -> 0 | E40: =D40/'Project Data'!$D$22 -> 0 | F40: 0 | G40: {=_xlfn.IFNA(_xlfn.IFS('02-Existing Conditions'!F33="*",'02-Existing Conditions'!E33,'02-Existing Conditions'!H33="*",'02-Existing Conditions'!G33,'02-Existing Conditions'!J33="*",'02-Existing Conditions'!I33,'02-Existing Conditions'!L33="*",'02-Existing Conditions'!K33,'02-Existing Conditions'!N33="*",'02-Existing Conditions'!M33,'02-Existing Conditions'!P33="*",'02-Existing Conditions'!O33,'02-Existing Conditions'!R33="*",'02-Existing Conditions'!Q33,'02-Existing Conditions'!T33="*",'02-Existing Conditions'!S33,'02-Existing Conditions'!V33="*",'02-Existing Conditions'!U33),"")} -> 0 | H40: =G40/'Project Data'!$D$22 -> #VALUE!
A41: ='02-Existing Conditions'!A34 -> 0 | B41: ='02-Existing Conditions'!B34 -> 02 26 23 Asbestos Assessment | D41: {=_xlfn.IFNA(_xlfn.IFS('02-Existing Conditions'!D34="*",'02-Existing Conditions'!C34,'02-Existing Conditions'!F34="*",'02-Existing Conditions'!E34,'02-Existing Conditions'!H34="*",'02-Existing Conditions'!G34,'02-Existing Conditions'!J34="*",'02-Existing Conditions'!I34,'02-Existing Conditions'!L34="*",'02-Existing Conditions'!K34,'02-Existing Conditions'!N34="*",'02-Existing Conditions'!M34,'02-Existing Conditions'!P34="*",'02-Existing Conditions'!O34,'02-Existing Conditions'!R34="*",'02-Existing Conditions'!Q34,'02-Existing Conditions'!T34="*",'02-Existing Conditions'!S34),"")} -> 0 | E41: =D41/'Project Data'!$D$22 -> 0 | F41: 0 | G41: {=_xlfn.IFNA(_xlfn.IFS('02-Existing Conditions'!F34="*",'02-Existing Conditions'!E34,'02-Existing Conditions'!H34="*",'02-Existing Conditions'!G34,'02-Existing Conditions'!J34="*",'02-Existing Conditions'!I34,'02-Existing Conditions'!L34="*",'02-Existing Conditions'!K34,'02-Existing Conditions'!N34="*",'02-Existing Conditions'!M34,'02-Existing Conditions'!P34="*",'02-Existing Conditions'!O34,'02-Existing Conditions'!R34="*",'02-Existing Conditions'!Q34,'02-Existing Conditions'!T34="*",'02-Existing Conditions'!S34,'02-Existing Conditions'!V34="*",'02-Existing Conditions'!U34),"")} -> 0 | H41: =G41/'Project Data'!$D$22 -> #VALUE!
A42: ='02-Existing Conditions'!A35 -> 0 | B42: ='02-Existing Conditions'!B35 -> 02 26 26 Lead Assessment | D42: {=_xlfn.IFNA(_xlfn.IFS('02-Existing Conditions'!D35="*",'02-Existing Conditions'!C35,'02-Existing Conditions'!F35="*",'02-Existing Conditions'!E35,'02-Existing Conditions'!H35="*",'02-Existing Conditions'!G35,'02-Existing Conditions'!J35="*",'02-Existing Conditions'!I35,'02-Existing Conditions'!L35="*",'02-Existing Conditions'!K35,'02-Existing Conditions'!N35="*",'02-Existing Conditions'!M35,'02-Existing Conditions'!P35="*",'02-Existing Conditions'!O35,'02-Existing Conditions'!R35="*",'02-Existing Conditions'!Q35,'02-Existing Conditions'!T35="*",'02-Existing Conditions'!S35),"")} -> 0 | E42: =D42/'Project Data'!$D$22 -> 0 | F42: 0 | G42: {=_xlfn.IFNA(_xlfn.IFS('02-Existing Conditions'!F35="*",'02-Existing Conditions'!E35,'02-Existing Conditions'!H35="*",'02-Existing Conditions'!G35,'02-Existing Conditions'!J35="*",'02-Existing Conditions'!I35,'02-Existing Conditions'!L35="*",'02-Existing Conditions'!K35,'02-Existing Conditions'!N35="*",'02-Existing Conditions'!M35,'02-Existing Conditions'!P35="*",'02-Existing Conditions'!O35,'02-Existing Conditions'!R35="*",'02-Existing Conditions'!Q35,'02-Existing Conditions'!T35="*",'02-Existing Conditions'!S35,'02-Existing Conditions'!V35="*",'02-Existing Conditions'!U35),"")} -> 0 | H42: =G42/'Project Data'!$D$22 -> #VALUE!
A43: ='02-Existing Conditions'!A36 -> 1 | B43: ='02-Existing Conditions'!B36 -> 02 26 33.13 Final Cleaning | D43: ='02-Existing Conditions'!E36 -> 41700 | E43: =D43/'Project Data'!$D$22 -> 0.46596864 | F43: 0 | G43: {=_xlfn.IFNA(_xlfn.IFS('02-Existing Conditions'!F36="*",'02-Existing Conditions'!E36,'02-Existing Conditions'!H36="*",'02-Existing Conditions'!G36,'02-Existing Conditions'!J36="*",'02-Existing Conditions'!I36,'02-Existing Conditions'!L36="*",'02-Existing Conditions'!K36,'02-Existing Conditions'!N36="*",'02-Existing Conditions'!M36,'02-Existing Conditions'!P36="*",'02-Existing Conditions'!O36,'02-Existing Conditions'!R36="*",'02-Existing Conditions'!Q36,'02-Existing Conditions'!T36="*",'02-Existing Conditions'!S36,'02-Existing Conditions'!V36="*",'02-Existing Conditions'!U36),"")} -> 0 | H43: =G43/'Project Data'!$D$22 -> #VALUE! | K43: Florida Construction Cleanup
A44: ='02-Existing Conditions'!A37 -> 0 | B44: ='02-Existing Conditions'!B37 -> 02 26 36 Hazardous Waste Drum Assessment | D44: {=_xlfn.IFNA(_xlfn.IFS('02-Existing Conditions'!D37="*",'02-Existing Conditions'!C37,'02-Existing Conditions'!F37="*",'02-Existing Conditions'!E37,'02-Existing Conditions'!H37="*",'02-Existing Conditions'!G37,'02-Existing Conditions'!J37="*",'02-Existing Conditions'!I37,'02-Existing Conditions'!L37="*",'02-Existing Conditions'!K37,'02-Existing Conditions'!N37="*",'02-Existing Conditions'!M37,'02-Existing Conditions'!P37="*",'02-Existing Conditions'!O37,'02-Existing Conditions'!R37="*",'02-Existing Conditions'!Q37,'02-Existing Conditions'!T37="*",'02-Existing Conditions'!S37),"")} -> 0 | E44: =D44/'Project Data'!$D$22 -> 0 | F44: 0 | G44: {=_xlfn.IFNA(_xlfn.IFS('02-Existing Conditions'!F37="*",'02-Existing Conditions'!E37,'02-Existing Conditions'!H37="*",'02-Existing Conditions'!G37,'02-Existing Conditions'!J37="*",'02-Existing Conditions'!I37,'02-Existing Conditions'!L37="*",'02-Existing Conditions'!K37,'02-Existing Conditions'!N37="*",'02-Existing Conditions'!M37,'02-Existing Conditions'!P37="*",'02-Existing Conditions'!O37,'02-Existing Conditions'!R37="*",'02-Existing Conditions'!Q37,'02-Existing Conditions'!T37="*",'02-Existing Conditions'!S37,'02-Existing Conditions'!V37="*",'02-Existing Conditions'!U37),"")} -> 0 | H44: =G44/'Project Data'!$D$22 -> #VALUE!
A45: ='02-Existing Conditions'!A38 -> 0 | B45: ='02-Existing Conditions'!B38 -> 02 30 00 Subsurface Investigation | D45: {=_xlfn.IFNA(_xlfn.IFS('02-Existing Conditions'!D38="*",'02-Existing Conditions'!C38,'02-Existing Conditions'!F38="*",'02-Existing Conditions'!E38,'02-Existing Conditions'!H38="*",'02-Existing Conditions'!G38,'02-Existing Conditions'!J38="*",'02-Existing Conditions'!I38,'02-Existing Conditions'!L38="*",'02-Existing Conditions'!K38,'02-Existing Conditions'!N38="*",'02-Existing Conditions'!M38,'02-Existing Conditions'!P38="*",'02-Existing Conditions'!O38,'02-Existing Conditions'!R38="*",'02-Existing Conditions'!Q38,'02-Existing Conditions'!T38="*",'02-Existing Conditions'!S38),"")} -> 0 | E45: =D45/'Project Data'!$D$22 -> 0 | F45: 0 | G45: {=_xlfn.IFNA(_xlfn.IFS('02-Existing Conditions'!F38="*",'02-Existing Conditions'!E38,'02-Existing Conditions'!H38="*",'02-Existing Conditions'!G38,'02-Existing Conditions'!J38="*",'02-Existing Conditions'!I38,'02-Existing Conditions'!L38="*",'02-Existing Conditions'!K38,'02-Existing Conditions'!N38="*",'02-Existing Conditions'!M38,'02-Existing Conditions'!P38="*",'02-Existing Conditions'!O38,'02-Existing Conditions'!R38="*",'02-Existing Conditions'!Q38,'02-Existing Conditions'!T38="*",'02-Existing Conditions'!S38,'02-Existing Conditions'!V38="*",'02-Existing Conditions'!U38),"")} -> 0 | H45: =G45/'Project Data'!$D$22 -> #VALUE!
A46: ='02-Existing Conditions'!A39 -> 0 | B46: ='02-Existing Conditions'!B39 -> 02 32 13 Subsurface Drilling and Sampling | D46: {=_xlfn.IFNA(_xlfn.IFS('02-Existing Conditions'!D39="*",'02-Existing Conditions'!C39,'02-Existing Conditions'!F39="*",'02-Existing Conditions'!E39,'02-Existing Conditions'!H39="*",'02-Existing Conditions'!G39,'02-Existing Conditions'!J39="*",'02-Existing Conditions'!I39,'02-Existing Conditions'!L39="*",'02-Existing Conditions'!K39,'02-Existing Conditions'!N39="*",'02-Existing Conditions'!M39,'02-Existing Conditions'!P39="*",'02-Existing Conditions'!O39,'02-Existing Conditions'!R39="*",'02-Existing Conditions'!Q39,'02-Existing Conditions'!T39="*",'02-Existing Conditions'!S39),"")} -> 0 | E46: =D46/'Project Data'!$D$22 -> 0 | F46: 0 | G46: {=_xlfn.IFNA(_xlfn.IFS('02-Existing Conditions'!F39="*",'02-Existing Conditions'!E39,'02-Existing Conditions'!H39="*",'02-Existing Conditions'!G39,'02-Existing Conditions'!J39="*",'02-Existing Conditions'!I39,'02-Existing Conditions'!L39="*",'02-Existing Conditions'!K39,'02-Existing Conditions'!N39="*",'02-Existing Conditions'!M39,'02-Existing Conditions'!P39="*",'02-Existing Conditions'!O39,'02-Existing Conditions'!R39="*",'02-Existing Conditions'!Q39,'02-Existing Conditions'!T39="*",'02-Existing Conditions'!S39,'02-Existing Conditions'!V39="*",'02-Existing Conditions'!U39),"")} -> 0 | H46: =G46/'Project Data'!$D$22 -> #VALUE!
A47: ='02-Existing Conditions'!A40 -> 1 | B47: ='02-Existing Conditions'!B40 -> 02 32 16 Material Testing & Threshold Inspections | D47: ='02-Existing Conditions'!E40 -> 21238 | E47: =D47/'Project Data'!$D$22 -> 0.23731995 | F47: 0 | G47: {=_xlfn.IFNA(_xlfn.IFS('02-Existing Conditions'!F40="*",'02-Existing Conditions'!E40,'02-Existing Conditions'!H40="*",'02-Existing Conditions'!G40,'02-Existing Conditions'!J40="*",'02-Existing Conditions'!I40,'02-Existing Conditions'!L40="*",'02-Existing Conditions'!K40,'02-Existing Conditions'!N40="*",'02-Existing Conditions'!M40,'02-Existing Conditions'!P40="*",'02-Existing Conditions'!O40,'02-Existing Conditions'!R40="*",'02-Existing Conditions'!Q40,'02-Existing Conditions'!T40="*",'02-Existing Conditions'!S40,'02-Existing Conditions'!V40="*",'02-Existing Conditions'!U40),"")} -> 0 | H47: =G47/'Project Data'!$D$22 -> #VALUE! | K47: Pacson
A48: ='02-Existing Conditions'!A41 -> 0 | B48: ='02-Existing Conditions'!B41 -> 02 32 19 Exploratory Excavations | D48: {=_xlfn.IFNA(_xlfn.IFS('02-Existing Conditions'!D41="*",'02-Existing Conditions'!C41,'02-Existing Conditions'!F41="*",'02-Existing Conditions'!E41,'02-Existing Conditions'!H41="*",'02-Existing Conditions'!G41,'02-Existing Conditions'!J41="*",'02-Existing Conditions'!I41,'02-Existing Conditions'!L41="*",'02-Existing Conditions'!K41,'02-Existing Conditions'!N41="*",'02-Existing Conditions'!M41,'02-Existing Conditions'!P41="*",'02-Existing Conditions'!O41,'02-Existing Conditions'!R41="*",'02-Existing Conditions'!Q41,'02-Existing Conditions'!T41="*",'02-Existing Conditions'!S41),"")} -> 0 | E48: =D48/'Project Data'!$D$22 -> 0 | F48: 0 | G48: {=_xlfn.IFNA(_xlfn.IFS('02-Existing Conditions'!F41="*",'02-Existing Conditions'!E41,'02-Existing Conditions'!H41="*",'02-Existing Conditions'!G41,'02-Existing Conditions'!J41="*",'02-Existing Conditions'!I41,'02-Existing Conditions'!L41="*",'02-Existing Conditions'!K41,'02-Existing Conditions'!N41="*",'02-Existing Conditions'!M41,'02-Existing Conditions'!P41="*",'02-Existing Conditions'!O41,'02-Existing Conditions'!R41="*",'02-Existing Conditions'!Q41,'02-Existing Conditions'!T41="*",'02-Existing Conditions'!S41,'02-Existing Conditions'!V41="*",'02-Existing Conditions'!U41),"")} -> 0 | H48: =G48/'Project Data'!$D$22 -> #VALUE!
A49: 1 | B49: Div. 02 42 - Demolition | D49: =SUM(D51:D54) -> 503586 | E49: =D49/'Project Data'!$D$22 -> 5.6272251 | F49: 503586 | G49: {=_xlfn.IFNA(_xlfn.IFS('02-41-Demolition'!F9="*",'02-41-Demolition'!E9,'02-41-Demolition'!H9="*",'02-41-Demolition'!G9,'02-41-Demolition'!J9="*",'02-41-Demolition'!I9,'02-41-Demolition'!L9="*",'02-41-Demolition'!K9,'02-41-Demolition'!N9="*",'02-41-Demolition'!M9,'02-41-Demolition'!P9="*",'02-41-Demolition'!O9,'02-41-Demolition'!R9="*",'02-41-Demolition'!Q9,'02-41-Demolition'!T9="*",'02-41-Demolition'!S9,'02-41-Demolition'!V9="*",'02-41-Demolition'!U9),"")} -> 503586 | H49: =G49/'Project Data'!$D$22 -> 5.6272251 | J49: =IFERROR(G49-F49, "--") -> 0
A50: ='02-41-Demolition'!A11 -> 0 | B50: ='02-41-Demolition'!B11 -> 02 41 00 Demolition | D50: {=_xlfn.IFNA(_xlfn.IFS('02-41-Demolition'!D11="*",'02-41-Demolition'!C11,'02-41-Demolition'!F11="*",'02-41-Demolition'!E11,'02-41-Demolition'!H11="*",'02-41-Demolition'!G11,'02-41-Demolition'!J11="*",'02-41-Demolition'!I11,'02-41-Demolition'!L11="*",'02-41-Demolition'!K11,'02-41-Demolition'!N11="*",'02-41-Demolition'!M11,'02-41-Demolition'!P11="*",'02-41-Demolition'!O11,'02-41-Demolition'!R11="*",'02-41-Demolition'!Q11,'02-41-Demolition'!T11="*",'02-41-Demolition'!S11),"")} | E50: =D50/'Project Data'!$D$22 -> #VALUE! | G50: {=_xlfn.IFNA(_xlfn.IFS('02-41-Demolition'!F11="*",'02-41-Demolition'!E11,'02-41-Demolition'!H11="*",'02-41-Demolition'!G11,'02-41-Demolition'!J11="*",'02-41-Demolition'!I11,'02-41-Demolition'!L11="*",'02-41-Demolition'!K11,'02-41-Demolition'!N11="*",'02-41-Demolition'!M11,'02-41-Demolition'!P11="*",'02-41-Demolition'!O11,'02-41-Demolition'!R11="*",'02-41-Demolition'!Q11,'02-41-Demolition'!T11="*",'02-41-Demolition'!S11,'02-41-Demolition'!V11="*",'02-41-Demolition'!U11),"")} | H50: =G50/'Project Data'!$D$22 -> #VALUE!
A51: ='02-41-Demolition'!A12 -> 1 | B51: ='02-41-Demolition'!B12 -> 02 41 13 Selective Site Demolition | D51: {=_xlfn.IFNA(_xlfn.IFS('02-41-Demolition'!D12="*",'02-41-Demolition'!C12,'02-41-Demolition'!F12="*",'02-41-Demolition'!E12,'02-41-Demolition'!H12="*",'02-41-Demolition'!G12,'02-41-Demolition'!J12="*",'02-41-Demolition'!I12,'02-41-Demolition'!L12="*",'02-41-Demolition'!K12,'02-41-Demolition'!N12="*",'02-41-Demolition'!M12,'02-41-Demolition'!P12="*",'02-41-Demolition'!O12,'02-41-Demolition'!R12="*",'02-41-Demolition'!Q12,'02-41-Demolition'!T12="*",'02-41-Demolition'!S12),"")} -> 153586 | E51: =D51/'Project Data'!$D$22 -> 1.7162173 | F51: 153586 | G51: {=_xlfn.IFNA(_xlfn.IFS('02-41-Demolition'!F12="*",'02-41-Demolition'!E12,'02-41-Demolition'!H12="*",'02-41-Demolition'!G12,'02-41-Demolition'!J12="*",'02-41-Demolition'!I12,'02-41-Demolition'!L12="*",'02-41-Demolition'!K12,'02-41-Demolition'!N12="*",'02-41-Demolition'!M12,'02-41-Demolition'!P12="*",'02-41-Demolition'!O12,'02-41-Demolition'!R12="*",'02-41-Demolition'!Q12,'02-41-Demolition'!T12="*",'02-41-Demolition'!S12,'02-41-Demolition'!V12="*",'02-41-Demolition'!U12),"")} -> 153586 | H51: =G51/'Project Data'!$D$22 -> 1.7162173 | K51: DHC
A52: ='02-41-Demolition'!A13 | B52: ='02-41-Demolition'!B13 -> 02 41 13.13 Paving Removal | D52: {=_xlfn.IFNA(_xlfn.IFS('02-41-Demolition'!D13="*",'02-41-Demolition'!C13,'02-41-Demolition'!F13="*",'02-41-Demolition'!E13,'02-41-Demolition'!H13="*",'02-41-Demolition'!G13,'02-41-Demolition'!J13="*",'02-41-Demolition'!I13,'02-41-Demolition'!L13="*",'02-41-Demolition'!K13,'02-41-Demolition'!N13="*",'02-41-Demolition'!M13,'02-41-Demolition'!P13="*",'02-41-Demolition'!O13,'02-41-Demolition'!R13="*",'02-41-Demolition'!Q13,'02-41-Demolition'!T13="*",'02-41-Demolition'!S13),"")} | E52: =D52/'Project Data'!$D$22 -> #VALUE! | G52: {=_xlfn.IFNA(_xlfn.IFS('02-41-Demolition'!F13="*",'02-41-Demolition'!E13,'02-41-Demolition'!H13="*",'02-41-Demolition'!G13,'02-41-Demolition'!J13="*",'02-41-Demolition'!I13,'02-41-Demolition'!L13="*",'02-41-Demolition'!K13,'02-41-Demolition'!N13="*",'02-41-Demolition'!M13,'02-41-Demolition'!P13="*",'02-41-Demolition'!O13,'02-41-Demolition'!R13="*",'02-41-Demolition'!Q13,'02-41-Demolition'!T13="*",'02-41-Demolition'!S13,'02-41-Demolition'!V13="*",'02-41-Demolition'!U13),"")} | H52: =G52/'Project Data'!$D$22 -> #VALUE!
A53: ='02-41-Demolition'!A14 | B53: ='02-41-Demolition'!B14 -> 02 41 13.23 Utility Line Removal | D53: {=_xlfn.IFNA(_xlfn.IFS('02-41-Demolition'!D14="*",'02-41-Demolition'!C14,'02-41-Demolition'!F14="*",'02-41-Demolition'!E14,'02-41-Demolition'!H14="*",'02-41-Demolition'!G14,'02-41-Demolition'!J14="*",'02-41-Demolition'!I14,'02-41-Demolition'!L14="*",'02-41-Demolition'!K14,'02-41-Demolition'!N14="*",'02-41-Demolition'!M14,'02-41-Demolition'!P14="*",'02-41-Demolition'!O14,'02-41-Demolition'!R14="*",'02-41-Demolition'!Q14,'02-41-Demolition'!T14="*",'02-41-Demolition'!S14),"")} | E53: =D53/'Project Data'!$D$22 -> #VALUE! | G53: {=_xlfn.IFNA(_xlfn.IFS('02-41-Demolition'!F14="*",'02-41-Demolition'!E14,'02-41-Demolition'!H14="*",'02-41-Demolition'!G14,'02-41-Demolition'!J14="*",'02-41-Demolition'!I14,'02-41-Demolition'!L14="*",'02-41-Demolition'!K14,'02-41-Demolition'!N14="*",'02-41-Demolition'!M14,'02-41-Demolition'!P14="*",'02-41-Demolition'!O14,'02-41-Demolition'!R14="*",'02-41-Demolition'!Q14,'02-41-Demolition'!T14="*",'02-41-Demolition'!S14,'02-41-Demolition'!V14="*",'02-41-Demolition'!U14),"")} | H53: =G53/'Project Data'!$D$22 -> #VALUE!
A54: ='02-41-Demolition'!A15 -> 1 | B54: ='02-41-Demolition'!B15 -> 02 41 13.33 Shoring Allowance | D54: {=_xlfn.IFNA(_xlfn.IFS('02-41-Demolition'!D15="*",'02-41-Demolition'!C15,'02-41-Demolition'!F15="*",'02-41-Demolition'!E15,'02-41-Demolition'!H15="*",'02-41-Demolition'!G15,'02-41-Demolition'!J15="*",'02-41-Demolition'!I15,'02-41-Demolition'!L15="*",'02-41-Demolition'!K15,'02-41-Demolition'!N15="*",'02-41-Demolition'!M15,'02-41-Demolition'!P15="*",'02-41-Demolition'!O15,'02-41-Demolition'!R15="*",'02-41-Demolition'!Q15,'02-41-Demolition'!T15="*",'02-41-Demolition'!S15),"")} -> 350000 | E54: =D54/'Project Data'!$D$22 -> 3.9110078 | F54: 350000 | G54: {=_xlfn.IFNA(_xlfn.IFS('02-41-Demolition'!F15="*",'02-41-Demolition'!E15,'02-41-Demolition'!H15="*",'02-41-Demolition'!G15,'02-41-Demolition'!J15="*",'02-41-Demolition'!I15,'02-41-Demolition'!L15="*",'02-41-Demolition'!K15,'02-41-Demolition'!N15="*",'02-41-Demolition'!M15,'02-41-Demolition'!P15="*",'02-41-Demolition'!O15,'02-41-Demolition'!R15="*",'02-41-Demolition'!Q15,'02-41-Demolition'!T15="*",'02-41-Demolition'!S15,'02-41-Demolition'!V15="*",'02-41-Demolition'!U15),"")} -> 350000 | H54: =G54/'Project Data'!$D$22 -> 3.9110078 | K54: Allowance
A55: ='02-41-Demolition'!A16 | B55: ='02-41-Demolition'!B16 -> 02 41 16 Structure Demolition | D55: {=_xlfn.IFNA(_xlfn.IFS('02-41-Demolition'!D16="*",'02-41-Demolition'!C16,'02-41-Demolition'!F16="*",'02-41-Demolition'!E16,'02-41-Demolition'!H16="*",'02-41-Demolition'!G16,'02-41-Demolition'!J16="*",'02-41-Demolition'!I16,'02-41-Demolition'!L16="*",'02-41-Demolition'!K16,'02-41-Demolition'!N16="*",'02-41-Demolition'!M16,'02-41-Demolition'!P16="*",'02-41-Demolition'!O16,'02-41-Demolition'!R16="*",'02-41-Demolition'!Q16,'02-41-Demolition'!T16="*",'02-41-Demolition'!S16),"")} | E55: =D55/'Project Data'!$D$22 -> #VALUE! | G55: {=_xlfn.IFNA(_xlfn.IFS('02-41-Demolition'!F16="*",'02-41-Demolition'!E16,'02-41-Demolition'!H16="*",'02-41-Demolition'!G16,'02-41-Demolition'!J16="*",'02-41-Demolition'!I16,'02-41-Demolition'!L16="*",'02-41-Demolition'!K16,'02-41-Demolition'!N16="*",'02-41-Demolition'!M16,'02-41-Demolition'!P16="*",'02-41-Demolition'!O16,'02-41-Demolition'!R16="*",'02-41-Demolition'!Q16,'02-41-Demolition'!T16="*",'02-41-Demolition'!S16,'02-41-Demolition'!V16="*",'02-41-Demolition'!U16),"")} | H55: =G55/'Project Data'!$D$22 -> #VALUE!
A56: ='02-41-Demolition'!A17 | B56: ='02-41-Demolition'!B17 -> 02 41 16.13 Building Demolition | D56: {=_xlfn.IFNA(_xlfn.IFS('02-41-Demolition'!D17="*",'02-41-Demolition'!C17,'02-41-Demolition'!F17="*",'02-41-Demolition'!E17,'02-41-Demolition'!H17="*",'02-41-Demolition'!G17,'02-41-Demolition'!J17="*",'02-41-Demolition'!I17,'02-41-Demolition'!L17="*",'02-41-Demolition'!K17,'02-41-Demolition'!N17="*",'02-41-Demolition'!M17,'02-41-Demolition'!P17="*",'02-41-Demolition'!O17,'02-41-Demolition'!R17="*",'02-41-Demolition'!Q17,'02-41-Demolition'!T17="*",'02-41-Demolition'!S17),"")} | E56: =D56/'Project Data'!$D$22 -> #VALUE! | G56: {=_xlfn.IFNA(_xlfn.IFS('02-41-Demolition'!F17="*",'02-41-Demolition'!E17,'02-41-Demolition'!H17="*",'02-41-Demolition'!G17,'02-41-Demolition'!J17="*",'02-41-Demolition'!I17,'02-41-Demolition'!L17="*",'02-41-Demolition'!K17,'02-41-Demolition'!N17="*",'02-41-Demolition'!M17,'02-41-Demolition'!P17="*",'02-41-Demolition'!O17,'02-41-Demolition'!R17="*",'02-41-Demolition'!Q17,'02-41-Demolition'!T17="*",'02-41-Demolition'!S17,'02-41-Demolition'!V17="*",'02-41-Demolition'!U17),"")} | H56: =G56/'Project Data'!$D$22 -> #VALUE!
A57: ='02-41-Demolition'!A18 -> 0 | B57: ='02-41-Demolition'!B18 -> 02 41 16.23 Tower Demolition | D57: {=_xlfn.IFNA(_xlfn.IFS('02-41-Demolition'!D18="*",'02-41-Demolition'!C18,'02-41-Demolition'!F18="*",'02-41-Demolition'!E18,'02-41-Demolition'!H18="*",'02-41-Demolition'!G18,'02-41-Demolition'!J18="*",'02-41-Demolition'!I18,'02-41-Demolition'!L18="*",'02-41-Demolition'!K18,'02-41-Demolition'!N18="*",'02-41-Demolition'!M18,'02-41-Demolition'!P18="*",'02-41-Demolition'!O18,'02-41-Demolition'!R18="*",'02-41-Demolition'!Q18,'02-41-Demolition'!T18="*",'02-41-Demolition'!S18),"")} | E57: =D57/'Project Data'!$D$22 -> #VALUE! | G57: {=_xlfn.IFNA(_xlfn.IFS('02-41-Demolition'!F18="*",'02-41-Demolition'!E18,'02-41-Demolition'!H18="*",'02-41-Demolition'!G18,'02-41-Demolition'!J18="*",'02-41-Demolition'!I18,'02-41-Demolition'!L18="*",'02-41-Demolition'!K18,'02-41-Demolition'!N18="*",'02-41-Demolition'!M18,'02-41-Demolition'!P18="*",'02-41-Demolition'!O18,'02-41-Demolition'!R18="*",'02-41-Demolition'!Q18,'02-41-Demolition'!T18="*",'02-41-Demolition'!S18,'02-41-Demolition'!V18="*",'02-41-Demolition'!U18),"")} | H57: =G57/'Project Data'!$D$22 -> #VALUE!
A58: ='02-41-Demolition'!A19 -> 0 | B58: ='02-41-Demolition'!B19 -> 02 41 16.43 Dam Demolition | D58: {=_xlfn.IFNA(_xlfn.IFS('02-41-Demolition'!D19="*",'02-41-Demolition'!C19,'02-41-Demolition'!F19="*",'02-41-Demolition'!E19,'02-41-Demolition'!H19="*",'02-41-Demolition'!G19,'02-41-Demolition'!J19="*",'02-41-Demolition'!I19,'02-41-Demolition'!L19="*",'02-41-Demolition'!K19,'02-41-Demolition'!N19="*",'02-41-Demolition'!M19,'02-41-Demolition'!P19="*",'02-41-Demolition'!O19,'02-41-Demolition'!R19="*",'02-41-Demolition'!Q19,'02-41-Demolition'!T19="*",'02-41-Demolition'!S19),"")} | E58: =D58/'Project Data'!$D$22 -> #VALUE! | G58: {=_xlfn.IFNA(_xlfn.IFS('02-41-Demolition'!F19="*",'02-41-Demolition'!E19,'02-41-Demolition'!H19="*",'02-41-Demolition'!G19,'02-41-Demolition'!J19="*",'02-41-Demolition'!I19,'02-41-Demolition'!L19="*",'02-41-Demolition'!K19,'02-41-Demolition'!N19="*",'02-41-Demolition'!M19,'02-41-Demolition'!P19="*",'02-41-Demolition'!O19,'02-41-Demolition'!R19="*",'02-41-Demolition'!Q19,'02-41-Demolition'!T19="*",'02-41-Demolition'!S19,'02-41-Demolition'!V19="*",'02-41-Demolition'!U19),"")} | H58: =G58/'Project Data'!$D$22 -> #VALUE!
A59: ='02-41-Demolition'!A20 -> 0 | B59: ='02-41-Demolition'!B20 -> 02 41 19 Selective Demolition | D59: {=_xlfn.IFNA(_xlfn.IFS('02-41-Demolition'!D20="*",'02-41-Demolition'!C20,'02-41-Demolition'!F20="*",'02-41-Demolition'!E20,'02-41-Demolition'!H20="*",'02-41-Demolition'!G20,'02-41-Demolition'!J20="*",'02-41-Demolition'!I20,'02-41-Demolition'!L20="*",'02-41-Demolition'!K20,'02-41-Demolition'!N20="*",'02-41-Demolition'!M20,'02-41-Demolition'!P20="*",'02-41-Demolition'!O20,'02-41-Demolition'!R20="*",'02-41-Demolition'!Q20,'02-41-Demolition'!T20="*",'02-41-Demolition'!S20),"")} | E59: =D59/'Project Data'!$D$22 -> #VALUE! | G59: {=_xlfn.IFNA(_xlfn.IFS('02-41-Demolition'!F20="*",'02-41-Demolition'!E20,'02-41-Demolition'!H20="*",'02-41-Demolition'!G20,'02-41-Demolition'!J20="*",'02-41-Demolition'!I20,'02-41-Demolition'!L20="*",'02-41-Demolition'!K20,'02-41-Demolition'!N20="*",'02-41-Demolition'!M20,'02-41-Demolition'!P20="*",'02-41-Demolition'!O20,'02-41-Demolition'!R20="*",'02-41-Demolition'!Q20,'02-41-Demolition'!T20="*",'02-41-Demolition'!S20,'02-41-Demolition'!V20="*",'02-41-Demolition'!U20),"")} | H59: =G59/'Project Data'!$D$22 -> #VALUE!
A60: ='02-41-Demolition'!A21 -> 0 | B60: ='02-41-Demolition'!B21 -> 02 41 19.13 Selective Building Demolition | D60: {=_xlfn.IFNA(_xlfn.IFS('02-41-Demolition'!D21="*",'02-41-Demolition'!C21,'02-41-Demolition'!F21="*",'02-41-Demolition'!E21,'02-41-Demolition'!H21="*",'02-41-Demolition'!G21,'02-41-Demolition'!J21="*",'02-41-Demolition'!I21,'02-41-Demolition'!L21="*",'02-41-Demolition'!K21,'02-41-Demolition'!N21="*",'02-41-Demolition'!M21,'02-41-Demolition'!P21="*",'02-41-Demolition'!O21,'02-41-Demolition'!R21="*",'02-41-Demolition'!Q21,'02-41-Demolition'!T21="*",'02-41-Demolition'!S21),"")} | E60: =D60/'Project Data'!$D$22 -> #VALUE! | G60: {=_xlfn.IFNA(_xlfn.IFS('02-41-Demolition'!F21="*",'02-41-Demolition'!E21,'02-41-Demolition'!H21="*",'02-41-Demolition'!G21,'02-41-Demolition'!J21="*",'02-41-Demolition'!I21,'02-41-Demolition'!L21="*",'02-41-Demolition'!K21,'02-41-Demolition'!N21="*",'02-41-Demolition'!M21,'02-41-Demolition'!P21="*",'02-41-Demolition'!O21,'02-41-Demolition'!R21="*",'02-41-Demolition'!Q21,'02-41-Demolition'!T21="*",'02-41-Demolition'!S21,'02-41-Demolition'!V21="*",'02-41-Demolition'!U21),"")} | H60: =G60/'Project Data'!$D$22 -> #VALUE!
A61: ='02-41-Demolition'!A22 -> 0 | B61: ='02-41-Demolition'!B22 -> 02 41 19.16 Selective Interior Demolition | D61: {=_xlfn.IFNA(_xlfn.IFS('02-41-Demolition'!D22="*",'02-41-Demolition'!C22,'02-41-Demolition'!F22="*",'02-41-Demolition'!E22,'02-41-Demolition'!H22="*",'02-41-Demolition'!G22,'02-41-Demolition'!J22="*",'02-41-Demolition'!I22,'02-41-Demolition'!L22="*",'02-41-Demolition'!K22,'02-41-Demolition'!N22="*",'02-41-Demolition'!M22,'02-41-Demolition'!P22="*",'02-41-Demolition'!O22,'02-41-Demolition'!R22="*",'02-41-Demolition'!Q22,'02-41-Demolition'!T22="*",'02-41-Demolition'!S22),"")} | E61: =D61/'Project Data'!$D$22 -> #VALUE! | G61: {=_xlfn.IFNA(_xlfn.IFS('02-41-Demolition'!F22="*",'02-41-Demolition'!E22,'02-41-Demolition'!H22="*",'02-41-Demolition'!G22,'02-41-Demolition'!J22="*",'02-41-Demolition'!I22,'02-41-Demolition'!L22="*",'02-41-Demolition'!K22,'02-41-Demolition'!N22="*",'02-41-Demolition'!M22,'02-41-Demolition'!P22="*",'02-41-Demolition'!O22,'02-41-Demolition'!R22="*",'02-41-Demolition'!Q22,'02-41-Demolition'!T22="*",'02-41-Demolition'!S22,'02-41-Demolition'!V22="*",'02-41-Demolition'!U22),"")} | H61: =G61/'Project Data'!$D$22 -> #VALUE!
A62: ='02-41-Demolition'!A23 -> 0 | B62: ='02-41-Demolition'!B23 -> 02 42 13 Deconstruction of Structures | D62: {=_xlfn.IFNA(_xlfn.IFS('02-41-Demolition'!D23="*",'02-41-Demolition'!C23,'02-41-Demolition'!F23="*",'02-41-Demolition'!E23,'02-41-Demolition'!H23="*",'02-41-Demolition'!G23,'02-41-Demolition'!J23="*",'02-41-Demolition'!I23,'02-41-Demolition'!L23="*",'02-41-Demolition'!K23,'02-41-Demolition'!N23="*",'02-41-Demolition'!M23,'02-41-Demolition'!P23="*",'02-41-Demolition'!O23,'02-41-Demolition'!R23="*",'02-41-Demolition'!Q23,'02-41-Demolition'!T23="*",'02-41-Demolition'!S23),"")} | E62: =D62/'Project Data'!$D$22 -> #VALUE! | G62: {=_xlfn.IFNA(_xlfn.IFS('02-41-Demolition'!F23="*",'02-41-Demolition'!E23,'02-41-Demolition'!H23="*",'02-41-Demolition'!G23,'02-41-Demolition'!J23="*",'02-41-Demolition'!I23,'02-41-Demolition'!L23="*",'02-41-Demolition'!K23,'02-41-Demolition'!N23="*",'02-41-Demolition'!M23,'02-41-Demolition'!P23="*",'02-41-Demolition'!O23,'02-41-Demolition'!R23="*",'02-41-Demolition'!Q23,'02-41-Demolition'!T23="*",'02-41-Demolition'!S23,'02-41-Demolition'!V23="*",'02-41-Demolition'!U23),"")} | H62: =G62/'Project Data'!$D$22 -> #VALUE!
A63: ='02-41-Demolition'!A24 -> 0 | B63: ='02-41-Demolition'!B24 -> 02 42 19 Recycling of Construction Materials | D63: {=_xlfn.IFNA(_xlfn.IFS('02-41-Demolition'!D24="*",'02-41-Demolition'!C24,'02-41-Demolition'!F24="*",'02-41-Demolition'!E24,'02-41-Demolition'!H24="*",'02-41-Demolition'!G24,'02-41-Demolition'!J24="*",'02-41-Demolition'!I24,'02-41-Demolition'!L24="*",'02-41-Demolition'!K24,'02-41-Demolition'!N24="*",'02-41-Demolition'!M24,'02-41-Demolition'!P24="*",'02-41-Demolition'!O24,'02-41-Demolition'!R24="*",'02-41-Demolition'!Q24,'02-41-Demolition'!T24="*",'02-41-Demolition'!S24),"")} | E63: =D63/'Project Data'!$D$22 -> #VALUE! | G63: {=_xlfn.IFNA(_xlfn.IFS('02-41-Demolition'!F24="*",'02-41-Demolition'!E24,'02-41-Demolition'!H24="*",'02-41-Demolition'!G24,'02-41-Demolition'!J24="*",'02-41-Demolition'!I24,'02-41-Demolition'!L24="*",'02-41-Demolition'!K24,'02-41-Demolition'!N24="*",'02-41-Demolition'!M24,'02-41-Demolition'!P24="*",'02-41-Demolition'!O24,'02-41-Demolition'!R24="*",'02-41-Demolition'!Q24,'02-41-Demolition'!T24="*",'02-41-Demolition'!S24,'02-41-Demolition'!V24="*",'02-41-Demolition'!U24),"")} | H63: =G63/'Project Data'!$D$22 -> #VALUE!
A64: ='02-41-Demolition'!A25 -> 0 | B64: ='02-41-Demolition'!B25 -> 02 42 19.15 Concrete Recycling | D64: {=_xlfn.IFNA(_xlfn.IFS('02-41-Demolition'!D25="*",'02-41-Demolition'!C25,'02-41-Demolition'!F25="*",'02-41-Demolition'!E25,'02-41-Demolition'!H25="*",'02-41-Demolition'!G25,'02-41-Demolition'!J25="*",'02-41-Demolition'!I25,'02-41-Demolition'!L25="*",'02-41-Demolition'!K25,'02-41-Demolition'!N25="*",'02-41-Demolition'!M25,'02-41-Demolition'!P25="*",'02-41-Demolition'!O25,'02-41-Demolition'!R25="*",'02-41-Demolition'!Q25,'02-41-Demolition'!T25="*",'02-41-Demolition'!S25),"")} | E64: =D64/'Project Data'!$D$22 -> #VALUE! | G64: {=_xlfn.IFNA(_xlfn.IFS('02-41-Demolition'!F25="*",'02-41-Demolition'!E25,'02-41-Demolition'!H25="*",'02-41-Demolition'!G25,'02-41-Demolition'!J25="*",'02-41-Demolition'!I25,'02-41-Demolition'!L25="*",'02-41-Demolition'!K25,'02-41-Demolition'!N25="*",'02-41-Demolition'!M25,'02-41-Demolition'!P25="*",'02-41-Demolition'!O25,'02-41-Demolition'!R25="*",'02-41-Demolition'!Q25,'02-41-Demolition'!T25="*",'02-41-Demolition'!S25,'02-41-Demolition'!V25="*",'02-41-Demolition'!U25),"")} | H64: =G64/'Project Data'!$D$22 -> #VALUE!
A65: ='02-41-Demolition'!A26 -> 0 | B65: ='02-41-Demolition'!B26 -> 02 42 19.17 Masonry Recycling | D65: {=_xlfn.IFNA(_xlfn.IFS('02-41-Demolition'!D26="*",'02-41-Demolition'!C26,'02-41-Demolition'!F26="*",'02-41-Demolition'!E26,'02-41-Demolition'!H26="*",'02-41-Demolition'!G26,'02-41-Demolition'!J26="*",'02-41-Demolition'!I26,'02-41-Demolition'!L26="*",'02-41-Demolition'!K26,'02-41-Demolition'!N26="*",'02-41-Demolition'!M26,'02-41-Demolition'!P26="*",'02-41-Demolition'!O26,'02-41-Demolition'!R26="*",'02-41-Demolition'!Q26,'02-41-Demolition'!T26="*",'02-41-Demolition'!S26),"")} | E65: =D65/'Project Data'!$D$22 -> #VALUE! | G65: {=_xlfn.IFNA(_xlfn.IFS('02-41-Demolition'!F26="*",'02-41-Demolition'!E26,'02-41-Demolition'!H26="*",'02-41-Demolition'!G26,'02-41-Demolition'!J26="*",'02-41-Demolition'!I26,'02-41-Demolition'!L26="*",'02-41-Demolition'!K26,'02-41-Demolition'!N26="*",'02-41-Demolition'!M26,'02-41-Demolition'!P26="*",'02-41-Demolition'!O26,'02-41-Demolition'!R26="*",'02-41-Demolition'!Q26,'02-41-Demolition'!T26="*",'02-41-Demolition'!S26,'02-41-Demolition'!V26="*",'02-41-Demolition'!U26),"")} | H65: =G65/'Project Data'!$D$22 -> #VALUE!
B66: ='02-41-Demolition'!B27 -> 02 42 19 Shoring | D66: {=_xlfn.IFNA(_xlfn.IFS('02-41-Demolition'!D27="*",'02-41-Demolition'!C27,'02-41-Demolition'!F27="*",'02-41-Demolition'!E27,'02-41-Demolition'!H27="*",'02-41-Demolition'!G27,'02-41-Demolition'!J27="*",'02-41-Demolition'!I27,'02-41-Demolition'!L27="*",'02-41-Demolition'!K27,'02-41-Demolition'!N27="*",'02-41-Demolition'!M27,'02-41-Demolition'!P27="*",'02-41-Demolition'!O27,'02-41-Demolition'!R27="*",'02-41-Demolition'!Q27,'02-41-Demolition'!T27="*",'02-41-Demolition'!S27),"")} | E66: =D66/'Project Data'!$D$22 -> #VALUE! | G66: {=_xlfn.IFNA(_xlfn.IFS('02-41-Demolition'!F27="*",'02-41-Demolition'!E27,'02-41-Demolition'!H27="*",'02-41-Demolition'!G27,'02-41-Demolition'!J27="*",'02-41-Demolition'!I27,'02-41-Demolition'!L27="*",'02-41-Demolition'!K27,'02-41-Demolition'!N27="*",'02-41-Demolition'!M27,'02-41-Demolition'!P27="*",'02-41-Demolition'!O27,'02-41-Demolition'!R27="*",'02-41-Demolition'!Q27,'02-41-Demolition'!T27="*",'02-41-Demolition'!S27,'02-41-Demolition'!V27="*",'02-41-Demolition'!U27),"")} | H66: =G66/'Project Data'!$D$22 -> #VALUE! | K66: Allowance
A67: ='02-41-Demolition'!A28 -> 0 | B67: ='02-41-Demolition'!B28 -> 02 42 19.23 Wood Recycling | D67: {=_xlfn.IFNA(_xlfn.IFS('02-41-Demolition'!D28="*",'02-41-Demolition'!C28,'02-41-Demolition'!F28="*",'02-41-Demolition'!E28,'02-41-Demolition'!H28="*",'02-41-Demolition'!G28,'02-41-Demolition'!J28="*",'02-41-Demolition'!I28,'02-41-Demolition'!L28="*",'02-41-Demolition'!K28,'02-41-Demolition'!N28="*",'02-41-Demolition'!M28,'02-41-Demolition'!P28="*",'02-41-Demolition'!O28,'02-41-Demolition'!R28="*",'02-41-Demolition'!Q28,'02-41-Demolition'!T28="*",'02-41-Demolition'!S28),"")} | E67: =D67/'Project Data'!$D$22 -> #VALUE! | G67: {=_xlfn.IFNA(_xlfn.IFS('02-41-Demolition'!F28="*",'02-41-Demolition'!E28,'02-41-Demolition'!H28="*",'02-41-Demolition'!G28,'02-41-Demolition'!J28="*",'02-41-Demolition'!I28,'02-41-Demolition'!L28="*",'02-41-Demolition'!K28,'02-41-Demolition'!N28="*",'02-41-Demolition'!M28,'02-41-Demolition'!P28="*",'02-41-Demolition'!O28,'02-41-Demolition'!R28="*",'02-41-Demolition'!Q28,'02-41-Demolition'!T28="*",'02-41-Demolition'!S28,'02-41-Demolition'!V28="*",'02-41-Demolition'!U28),"")} | H67: =G67/'Project Data'!$D$22 -> #VALUE!
A68: ='02-41-Demolition'!A29 -> 0 | B68: ='02-41-Demolition'!B29 -> 02 42 19.25 Plastic Recycling | D68: {=_xlfn.IFNA(_xlfn.IFS('02-41-Demolition'!D29="*",'02-41-Demolition'!C29,'02-41-Demolition'!F29="*",'02-41-Demolition'!E29,'02-41-Demolition'!H29="*",'02-41-Demolition'!G29,'02-41-Demolition'!J29="*",'02-41-Demolition'!I29,'02-41-Demolition'!L29="*",'02-41-Demolition'!K29,'02-41-Demolition'!N29="*",'02-41-Demolition'!M29,'02-41-Demolition'!P29="*",'02-41-Demolition'!O29,'02-41-Demolition'!R29="*",'02-41-Demolition'!Q29,'02-41-Demolition'!T29="*",'02-41-Demolition'!S29),"")} | E68: =D68/'Project Data'!$D$22 -> #VALUE! | G68: {=_xlfn.IFNA(_xlfn.IFS('02-41-Demolition'!F29="*",'02-41-Demolition'!E29,'02-41-Demolition'!H29="*",'02-41-Demolition'!G29,'02-41-Demolition'!J29="*",'02-41-Demolition'!I29,'02-41-Demolition'!L29="*",'02-41-Demolition'!K29,'02-41-Demolition'!N29="*",'02-41-Demolition'!M29,'02-41-Demolition'!P29="*",'02-41-Demolition'!O29,'02-41-Demolition'!R29="*",'02-41-Demolition'!Q29,'02-41-Demolition'!T29="*",'02-41-Demolition'!S29,'02-41-Demolition'!V29="*",'02-41-Demolition'!U29),"")} | H68: =G68/'Project Data'!$D$22 -> #VALUE!
A69: ='02-41-Demolition'!A30 -> 0 | B69: ='02-41-Demolition'!B30 -> 02 42 19.29 Solid Surface Recycling | D69: {=_xlfn.IFNA(_xlfn.IFS('02-41-Demolition'!D30="*",'02-41-Demolition'!C30,'02-41-Demolition'!F30="*",'02-41-Demolition'!E30,'02-41-Demolition'!H30="*",'02-41-Demolition'!G30,'02-41-Demolition'!J30="*",'02-41-Demolition'!I30,'02-41-Demolition'!L30="*",'02-41-Demolition'!K30,'02-41-Demolition'!N30="*",'02-41-Demolition'!M30,'02-41-Demolition'!P30="*",'02-41-Demolition'!O30,'02-41-Demolition'!R30="*",'02-41-Demolition'!Q30,'02-41-Demolition'!T30="*",'02-41-Demolition'!S30),"")} | E69: =D69/'Project Data'!$D$22 -> #VALUE! | G69: {=_xlfn.IFNA(_xlfn.IFS('02-41-Demolition'!F30="*",'02-41-Demolition'!E30,'02-41-Demolition'!H30="*",'02-41-Demolition'!G30,'02-41-Demolition'!J30="*",'02-41-Demolition'!I30,'02-41-Demolition'!L30="*",'02-41-Demolition'!K30,'02-41-Demolition'!N30="*",'02-41-Demolition'!M30,'02-41-Demolition'!P30="*",'02-41-Demolition'!O30,'02-41-Demolition'!R30="*",'02-41-Demolition'!Q30,'02-41-Demolition'!T30="*",'02-41-Demolition'!S30,'02-41-Demolition'!V30="*",'02-41-Demolition'!U30),"")} | H69: =G69/'Project Data'!$D$22 -> #VALUE!
A70: ='02-41-Demolition'!A31 -> 0 | B70: ='02-41-Demolition'!B31 -> 02 42 19.31 Insulation Recycling | D70: {=_xlfn.IFNA(_xlfn.IFS('02-41-Demolition'!D31="*",'02-41-Demolition'!C31,'02-41-Demolition'!F31="*",'02-41-Demolition'!E31,'02-41-Demolition'!H31="*",'02-41-Demolition'!G31,'02-41-Demolition'!J31="*",'02-41-Demolition'!I31,'02-41-Demolition'!L31="*",'02-41-Demolition'!K31,'02-41-Demolition'!N31="*",'02-41-Demolition'!M31,'02-41-Demolition'!P31="*",'02-41-Demolition'!O31,'02-41-Demolition'!R31="*",'02-41-Demolition'!Q31,'02-41-Demolition'!T31="*",'02-41-Demolition'!S31),"")} | E70: =D70/'Project Data'!$D$22 -> #VALUE! | G70: {=_xlfn.IFNA(_xlfn.IFS('02-41-Demolition'!F31="*",'02-41-Demolition'!E31,'02-41-Demolition'!H31="*",'02-41-Demolition'!G31,'02-41-Demolition'!J31="*",'02-41-Demolition'!I31,'02-41-Demolition'!L31="*",'02-41-Demolition'!K31,'02-41-Demolition'!N31="*",'02-41-Demolition'!M31,'02-41-Demolition'!P31="*",'02-41-Demolition'!O31,'02-41-Demolition'!R31="*",'02-41-Demolition'!Q31,'02-41-Demolition'!T31="*",'02-41-Demolition'!S31,'02-41-Demolition'!V31="*",'02-41-Demolition'!U31),"")} | H70: =G70/'Project Data'!$D$22 -> #VALUE!
A71: ='02-41-Demolition'!A32 -> 0 | B71: ='02-41-Demolition'!B32 -> 02 42 19.35 Roofing Recycling | D71: {=_xlfn.IFNA(_xlfn.IFS('02-41-Demolition'!D32="*",'02-41-Demolition'!C32,'02-41-Demolition'!F32="*",'02-41-Demolition'!E32,'02-41-Demolition'!H32="*",'02-41-Demolition'!G32,'02-41-Demolition'!J32="*",'02-41-Demolition'!I32,'02-41-Demolition'!L32="*",'02-41-Demolition'!K32,'02-41-Demolition'!N32="*",'02-41-Demolition'!M32,'02-41-Demolition'!P32="*",'02-41-Demolition'!O32,'02-41-Demolition'!R32="*",'02-41-Demolition'!Q32,'02-41-Demolition'!T32="*",'02-41-Demolition'!S32),"")} | E71: =D71/'Project Data'!$D$22 -> #VALUE! | G71: {=_xlfn.IFNA(_xlfn.IFS('02-41-Demolition'!F32="*",'02-41-Demolition'!E32,'02-41-Demolition'!H32="*",'02-41-Demolition'!G32,'02-41-Demolition'!J32="*",'02-41-Demolition'!I32,'02-41-Demolition'!L32="*",'02-41-Demolition'!K32,'02-41-Demolition'!N32="*",'02-41-Demolition'!M32,'02-41-Demolition'!P32="*",'02-41-Demolition'!O32,'02-41-Demolition'!R32="*",'02-41-Demolition'!Q32,'02-41-Demolition'!T32="*",'02-41-Demolition'!S32,'02-41-Demolition'!V32="*",'02-41-Demolition'!U32),"")} | H71: =G71/'Project Data'!$D$22 -> #VALUE!
A72: ='02-41-Demolition'!A33 -> 0 | B72: ='02-41-Demolition'!B33 -> 02 42 19.39 Window Recycling | D72: {=_xlfn.IFNA(_xlfn.IFS('02-41-Demolition'!D33="*",'02-41-Demolition'!C33,'02-41-Demolition'!F33="*",'02-41-Demolition'!E33,'02-41-Demolition'!H33="*",'02-41-Demolition'!G33,'02-41-Demolition'!J33="*",'02-41-Demolition'!I33,'02-41-Demolition'!L33="*",'02-41-Demolition'!K33,'02-41-Demolition'!N33="*",'02-41-Demolition'!M33,'02-41-Demolition'!P33="*",'02-41-Demolition'!O33,'02-41-Demolition'!R33="*",'02-41-Demolition'!Q33,'02-41-Demolition'!T33="*",'02-41-Demolition'!S33),"")} | E72: =D72/'Project Data'!$D$22 -> #VALUE! | G72: {=_xlfn.IFNA(_xlfn.IFS('02-41-Demolition'!F33="*",'02-41-Demolition'!E33,'02-41-Demolition'!H33="*",'02-41-Demolition'!G33,'02-41-Demolition'!J33="*",'02-41-Demolition'!I33,'02-41-Demolition'!L33="*",'02-41-Demolition'!K33,'02-41-Demolition'!N33="*",'02-41-Demolition'!M33,'02-41-Demolition'!P33="*",'02-41-Demolition'!O33,'02-41-Demolition'!R33="*",'02-41-Demolition'!Q33,'02-41-Demolition'!T33="*",'02-41-Demolition'!S33,'02-41-Demolition'!V33="*",'02-41-Demolition'!U33),"")} | H72: =G72/'Project Data'!$D$22 -> #VALUE!
A73: ='02-41-Demolition'!A34 -> 0 | B73: ='02-41-Demolition'!B34 -> 02 42 19.41 Glass Recycling | D73: {=_xlfn.IFNA(_xlfn.IFS('02-41-Demolition'!D34="*",'02-41-Demolition'!C34,'02-41-Demolition'!F34="*",'02-41-Demolition'!E34,'02-41-Demolition'!H34="*",'02-41-Demolition'!G34,'02-41-Demolition'!J34="*",'02-41-Demolition'!I34,'02-41-Demolition'!L34="*",'02-41-Demolition'!K34,'02-41-Demolition'!N34="*",'02-41-Demolition'!M34,'02-41-Demolition'!P34="*",'02-41-Demolition'!O34,'02-41-Demolition'!R34="*",'02-41-Demolition'!Q34,'02-41-Demolition'!T34="*",'02-41-Demolition'!S34),"")} | E73: =D73/'Project Data'!$D$22 -> #VALUE! | G73: {=_xlfn.IFNA(_xlfn.IFS('02-41-Demolition'!F34="*",'02-41-Demolition'!E34,'02-41-Demolition'!H34="*",'02-41-Demolition'!G34,'02-41-Demolition'!J34="*",'02-41-Demolition'!I34,'02-41-Demolition'!L34="*",'02-41-Demolition'!K34,'02-41-Demolition'!N34="*",'02-41-Demolition'!M34,'02-41-Demolition'!P34="*",'02-41-Demolition'!O34,'02-41-Demolition'!R34="*",'02-41-Demolition'!Q34,'02-41-Demolition'!T34="*",'02-41-Demolition'!S34,'02-41-Demolition'!V34="*",'02-41-Demolition'!U34),"")} | H73: =G73/'Project Data'!$D$22 -> #VALUE!
A74: ='02-41-Demolition'!A35 -> 0 | B74: ='02-41-Demolition'!B35 -> 02 42 19.43 Gypsum Board Recycling | D74: {=_xlfn.IFNA(_xlfn.IFS('02-41-Demolition'!D35="*",'02-41-Demolition'!C35,'02-41-Demolition'!F35="*",'02-41-Demolition'!E35,'02-41-Demolition'!H35="*",'02-41-Demolition'!G35,'02-41-Demolition'!J35="*",'02-41-Demolition'!I35,'02-41-Demolition'!L35="*",'02-41-Demolition'!K35,'02-41-Demolition'!N35="*",'02-41-Demolition'!M35,'02-41-Demolition'!P35="*",'02-41-Demolition'!O35,'02-41-Demolition'!R35="*",'02-41-Demolition'!Q35,'02-41-Demolition'!T35="*",'02-41-Demolition'!S35),"")} | E74: =D74/'Project Data'!$D$22 -> #VALUE! | G74: {=_xlfn.IFNA(_xlfn.IFS('02-41-Demolition'!F35="*",'02-41-Demolition'!E35,'02-41-Demolition'!H35="*",'02-41-Demolition'!G35,'02-41-Demolition'!J35="*",'02-41-Demolition'!I35,'02-41-Demolition'!L35="*",'02-41-Demolition'!K35,'02-41-Demolition'!N35="*",'02-41-Demolition'!M35,'02-41-Demolition'!P35="*",'02-41-Demolition'!O35,'02-41-Demolition'!R35="*",'02-41-Demolition'!Q35,'02-41-Demolition'!T35="*",'02-41-Demolition'!S35,'02-41-Demolition'!V35="*",'02-41-Demolition'!U35),"")} | H74: =G74/'Project Data'!$D$22 -> #VALUE!
A75: ='02-41-Demolition'!A36 -> 0 | B75: ='02-41-Demolition'!B36 -> 02 42 19.45 Ceiling Tile Recycling | D75: {=_xlfn.IFNA(_xlfn.IFS('02-41-Demolition'!D36="*",'02-41-Demolition'!C36,'02-41-Demolition'!F36="*",'02-41-Demolition'!E36,'02-41-Demolition'!H36="*",'02-41-Demolition'!G36,'02-41-Demolition'!J36="*",'02-41-Demolition'!I36,'02-41-Demolition'!L36="*",'02-41-Demolition'!K36,'02-41-Demolition'!N36="*",'02-41-Demolition'!M36,'02-41-Demolition'!P36="*",'02-41-Demolition'!O36,'02-41-Demolition'!R36="*",'02-41-Demolition'!Q36,'02-41-Demolition'!T36="*",'02-41-Demolition'!S36),"")} | E75: =D75/'Project Data'!$D$22 -> #VALUE! | G75: {=_xlfn.IFNA(_xlfn.IFS('02-41-Demolition'!F36="*",'02-41-Demolition'!E36,'02-41-Demolition'!H36="*",'02-41-Demolition'!G36,'02-41-Demolition'!J36="*",'02-41-Demolition'!I36,'02-41-Demolition'!L36="*",'02-41-Demolition'!K36,'02-41-Demolition'!N36="*",'02-41-Demolition'!M36,'02-41-Demolition'!P36="*",'02-41-Demolition'!O36,'02-41-Demolition'!R36="*",'02-41-Demolition'!Q36,'02-41-Demolition'!T36="*",'02-41-Demolition'!S36,'02-41-Demolition'!V36="*",'02-41-Demolition'!U36),"")} | H75: =G75/'Project Data'!$D$22 -> #VALUE!
A76: ='02-41-Demolition'!A37 -> 0 | B76: ='02-41-Demolition'!B37 -> 02 42 19.47 Flooring Recycling | D76: {=_xlfn.IFNA(_xlfn.IFS('02-41-Demolition'!D37="*",'02-41-Demolition'!C37,'02-41-Demolition'!F37="*",'02-41-Demolition'!E37,'02-41-Demolition'!H37="*",'02-41-Demolition'!G37,'02-41-Demolition'!J37="*",'02-41-Demolition'!I37,'02-41-Demolition'!L37="*",'02-41-Demolition'!K37,'02-41-Demolition'!N37="*",'02-41-Demolition'!M37,'02-41-Demolition'!P37="*",'02-41-Demolition'!O37,'02-41-Demolition'!R37="*",'02-41-Demolition'!Q37,'02-41-Demolition'!T37="*",'02-41-Demolition'!S37),"")} | E76: =D76/'Project Data'!$D$22 -> #VALUE! | G76: {=_xlfn.IFNA(_xlfn.IFS('02-41-Demolition'!F37="*",'02-41-Demolition'!E37,'02-41-Demolition'!H37="*",'02-41-Demolition'!G37,'02-41-Demolition'!J37="*",'02-41-Demolition'!I37,'02-41-Demolition'!L37="*",'02-41-Demolition'!K37,'02-41-Demolition'!N37="*",'02-41-Demolition'!M37,'02-41-Demolition'!P37="*",'02-41-Demolition'!O37,'02-41-Demolition'!R37="*",'02-41-Demolition'!Q37,'02-41-Demolition'!T37="*",'02-41-Demolition'!S37,'02-41-Demolition'!V37="*",'02-41-Demolition'!U37),"")} | H76: =G76/'Project Data'!$D$22 -> #VALUE!
A77: ='02-41-Demolition'!A38 -> 0 | B77: ='02-41-Demolition'!B38 -> 02 42 19.55 Appliance Recycling | D77: {=_xlfn.IFNA(_xlfn.IFS('02-41-Demolition'!D38="*",'02-41-Demolition'!C38,'02-41-Demolition'!F38="*",'02-41-Demolition'!E38,'02-41-Demolition'!H38="*",'02-41-Demolition'!G38,'02-41-Demolition'!J38="*",'02-41-Demolition'!I38,'02-41-Demolition'!L38="*",'02-41-Demolition'!K38,'02-41-Demolition'!N38="*",'02-41-Demolition'!M38,'02-41-Demolition'!P38="*",'02-41-Demolition'!O38,'02-41-Demolition'!R38="*",'02-41-Demolition'!Q38,'02-41-Demolition'!T38="*",'02-41-Demolition'!S38),"")} | E77: =D77/'Project Data'!$D$22 -> #VALUE! | G77: {=_xlfn.IFNA(_xlfn.IFS('02-41-Demolition'!F38="*",'02-41-Demolition'!E38,'02-41-Demolition'!H38="*",'02-41-Demolition'!G38,'02-41-Demolition'!J38="*",'02-41-Demolition'!I38,'02-41-Demolition'!L38="*",'02-41-Demolition'!K38,'02-41-Demolition'!N38="*",'02-41-Demolition'!M38,'02-41-Demolition'!P38="*",'02-41-Demolition'!O38,'02-41-Demolition'!R38="*",'02-41-Demolition'!Q38,'02-41-Demolition'!T38="*",'02-41-Demolition'!S38,'02-41-Demolition'!V38="*",'02-41-Demolition'!U38),"")} | H77: =G77/'Project Data'!$D$22 -> #VALUE!
A78: ='02-41-Demolition'!A39 -> 0 | B78: ='02-41-Demolition'!B39 -> 02 42 19.57 Mattress Recycling | D78: {=_xlfn.IFNA(_xlfn.IFS('02-41-Demolition'!D39="*",'02-41-Demolition'!C39,'02-41-Demolition'!F39="*",'02-41-Demolition'!E39,'02-41-Demolition'!H39="*",'02-41-Demolition'!G39,'02-41-Demolition'!J39="*",'02-41-Demolition'!I39,'02-41-Demolition'!L39="*",'02-41-Demolition'!K39,'02-41-Demolition'!N39="*",'02-41-Demolition'!M39,'02-41-Demolition'!P39="*",'02-41-Demolition'!O39,'02-41-Demolition'!R39="*",'02-41-Demolition'!Q39,'02-41-Demolition'!T39="*",'02-41-Demolition'!S39),"")} | E78: =D78/'Project Data'!$D$22 -> #VALUE! | G78: {=_xlfn.IFNA(_xlfn.IFS('02-41-Demolition'!F39="*",'02-41-Demolition'!E39,'02-41-Demolition'!H39="*",'02-41-Demolition'!G39,'02-41-Demolition'!J39="*",'02-41-Demolition'!I39,'02-41-Demolition'!L39="*",'02-41-Demolition'!K39,'02-41-Demolition'!N39="*",'02-41-Demolition'!M39,'02-41-Demolition'!P39="*",'02-41-Demolition'!O39,'02-41-Demolition'!R39="*",'02-41-Demolition'!Q39,'02-41-Demolition'!T39="*",'02-41-Demolition'!S39,'02-41-Demolition'!V39="*",'02-41-Demolition'!U39),"")} | H78: =G78/'Project Data'!$D$22 -> #VALUE!
... A128: ='02-41-Demolition'!A89 -> 0 | B128: ='02-41-Demolition'!B89 -> 02 81 00 Transportation and Disposal of Hazardous Materials | D128: {=_xlfn.IFNA(_xlfn.IFS('02-41-Demolition'!D89="*",'02-41-Demolition'!C89,'02-41-Demolition'!F89="*",'02-41-Demolition'!E89,'02-41-Demolition'!H89="*",'02-41-Demolition'!G89,'02-41-Demolition'!J89="*",'02-41-Demolition'!I89,'02-41-Demolition'!L89="*",'02-41-Demolition'!K89,'02-41-Demolition'!N89="*",'02-41-Demolition'!M89,'02-41-Demolition'!P89="*",'02-41-Demolition'!O89,'02-41-Demolition'!R89="*",'02-41-Demolition'!Q89,'02-41-Demolition'!T89="*",'02-41-Demolition'!S89),"")} | E128: =D128/'Project Data'!$D$22 -> #VALUE! | G128: {=_xlfn.IFNA(_xlfn.IFS('02-41-Demolition'!F89="*",'02-41-Demolition'!E89,'02-41-Demolition'!H89="*",'02-41-Demolition'!G89,'02-41-Demolition'!J89="*",'02-41-Demolition'!I89,'02-41-Demolition'!L89="*",'02-41-Demolition'!K89,'02-41-Demolition'!N89="*",'02-41-Demolition'!M89,'02-41-Demolition'!P89="*",'02-41-Demolition'!O89,'02-41-Demolition'!R89="*",'02-41-Demolition'!Q89,'02-41-Demolition'!T89="*",'02-41-Demolition'!S89,'02-41-Demolition'!V89="*",'02-41-Demolition'!U89),"")} | H128: =G128/'Project Data'!$D$22 -> #VALUE!
A129: 1 | B129: Div. 02 82 - Abatement | D129: =SUM(D131:D136) -> 14623.57 | E129: =D129/'Project Data'!$D$22 -> 0.16340828 | F129: 14623.57 | G129: {=_xlfn.IFNA(_xlfn.IFS('02-82-Abatement'!F9="*",'02-82-Abatement'!E9,'02-82-Abatement'!H9="*",'02-82-Abatement'!G9,'02-82-Abatement'!J9="*",'02-82-Abatement'!I9,'02-82-Abatement'!L9="*",'02-82-Abatement'!K9,'02-82-Abatement'!N9="*",'02-82-Abatement'!M9,'02-82-Abatement'!P9="*",'02-82-Abatement'!O9,'02-82-Abatement'!R9="*",'02-82-Abatement'!Q9,'02-82-Abatement'!T9="*",'02-82-Abatement'!S9,'02-82-Abatement'!V9="*",'02-82-Abatement'!U9),"")} -> 14623.57 | H129: =G129/'Project Data'!$D$22 -> 0.16340828 | J129: =IFERROR(G129-F129, "--") -> 0
A130: ='02-82-Abatement'!A11 | B130: ='02-82-Abatement'!B11 -> 02 82 00 Asbestos Remediation | D130: {=_xlfn.IFNA(_xlfn.IFS('02-82-Abatement'!D11="*",'02-82-Abatement'!C11,'02-82-Abatement'!F11="*",'02-82-Abatement'!E11,'02-82-Abatement'!H11="*",'02-82-Abatement'!G11,'02-82-Abatement'!J11="*",'02-82-Abatement'!I11,'02-82-Abatement'!L11="*",'02-82-Abatement'!K11,'02-82-Abatement'!N11="*",'02-82-Abatement'!M11,'02-82-Abatement'!P11="*",'02-82-Abatement'!O11,'02-82-Abatement'!R11="*",'02-82-Abatement'!Q11,'02-82-Abatement'!T11="*",'02-82-Abatement'!S11),"")} | E130: =D130/'Project Data'!$D$22 -> #VALUE! | G130: {=_xlfn.IFNA(_xlfn.IFS('02-82-Abatement'!F11="*",'02-82-Abatement'!E11,'02-82-Abatement'!H11="*",'02-82-Abatement'!G11,'02-82-Abatement'!J11="*",'02-82-Abatement'!I11,'02-82-Abatement'!L11="*",'02-82-Abatement'!K11,'02-82-Abatement'!N11="*",'02-82-Abatement'!M11,'02-82-Abatement'!P11="*",'02-82-Abatement'!O11,'02-82-Abatement'!R11="*",'02-82-Abatement'!Q11,'02-82-Abatement'!T11="*",'02-82-Abatement'!S11,'02-82-Abatement'!V11="*",'02-82-Abatement'!U11),"")} | H130: =G130/'Project Data'!$D$22 -> #VALUE!
A131: ='02-82-Abatement'!A12 -> 1 | B131: ='02-82-Abatement'!B12 -> 02 82 13 Asbestos Abatement | D131: {=_xlfn.IFNA(_xlfn.IFS('02-82-Abatement'!D12="*",'02-82-Abatement'!C12,'02-82-Abatement'!F12="*",'02-82-Abatement'!E12,'02-82-Abatement'!H12="*",'02-82-Abatement'!G12,'02-82-Abatement'!J12="*",'02-82-Abatement'!I12,'02-82-Abatement'!L12="*",'02-82-Abatement'!K12,'02-82-Abatement'!N12="*",'02-82-Abatement'!M12,'02-82-Abatement'!P12="*",'02-82-Abatement'!O12,'02-82-Abatement'!R12="*",'02-82-Abatement'!Q12,'02-82-Abatement'!T12="*",'02-82-Abatement'!S12),"")} -> Included in Demo | F131: Included in Demo | G131: {=_xlfn.IFNA(_xlfn.IFS('02-82-Abatement'!F12="*",'02-82-Abatement'!E12,'02-82-Abatement'!H12="*",'02-82-Abatement'!G12,'02-82-Abatement'!J12="*",'02-82-Abatement'!I12,'02-82-Abatement'!L12="*",'02-82-Abatement'!K12,'02-82-Abatement'!N12="*",'02-82-Abatement'!M12,'02-82-Abatement'!P12="*",'02-82-Abatement'!O12,'02-82-Abatement'!R12="*",'02-82-Abatement'!Q12,'02-82-Abatement'!T12="*",'02-82-Abatement'!S12,'02-82-Abatement'!V12="*",'02-82-Abatement'!U12),"")} -> Included in Demo | H131: =G131/'Project Data'!$D$22 -> #VALUE! | K131: DHC
A132: ='02-82-Abatement'!A13 -> 0 | B132: ='02-82-Abatement'!B13 -> 02 82 13.19 Asbestos Floor Tile and Mastic Abatement | D132: {=_xlfn.IFNA(_xlfn.IFS('02-82-Abatement'!D13="*",'02-82-Abatement'!C13,'02-82-Abatement'!F13="*",'02-82-Abatement'!E13,'02-82-Abatement'!H13="*",'02-82-Abatement'!G13,'02-82-Abatement'!J13="*",'02-82-Abatement'!I13,'02-82-Abatement'!L13="*",'02-82-Abatement'!K13,'02-82-Abatement'!N13="*",'02-82-Abatement'!M13,'02-82-Abatement'!P13="*",'02-82-Abatement'!O13,'02-82-Abatement'!R13="*",'02-82-Abatement'!Q13,'02-82-Abatement'!T13="*",'02-82-Abatement'!S13),"")} | E132: =D132/'Project Data'!$D$22 -> #VALUE! | G132: {=_xlfn.IFNA(_xlfn.IFS('02-82-Abatement'!F13="*",'02-82-Abatement'!E13,'02-82-Abatement'!H13="*",'02-82-Abatement'!G13,'02-82-Abatement'!J13="*",'02-82-Abatement'!I13,'02-82-Abatement'!L13="*",'02-82-Abatement'!K13,'02-82-Abatement'!N13="*",'02-82-Abatement'!M13,'02-82-Abatement'!P13="*",'02-82-Abatement'!O13,'02-82-Abatement'!R13="*",'02-82-Abatement'!Q13,'02-82-Abatement'!T13="*",'02-82-Abatement'!S13,'02-82-Abatement'!V13="*",'02-82-Abatement'!U13),"")} | H132: =G132/'Project Data'!$D$22 -> #VALUE!
A133: ='02-82-Abatement'!A14 -> 0 | B133: ='02-82-Abatement'!B14 -> 02 82 13.33 Asbestos Abatement for Utilities | D133: {=_xlfn.IFNA(_xlfn.IFS('02-82-Abatement'!D14="*",'02-82-Abatement'!C14,'02-82-Abatement'!F14="*",'02-82-Abatement'!E14,'02-82-Abatement'!H14="*",'02-82-Abatement'!G14,'02-82-Abatement'!J14="*",'02-82-Abatement'!I14,'02-82-Abatement'!L14="*",'02-82-Abatement'!K14,'02-82-Abatement'!N14="*",'02-82-Abatement'!M14,'02-82-Abatement'!P14="*",'02-82-Abatement'!O14,'02-82-Abatement'!R14="*",'02-82-Abatement'!Q14,'02-82-Abatement'!T14="*",'02-82-Abatement'!S14),"")} | E133: =D133/'Project Data'!$D$22 -> #VALUE! | G133: {=_xlfn.IFNA(_xlfn.IFS('02-82-Abatement'!F14="*",'02-82-Abatement'!E14,'02-82-Abatement'!H14="*",'02-82-Abatement'!G14,'02-82-Abatement'!J14="*",'02-82-Abatement'!I14,'02-82-Abatement'!L14="*",'02-82-Abatement'!K14,'02-82-Abatement'!N14="*",'02-82-Abatement'!M14,'02-82-Abatement'!P14="*",'02-82-Abatement'!O14,'02-82-Abatement'!R14="*",'02-82-Abatement'!Q14,'02-82-Abatement'!T14="*",'02-82-Abatement'!S14,'02-82-Abatement'!V14="*",'02-82-Abatement'!U14),"")} | H133: =G133/'Project Data'!$D$22 -> #VALUE!
A134: ='02-82-Abatement'!A15 -> 0 | B134: ='02-82-Abatement'!B15 -> 02 82 16 Engineering Control of Asbestos Containing Materials | D134: {=_xlfn.IFNA(_xlfn.IFS('02-82-Abatement'!D15="*",'02-82-Abatement'!C15,'02-82-Abatement'!F15="*",'02-82-Abatement'!E15,'02-82-Abatement'!H15="*",'02-82-Abatement'!G15,'02-82-Abatement'!J15="*",'02-82-Abatement'!I15,'02-82-Abatement'!L15="*",'02-82-Abatement'!K15,'02-82-Abatement'!N15="*",'02-82-Abatement'!M15,'02-82-Abatement'!P15="*",'02-82-Abatement'!O15,'02-82-Abatement'!R15="*",'02-82-Abatement'!Q15,'02-82-Abatement'!T15="*",'02-82-Abatement'!S15),"")} | E134: =D134/'Project Data'!$D$22 -> #VALUE! | G134: {=_xlfn.IFNA(_xlfn.IFS('02-82-Abatement'!F15="*",'02-82-Abatement'!E15,'02-82-Abatement'!H15="*",'02-82-Abatement'!G15,'02-82-Abatement'!J15="*",'02-82-Abatement'!I15,'02-82-Abatement'!L15="*",'02-82-Abatement'!K15,'02-82-Abatement'!N15="*",'02-82-Abatement'!M15,'02-82-Abatement'!P15="*",'02-82-Abatement'!O15,'02-82-Abatement'!R15="*",'02-82-Abatement'!Q15,'02-82-Abatement'!T15="*",'02-82-Abatement'!S15,'02-82-Abatement'!V15="*",'02-82-Abatement'!U15),"")} | H134: =G134/'Project Data'!$D$22 -> #VALUE!
A135: ='02-82-Abatement'!A16 -> 1 | B135: ='02-82-Abatement'!B16 -> 02 82 33 Asbestos Survey | D135: {=_xlfn.IFNA(_xlfn.IFS('02-82-Abatement'!D16="*",'02-82-Abatement'!C16,'02-82-Abatement'!F16="*",'02-82-Abatement'!E16,'02-82-Abatement'!H16="*",'02-82-Abatement'!G16,'02-82-Abatement'!J16="*",'02-82-Abatement'!I16,'02-82-Abatement'!L16="*",'02-82-Abatement'!K16,'02-82-Abatement'!N16="*",'02-82-Abatement'!M16,'02-82-Abatement'!P16="*",'02-82-Abatement'!O16,'02-82-Abatement'!R16="*",'02-82-Abatement'!Q16,'02-82-Abatement'!T16="*",'02-82-Abatement'!S16),"")} -> 10000 | E135: =D135/'Project Data'!$D$22 -> 0.11174308 | F135: 10000 | G135: {=_xlfn.IFNA(_xlfn.IFS('02-82-Abatement'!F16="*",'02-82-Abatement'!E16,'02-82-Abatement'!H16="*",'02-82-Abatement'!G16,'02-82-Abatement'!J16="*",'02-82-Abatement'!I16,'02-82-Abatement'!L16="*",'02-82-Abatement'!K16,'02-82-Abatement'!N16="*",'02-82-Abatement'!M16,'02-82-Abatement'!P16="*",'02-82-Abatement'!O16,'02-82-Abatement'!R16="*",'02-82-Abatement'!Q16,'02-82-Abatement'!T16="*",'02-82-Abatement'!S16,'02-82-Abatement'!V16="*",'02-82-Abatement'!U16),"")} -> 10000 | H135: =G135/'Project Data'!$D$22 -> 0.11174308 | K135: N-terprise
A136: ='02-82-Abatement'!A17 -> 1 | B136: ='02-82-Abatement'!B17 -> 02 83 00 Termite Prevention | D136: {=_xlfn.IFNA(_xlfn.IFS('02-82-Abatement'!D17="*",'02-82-Abatement'!C17,'02-82-Abatement'!F17="*",'02-82-Abatement'!E17,'02-82-Abatement'!H17="*",'02-82-Abatement'!G17,'02-82-Abatement'!J17="*",'02-82-Abatement'!I17,'02-82-Abatement'!L17="*",'02-82-Abatement'!K17,'02-82-Abatement'!N17="*",'02-82-Abatement'!M17,'02-82-Abatement'!P17="*",'02-82-Abatement'!O17,'02-82-Abatement'!R17="*",'02-82-Abatement'!Q17,'02-82-Abatement'!T17="*",'02-82-Abatement'!S17),"")} -> 4623.57 | E136: =D136/'Project Data'!$D$22 -> 0.051665195 | F136: 4623.57 | G136: {=_xlfn.IFNA(_xlfn.IFS('02-82-Abatement'!F17="*",'02-82-Abatement'!E17,'02-82-Abatement'!H17="*",'02-82-Abatement'!G17,'02-82-Abatement'!J17="*",'02-82-Abatement'!I17,'02-82-Abatement'!L17="*",'02-82-Abatement'!K17,'02-82-Abatement'!N17="*",'02-82-Abatement'!M17,'02-82-Abatement'!P17="*",'02-82-Abatement'!O17,'02-82-Abatement'!R17="*",'02-82-Abatement'!Q17,'02-82-Abatement'!T17="*",'02-82-Abatement'!S17,'02-82-Abatement'!V17="*",'02-82-Abatement'!U17),"")} -> 4623.57 | H136: =G136/'Project Data'!$D$22 -> 0.051665195 | K136: Diligent
A137: ='02-82-Abatement'!A18 -> 0 | B137: ='02-82-Abatement'!B18 -> 02 83 13 Lead Hazard Control Activities | D137: {=_xlfn.IFNA(_xlfn.IFS('02-82-Abatement'!D18="*",'02-82-Abatement'!C18,'02-82-Abatement'!F18="*",'02-82-Abatement'!E18,'02-82-Abatement'!H18="*",'02-82-Abatement'!G18,'02-82-Abatement'!J18="*",'02-82-Abatement'!I18,'02-82-Abatement'!L18="*",'02-82-Abatement'!K18,'02-82-Abatement'!N18="*",'02-82-Abatement'!M18,'02-82-Abatement'!P18="*",'02-82-Abatement'!O18,'02-82-Abatement'!R18="*",'02-82-Abatement'!Q18,'02-82-Abatement'!T18="*",'02-82-Abatement'!S18),"")} | E137: =D137/'Project Data'!$D$22 -> #VALUE! | G137: {=_xlfn.IFNA(_xlfn.IFS('02-82-Abatement'!F18="*",'02-82-Abatement'!E18,'02-82-Abatement'!H18="*",'02-82-Abatement'!G18,'02-82-Abatement'!J18="*",'02-82-Abatement'!I18,'02-82-Abatement'!L18="*",'02-82-Abatement'!K18,'02-82-Abatement'!N18="*",'02-82-Abatement'!M18,'02-82-Abatement'!P18="*",'02-82-Abatement'!O18,'02-82-Abatement'!R18="*",'02-82-Abatement'!Q18,'02-82-Abatement'!T18="*",'02-82-Abatement'!S18,'02-82-Abatement'!V18="*",'02-82-Abatement'!U18),"")} | H137: =G137/'Project Data'!$D$22 -> #VALUE!
A138: ='02-82-Abatement'!A19 -> 0 | B138: ='02-82-Abatement'!B19 -> 02 83 19 Lead-Based Paint Remediation | D138: {=_xlfn.IFNA(_xlfn.IFS('02-82-Abatement'!D19="*",'02-82-Abatement'!C19,'02-82-Abatement'!F19="*",'02-82-Abatement'!E19,'02-82-Abatement'!H19="*",'02-82-Abatement'!G19,'02-82-Abatement'!J19="*",'02-82-Abatement'!I19,'02-82-Abatement'!L19="*",'02-82-Abatement'!K19,'02-82-Abatement'!N19="*",'02-82-Abatement'!M19,'02-82-Abatement'!P19="*",'02-82-Abatement'!O19,'02-82-Abatement'!R19="*",'02-82-Abatement'!Q19,'02-82-Abatement'!T19="*",'02-82-Abatement'!S19),"")} | E138: =D138/'Project Data'!$D$22 -> #VALUE! | G138: {=_xlfn.IFNA(_xlfn.IFS('02-82-Abatement'!F19="*",'02-82-Abatement'!E19,'02-82-Abatement'!H19="*",'02-82-Abatement'!G19,'02-82-Abatement'!J19="*",'02-82-Abatement'!I19,'02-82-Abatement'!L19="*",'02-82-Abatement'!K19,'02-82-Abatement'!N19="*",'02-82-Abatement'!M19,'02-82-Abatement'!P19="*",'02-82-Abatement'!O19,'02-82-Abatement'!R19="*",'02-82-Abatement'!Q19,'02-82-Abatement'!T19="*",'02-82-Abatement'!S19,'02-82-Abatement'!V19="*",'02-82-Abatement'!U19),"")} | H138: =G138/'Project Data'!$D$22 -> #VALUE!
A139: ='02-82-Abatement'!A20 -> 0 | B139: ='02-82-Abatement'!B20 -> 02 83 19.13 Lead-Based Paint Abatement | D139: {=_xlfn.IFNA(_xlfn.IFS('02-82-Abatement'!D20="*",'02-82-Abatement'!C20,'02-82-Abatement'!F20="*",'02-82-Abatement'!E20,'02-82-Abatement'!H20="*",'02-82-Abatement'!G20,'02-82-Abatement'!J20="*",'02-82-Abatement'!I20,'02-82-Abatement'!L20="*",'02-82-Abatement'!K20,'02-82-Abatement'!N20="*",'02-82-Abatement'!M20,'02-82-Abatement'!P20="*",'02-82-Abatement'!O20,'02-82-Abatement'!R20="*",'02-82-Abatement'!Q20,'02-82-Abatement'!T20="*",'02-82-Abatement'!S20),"")} | E139: =D139/'Project Data'!$D$22 -> #VALUE! | G139: {=_xlfn.IFNA(_xlfn.IFS('02-82-Abatement'!F20="*",'02-82-Abatement'!E20,'02-82-Abatement'!H20="*",'02-82-Abatement'!G20,'02-82-Abatement'!J20="*",'02-82-Abatement'!I20,'02-82-Abatement'!L20="*",'02-82-Abatement'!K20,'02-82-Abatement'!N20="*",'02-82-Abatement'!M20,'02-82-Abatement'!P20="*",'02-82-Abatement'!O20,'02-82-Abatement'!R20="*",'02-82-Abatement'!Q20,'02-82-Abatement'!T20="*",'02-82-Abatement'!S20,'02-82-Abatement'!V20="*",'02-82-Abatement'!U20),"")} | H139: =G139/'Project Data'!$D$22 -> #VALUE!
A140: ='02-82-Abatement'!A21 -> 0 | B140: ='02-82-Abatement'!B21 -> 02 83 33.13 Lead-Based Paint Removal and Disposal | D140: {=_xlfn.IFNA(_xlfn.IFS('02-82-Abatement'!D21="*",'02-82-Abatement'!C21,'02-82-Abatement'!F21="*",'02-82-Abatement'!E21,'02-82-Abatement'!H21="*",'02-82-Abatement'!G21,'02-82-Abatement'!J21="*",'02-82-Abatement'!I21,'02-82-Abatement'!L21="*",'02-82-Abatement'!K21,'02-82-Abatement'!N21="*",'02-82-Abatement'!M21,'02-82-Abatement'!P21="*",'02-82-Abatement'!O21,'02-82-Abatement'!R21="*",'02-82-Abatement'!Q21,'02-82-Abatement'!T21="*",'02-82-Abatement'!S21),"")} | E140: =D140/'Project Data'!$D$22 -> #VALUE! | G140: {=_xlfn.IFNA(_xlfn.IFS('02-82-Abatement'!F21="*",'02-82-Abatement'!E21,'02-82-Abatement'!H21="*",'02-82-Abatement'!G21,'02-82-Abatement'!J21="*",'02-82-Abatement'!I21,'02-82-Abatement'!L21="*",'02-82-Abatement'!K21,'02-82-Abatement'!N21="*",'02-82-Abatement'!M21,'02-82-Abatement'!P21="*",'02-82-Abatement'!O21,'02-82-Abatement'!R21="*",'02-82-Abatement'!Q21,'02-82-Abatement'!T21="*",'02-82-Abatement'!S21,'02-82-Abatement'!V21="*",'02-82-Abatement'!U21),"")} | H140: =G140/'Project Data'!$D$22 -> #VALUE!
A141: ='02-82-Abatement'!A22 | B141: ='02-82-Abatement'!B22 -> 02 87 13 Mold Remediation | D141: {=_xlfn.IFNA(_xlfn.IFS('02-82-Abatement'!D22="*",'02-82-Abatement'!C22,'02-82-Abatement'!F22="*",'02-82-Abatement'!E22,'02-82-Abatement'!H22="*",'02-82-Abatement'!G22,'02-82-Abatement'!J22="*",'02-82-Abatement'!I22,'02-82-Abatement'!L22="*",'02-82-Abatement'!K22,'02-82-Abatement'!N22="*",'02-82-Abatement'!M22,'02-82-Abatement'!P22="*",'02-82-Abatement'!O22,'02-82-Abatement'!R22="*",'02-82-Abatement'!Q22,'02-82-Abatement'!T22="*",'02-82-Abatement'!S22),"")} | E141: =D141/'Project Data'!$D$22 -> #VALUE! | G141: {=_xlfn.IFNA(_xlfn.IFS('02-82-Abatement'!F22="*",'02-82-Abatement'!E22,'02-82-Abatement'!H22="*",'02-82-Abatement'!G22,'02-82-Abatement'!J22="*",'02-82-Abatement'!I22,'02-82-Abatement'!L22="*",'02-82-Abatement'!K22,'02-82-Abatement'!N22="*",'02-82-Abatement'!M22,'02-82-Abatement'!P22="*",'02-82-Abatement'!O22,'02-82-Abatement'!R22="*",'02-82-Abatement'!Q22,'02-82-Abatement'!T22="*",'02-82-Abatement'!S22,'02-82-Abatement'!V22="*",'02-82-Abatement'!U22),"")} | H141: =G141/'Project Data'!$D$22 -> #VALUE!
A142: ='02-82-Abatement'!A23 -> 0 | B142: ='02-82-Abatement'!B23 -> 02 87 13.16 Mold Remediation Preparation and Containment | D142: {=_xlfn.IFNA(_xlfn.IFS('02-82-Abatement'!D23="*",'02-82-Abatement'!C23,'02-82-Abatement'!F23="*",'02-82-Abatement'!E23,'02-82-Abatement'!H23="*",'02-82-Abatement'!G23,'02-82-Abatement'!J23="*",'02-82-Abatement'!I23,'02-82-Abatement'!L23="*",'02-82-Abatement'!K23,'02-82-Abatement'!N23="*",'02-82-Abatement'!M23,'02-82-Abatement'!P23="*",'02-82-Abatement'!O23,'02-82-Abatement'!R23="*",'02-82-Abatement'!Q23,'02-82-Abatement'!T23="*",'02-82-Abatement'!S23),"")} | E142: =D142/'Project Data'!$D$22 -> #VALUE! | G142: {=_xlfn.IFNA(_xlfn.IFS('02-82-Abatement'!F23="*",'02-82-Abatement'!E23,'02-82-Abatement'!H23="*",'02-82-Abatement'!G23,'02-82-Abatement'!J23="*",'02-82-Abatement'!I23,'02-82-Abatement'!L23="*",'02-82-Abatement'!K23,'02-82-Abatement'!N23="*",'02-82-Abatement'!M23,'02-82-Abatement'!P23="*",'02-82-Abatement'!O23,'02-82-Abatement'!R23="*",'02-82-Abatement'!Q23,'02-82-Abatement'!T23="*",'02-82-Abatement'!S23,'02-82-Abatement'!V23="*",'02-82-Abatement'!U23),"")} | H142: =G142/'Project Data'!$D$22 -> #VALUE!
A143: ='02-82-Abatement'!A24 -> 0 | B143: ='02-82-Abatement'!B24 -> 02 87 13.19 Mold Remediation Clearance Air Sampling | D143: {=_xlfn.IFNA(_xlfn.IFS('02-82-Abatement'!D24="*",'02-82-Abatement'!C24,'02-82-Abatement'!F24="*",'02-82-Abatement'!E24,'02-82-Abatement'!H24="*",'02-82-Abatement'!G24,'02-82-Abatement'!J24="*",'02-82-Abatement'!I24,'02-82-Abatement'!L24="*",'02-82-Abatement'!K24,'02-82-Abatement'!N24="*",'02-82-Abatement'!M24,'02-82-Abatement'!P24="*",'02-82-Abatement'!O24,'02-82-Abatement'!R24="*",'02-82-Abatement'!Q24,'02-82-Abatement'!T24="*",'02-82-Abatement'!S24),"")} | E143: =D143/'Project Data'!$D$22 -> #VALUE! | G143: {=_xlfn.IFNA(_xlfn.IFS('02-82-Abatement'!F24="*",'02-82-Abatement'!E24,'02-82-Abatement'!H24="*",'02-82-Abatement'!G24,'02-82-Abatement'!J24="*",'02-82-Abatement'!I24,'02-82-Abatement'!L24="*",'02-82-Abatement'!K24,'02-82-Abatement'!N24="*",'02-82-Abatement'!M24,'02-82-Abatement'!P24="*",'02-82-Abatement'!O24,'02-82-Abatement'!R24="*",'02-82-Abatement'!Q24,'02-82-Abatement'!T24="*",'02-82-Abatement'!S24,'02-82-Abatement'!V24="*",'02-82-Abatement'!U24),"")} | H143: =G143/'Project Data'!$D$22 -> #VALUE!
A144: 1 | B144: Div. 03 - Concrete | D144: =SUM(D201:D266) -> 2397804 | E144: =D144/'Project Data'!$D$22 -> 26.7938 | F144: 2534631 | G144: {=_xlfn.IFNA(_xlfn.IFS('03-Concrete'!F9="*",'03-Concrete'!E9,'03-Concrete'!H9="*",'03-Concrete'!G9,'03-Concrete'!J9="*",'03-Concrete'!I9,'03-Concrete'!L9="*",'03-Concrete'!K9,'03-Concrete'!N9="*",'03-Concrete'!M9,'03-Concrete'!P9="*",'03-Concrete'!O9,'03-Concrete'!R9="*",'03-Concrete'!Q9,'03-Concrete'!T9="*",'03-Concrete'!S9,'03-Concrete'!V9="*",'03-Concrete'!U9),"")} -> 2397804 | H144: =G144/'Project Data'!$D$22 -> 26.7938 | I144: ='03-Concrete'!W9 | J144: =IFERROR(G144-F144, "--") -> -136827
A145: ='03-Concrete'!A11 -> 0 | B145: ='03-Concrete'!B11 -> 03 00 00 Concrete | D145: {=_xlfn.IFNA(_xlfn.IFS('03-Concrete'!D11="*",'03-Concrete'!C11,'03-Concrete'!F11="*",'03-Concrete'!E11,'03-Concrete'!H11="*",'03-Concrete'!G11,'03-Concrete'!J11="*",'03-Concrete'!I11,'03-Concrete'!L11="*",'03-Concrete'!K11,'03-Concrete'!N11="*",'03-Concrete'!M11,'03-Concrete'!P11="*",'03-Concrete'!O11,'03-Concrete'!R11="*",'03-Concrete'!Q11,'03-Concrete'!T11="*",'03-Concrete'!S11),"")} | E145: =D145/'Project Data'!$D$22 -> #VALUE! | G145: {=_xlfn.IFNA(_xlfn.IFS('03-Concrete'!F11="*",'03-Concrete'!E11,'03-Concrete'!H11="*",'03-Concrete'!G11,'03-Concrete'!J11="*",'03-Concrete'!I11,'03-Concrete'!L11="*",'03-Concrete'!K11,'03-Concrete'!N11="*",'03-Concrete'!M11,'03-Concrete'!P11="*",'03-Concrete'!O11,'03-Concrete'!R11="*",'03-Concrete'!Q11,'03-Concrete'!T11="*",'03-Concrete'!S11,'03-Concrete'!V11="*",'03-Concrete'!U11),"")} | H145: =G145/'Project Data'!$D$22 -> #VALUE!
A146: ='03-Concrete'!A12 -> 0 | B146: ='03-Concrete'!B12 -> 03 01 30.51 Cleaning of Cast-in-Place Concrete | D146: {=_xlfn.IFNA(_xlfn.IFS('03-Concrete'!D12="*",'03-Concrete'!C12,'03-Concrete'!F12="*",'03-Concrete'!E12,'03-Concrete'!H12="*",'03-Concrete'!G12,'03-Concrete'!J12="*",'03-Concrete'!I12,'03-Concrete'!L12="*",'03-Concrete'!K12,'03-Concrete'!N12="*",'03-Concrete'!M12,'03-Concrete'!P12="*",'03-Concrete'!O12,'03-Concrete'!R12="*",'03-Concrete'!Q12,'03-Concrete'!T12="*",'03-Concrete'!S12),"")} | E146: =D146/'Project Data'!$D$22 -> #VALUE! | G146: {=_xlfn.IFNA(_xlfn.IFS('03-Concrete'!F12="*",'03-Concrete'!E12,'03-Concrete'!H12="*",'03-Concrete'!G12,'03-Concrete'!J12="*",'03-Concrete'!I12,'03-Concrete'!L12="*",'03-Concrete'!K12,'03-Concrete'!N12="*",'03-Concrete'!M12,'03-Concrete'!P12="*",'03-Concrete'!O12,'03-Concrete'!R12="*",'03-Concrete'!Q12,'03-Concrete'!T12="*",'03-Concrete'!S12,'03-Concrete'!V12="*",'03-Concrete'!U12),"")} | H146: =G146/'Project Data'!$D$22 -> #VALUE!
A147: ='03-Concrete'!A13 -> 0 | B147: ='03-Concrete'!B13 -> 03 01 30.61 Resurfacing of Cast-in-Place Concrete | D147: {=_xlfn.IFNA(_xlfn.IFS('03-Concrete'!D13="*",'03-Concrete'!C13,'03-Concrete'!F13="*",'03-Concrete'!E13,'03-Concrete'!H13="*",'03-Concrete'!G13,'03-Concrete'!J13="*",'03-Concrete'!I13,'03-Concrete'!L13="*",'03-Concrete'!K13,'03-Concrete'!N13="*",'03-Concrete'!M13,'03-Concrete'!P13="*",'03-Concrete'!O13,'03-Concrete'!R13="*",'03-Concrete'!Q13,'03-Concrete'!T13="*",'03-Concrete'!S13),"")} | E147: =D147/'Project Data'!$D$22 -> #VALUE! | G147: {=_xlfn.IFNA(_xlfn.IFS('03-Concrete'!F13="*",'03-Concrete'!E13,'03-Concrete'!H13="*",'03-Concrete'!G13,'03-Concrete'!J13="*",'03-Concrete'!I13,'03-Concrete'!L13="*",'03-Concrete'!K13,'03-Concrete'!N13="*",'03-Concrete'!M13,'03-Concrete'!P13="*",'03-Concrete'!O13,'03-Concrete'!R13="*",'03-Concrete'!Q13,'03-Concrete'!T13="*",'03-Concrete'!S13,'03-Concrete'!V13="*",'03-Concrete'!U13),"")} | H147: =G147/'Project Data'!$D$22 -> #VALUE!
A148: ='03-Concrete'!A14 -> 0 | B148: ='03-Concrete'!B14 -> 03 01 30.71 Rehabilitation of Cast-in-Place Concrete | D148: {=_xlfn.IFNA(_xlfn.IFS('03-Concrete'!D14="*",'03-Concrete'!C14,'03-Concrete'!F14="*",'03-Concrete'!E14,'03-Concrete'!H14="*",'03-Concrete'!G14,'03-Concrete'!J14="*",'03-Concrete'!I14,'03-Concrete'!L14="*",'03-Concrete'!K14,'03-Concrete'!N14="*",'03-Concrete'!M14,'03-Concrete'!P14="*",'03-Concrete'!O14,'03-Concrete'!R14="*",'03-Concrete'!Q14,'03-Concrete'!T14="*",'03-Concrete'!S14),"")} | E148: =D148/'Project Data'!$D$22 -> #VALUE! | G148: {=_xlfn.IFNA(_xlfn.IFS('03-Concrete'!F14="*",'03-Concrete'!E14,'03-Concrete'!H14="*",'03-Concrete'!G14,'03-Concrete'!J14="*",'03-Concrete'!I14,'03-Concrete'!L14="*",'03-Concrete'!K14,'03-Concrete'!N14="*",'03-Concrete'!M14,'03-Concrete'!P14="*",'03-Concrete'!O14,'03-Concrete'!R14="*",'03-Concrete'!Q14,'03-Concrete'!T14="*",'03-Concrete'!S14,'03-Concrete'!V14="*",'03-Concrete'!U14),"")} | H148: =G148/'Project Data'!$D$22 -> #VALUE!
A149: ='03-Concrete'!A15 -> 0 | B149: ='03-Concrete'!B15 -> 03 01 30.72 Strengthening of Cast-in-Place Concrete | D149: {=_xlfn.IFNA(_xlfn.IFS('03-Concrete'!D15="*",'03-Concrete'!C15,'03-Concrete'!F15="*",'03-Concrete'!E15,'03-Concrete'!H15="*",'03-Concrete'!G15,'03-Concrete'!J15="*",'03-Concrete'!I15,'03-Concrete'!L15="*",'03-Concrete'!K15,'03-Concrete'!N15="*",'03-Concrete'!M15,'03-Concrete'!P15="*",'03-Concrete'!O15,'03-Concrete'!R15="*",'03-Concrete'!Q15,'03-Concrete'!T15="*",'03-Concrete'!S15),"")} | E149: =D149/'Project Data'!$D$22 -> #VALUE! | G149: {=_xlfn.IFNA(_xlfn.IFS('03-Concrete'!F15="*",'03-Concrete'!E15,'03-Concrete'!H15="*",'03-Concrete'!G15,'03-Concrete'!J15="*",'03-Concrete'!I15,'03-Concrete'!L15="*",'03-Concrete'!K15,'03-Concrete'!N15="*",'03-Concrete'!M15,'03-Concrete'!P15="*",'03-Concrete'!O15,'03-Concrete'!R15="*",'03-Concrete'!Q15,'03-Concrete'!T15="*",'03-Concrete'!S15,'03-Concrete'!V15="*",'03-Concrete'!U15),"")} | H149: =G149/'Project Data'!$D$22 -> #VALUE!
A150: ='03-Concrete'!A16 -> 0 | B150: ='03-Concrete'!B16 -> 03 01 50.51 Cleaning Cast Decks and Underlayment | D150: {=_xlfn.IFNA(_xlfn.IFS('03-Concrete'!D16="*",'03-Concrete'!C16,'03-Concrete'!F16="*",'03-Concrete'!E16,'03-Concrete'!H16="*",'03-Concrete'!G16,'03-Concrete'!J16="*",'03-Concrete'!I16,'03-Concrete'!L16="*",'03-Concrete'!K16,'03-Concrete'!N16="*",'03-Concrete'!M16,'03-Concrete'!P16="*",'03-Concrete'!O16,'03-Concrete'!R16="*",'03-Concrete'!Q16,'03-Concrete'!T16="*",'03-Concrete'!S16),"")} | E150: =D150/'Project Data'!$D$22 -> #VALUE! | G150: {=_xlfn.IFNA(_xlfn.IFS('03-Concrete'!F16="*",'03-Concrete'!E16,'03-Concrete'!H16="*",'03-Concrete'!G16,'03-Concrete'!J16="*",'03-Concrete'!I16,'03-Concrete'!L16="*",'03-Concrete'!K16,'03-Concrete'!N16="*",'03-Concrete'!M16,'03-Concrete'!P16="*",'03-Concrete'!O16,'03-Concrete'!R16="*",'03-Concrete'!Q16,'03-Concrete'!T16="*",'03-Concrete'!S16,'03-Concrete'!V16="*",'03-Concrete'!U16),"")} | H150: =G150/'Project Data'!$D$22 -> #VALUE!
A151: ='03-Concrete'!A17 -> 0 | B151: ='03-Concrete'!B17 -> 03 01 50.61 Resurfacing of Cast Decks and Underlayment | D151: {=_xlfn.IFNA(_xlfn.IFS('03-Concrete'!D17="*",'03-Concrete'!C17,'03-Concrete'!F17="*",'03-Concrete'!E17,'03-Concrete'!H17="*",'03-Concrete'!G17,'03-Concrete'!J17="*",'03-Concrete'!I17,'03-Concrete'!L17="*",'03-Concrete'!K17,'03-Concrete'!N17="*",'03-Concrete'!M17,'03-Concrete'!P17="*",'03-Concrete'!O17,'03-Concrete'!R17="*",'03-Concrete'!Q17,'03-Concrete'!T17="*",'03-Concrete'!S17),"")} | E151: =D151/'Project Data'!$D$22 -> #VALUE! | G151: {=_xlfn.IFNA(_xlfn.IFS('03-Concrete'!F17="*",'03-Concrete'!E17,'03-Concrete'!H17="*",'03-Concrete'!G17,'03-Concrete'!J17="*",'03-Concrete'!I17,'03-Concrete'!L17="*",'03-Concrete'!K17,'03-Concrete'!N17="*",'03-Concrete'!M17,'03-Concrete'!P17="*",'03-Concrete'!O17,'03-Concrete'!R17="*",'03-Concrete'!Q17,'03-Concrete'!T17="*",'03-Concrete'!S17,'03-Concrete'!V17="*",'03-Concrete'!U17),"")} | H151: =G151/'Project Data'!$D$22 -> #VALUE!
A152: ='03-Concrete'!A18 -> 0 | B152: ='03-Concrete'!B18 -> 03 01 50.71 Rehabilitation of Cast Decks and Underlayment | D152: {=_xlfn.IFNA(_xlfn.IFS('03-Concrete'!D18="*",'03-Concrete'!C18,'03-Concrete'!F18="*",'03-Concrete'!E18,'03-Concrete'!H18="*",'03-Concrete'!G18,'03-Concrete'!J18="*",'03-Concrete'!I18,'03-Concrete'!L18="*",'03-Concrete'!K18,'03-Concrete'!N18="*",'03-Concrete'!M18,'03-Concrete'!P18="*",'03-Concrete'!O18,'03-Concrete'!R18="*",'03-Concrete'!Q18,'03-Concrete'!T18="*",'03-Concrete'!S18),"")} | E152: =D152/'Project Data'!$D$22 -> #VALUE! | G152: {=_xlfn.IFNA(_xlfn.IFS('03-Concrete'!F18="*",'03-Concrete'!E18,'03-Concrete'!H18="*",'03-Concrete'!G18,'03-Concrete'!J18="*",'03-Concrete'!I18,'03-Concrete'!L18="*",'03-Concrete'!K18,'03-Concrete'!N18="*",'03-Concrete'!M18,'03-Concrete'!P18="*",'03-Concrete'!O18,'03-Concrete'!R18="*",'03-Concrete'!Q18,'03-Concrete'!T18="*",'03-Concrete'!S18,'03-Concrete'!V18="*",'03-Concrete'!U18),"")} | H152: =G152/'Project Data'!$D$22 -> #VALUE!
A153: ='03-Concrete'!A19 -> 0 | B153: ='03-Concrete'!B19 -> 03 01 50.72 Strengthening of Cast Decks and Underlayment | D153: {=_xlfn.IFNA(_xlfn.IFS('03-Concrete'!D19="*",'03-Concrete'!C19,'03-Concrete'!F19="*",'03-Concrete'!E19,'03-Concrete'!H19="*",'03-Concrete'!G19,'03-Concrete'!J19="*",'03-Concrete'!I19,'03-Concrete'!L19="*",'03-Concrete'!K19,'03-Concrete'!N19="*",'03-Concrete'!M19,'03-Concrete'!P19="*",'03-Concrete'!O19,'03-Concrete'!R19="*",'03-Concrete'!Q19,'03-Concrete'!T19="*",'03-Concrete'!S19),"")} | E153: =D153/'Project Data'!$D$22 -> #VALUE! | G153: {=_xlfn.IFNA(_xlfn.IFS('03-Concrete'!F19="*",'03-Concrete'!E19,'03-Concrete'!H19="*",'03-Concrete'!G19,'03-Concrete'!J19="*",'03-Concrete'!I19,'03-Concrete'!L19="*",'03-Concrete'!K19,'03-Concrete'!N19="*",'03-Concrete'!M19,'03-Concrete'!P19="*",'03-Concrete'!O19,'03-Concrete'!R19="*",'03-Concrete'!Q19,'03-Concrete'!T19="*",'03-Concrete'!S19,'03-Concrete'!V19="*",'03-Concrete'!U19),"")} | H153: =G153/'Project Data'!$D$22 -> #VALUE!
A154: ='03-Concrete'!A20 -> 0 | B154: ='03-Concrete'!B20 -> 03 03 00 Conservation Treatment for Period Concrete | D154: {=_xlfn.IFNA(_xlfn.IFS('03-Concrete'!D20="*",'03-Concrete'!C20,'03-Concrete'!F20="*",'03-Concrete'!E20,'03-Concrete'!H20="*",'03-Concrete'!G20,'03-Concrete'!J20="*",'03-Concrete'!I20,'03-Concrete'!L20="*",'03-Concrete'!K20,'03-Concrete'!N20="*",'03-Concrete'!M20,'03-Concrete'!P20="*",'03-Concrete'!O20,'03-Concrete'!R20="*",'03-Concrete'!Q20,'03-Concrete'!T20="*",'03-Concrete'!S20),"")} | E154: =D154/'Project Data'!$D$22 -> #VALUE! | G154: {=_xlfn.IFNA(_xlfn.IFS('03-Concrete'!F20="*",'03-Concrete'!E20,'03-Concrete'!H20="*",'03-Concrete'!G20,'03-Concrete'!J20="*",'03-Concrete'!I20,'03-Concrete'!L20="*",'03-Concrete'!K20,'03-Concrete'!N20="*",'03-Concrete'!M20,'03-Concrete'!P20="*",'03-Concrete'!O20,'03-Concrete'!R20="*",'03-Concrete'!Q20,'03-Concrete'!T20="*",'03-Concrete'!S20,'03-Concrete'!V20="*",'03-Concrete'!U20),"")} | H154: =G154/'Project Data'!$D$22 -> #VALUE!
A155: ='03-Concrete'!A21 -> 0 | B155: ='03-Concrete'!B21 -> 03 03 30 Conservation Treatment for Period Cast-in-Place Concrete | D155: {=_xlfn.IFNA(_xlfn.IFS('03-Concrete'!D21="*",'03-Concrete'!C21,'03-Concrete'!F21="*",'03-Concrete'!E21,'03-Concrete'!H21="*",'03-Concrete'!G21,'03-Concrete'!J21="*",'03-Concrete'!I21,'03-Concrete'!L21="*",'03-Concrete'!K21,'03-Concrete'!N21="*",'03-Concrete'!M21,'03-Concrete'!P21="*",'03-Concrete'!O21,'03-Concrete'!R21="*",'03-Concrete'!Q21,'03-Concrete'!T21="*",'03-Concrete'!S21),"")} | E155: =D155/'Project Data'!$D$22 -> #VALUE! | G155: {=_xlfn.IFNA(_xlfn.IFS('03-Concrete'!F21="*",'03-Concrete'!E21,'03-Concrete'!H21="*",'03-Concrete'!G21,'03-Concrete'!J21="*",'03-Concrete'!I21,'03-Concrete'!L21="*",'03-Concrete'!K21,'03-Concrete'!N21="*",'03-Concrete'!M21,'03-Concrete'!P21="*",'03-Concrete'!O21,'03-Concrete'!R21="*",'03-Concrete'!Q21,'03-Concrete'!T21="*",'03-Concrete'!S21,'03-Concrete'!V21="*",'03-Concrete'!U21),"")} | H155: =G155/'Project Data'!$D$22 -> #VALUE!
A156: ='03-Concrete'!A22 -> 0 | B156: ='03-Concrete'!B22 -> 03 03 31 Conservation Treatment for Period Structural Concrete | D156: {=_xlfn.IFNA(_xlfn.IFS('03-Concrete'!D22="*",'03-Concrete'!C22,'03-Concrete'!F22="*",'03-Concrete'!E22,'03-Concrete'!H22="*",'03-Concrete'!G22,'03-Concrete'!J22="*",'03-Concrete'!I22,'03-Concrete'!L22="*",'03-Concrete'!K22,'03-Concrete'!N22="*",'03-Concrete'!M22,'03-Concrete'!P22="*",'03-Concrete'!O22,'03-Concrete'!R22="*",'03-Concrete'!Q22,'03-Concrete'!T22="*",'03-Concrete'!S22),"")} | E156: =D156/'Project Data'!$D$22 -> #VALUE! | G156: {=_xlfn.IFNA(_xlfn.IFS('03-Concrete'!F22="*",'03-Concrete'!E22,'03-Concrete'!H22="*",'03-Concrete'!G22,'03-Concrete'!J22="*",'03-Concrete'!I22,'03-Concrete'!L22="*",'03-Concrete'!K22,'03-Concrete'!N22="*",'03-Concrete'!M22,'03-Concrete'!P22="*",'03-Concrete'!O22,'03-Concrete'!R22="*",'03-Concrete'!Q22,'03-Concrete'!T22="*",'03-Concrete'!S22,'03-Concrete'!V22="*",'03-Concrete'!U22),"")} | H156: =G156/'Project Data'!$D$22 -> #VALUE!
... A200: ='03-Concrete'!A66 -> 0 | B200: ='03-Concrete'!B66 -> 03 30 53 Miscellaneous Cast-in-Place Concrete | D200: {=_xlfn.IFNA(_xlfn.IFS('03-Concrete'!D66="*",'03-Concrete'!C66,'03-Concrete'!F66="*",'03-Concrete'!E66,'03-Concrete'!H66="*",'03-Concrete'!G66,'03-Concrete'!J66="*",'03-Concrete'!I66,'03-Concrete'!L66="*",'03-Concrete'!K66,'03-Concrete'!N66="*",'03-Concrete'!M66,'03-Concrete'!P66="*",'03-Concrete'!O66,'03-Concrete'!R66="*",'03-Concrete'!Q66,'03-Concrete'!T66="*",'03-Concrete'!S66),"")} | E200: =D200/'Project Data'!$D$22 -> #VALUE! | G200: {=_xlfn.IFNA(_xlfn.IFS('03-Concrete'!F66="*",'03-Concrete'!E66,'03-Concrete'!H66="*",'03-Concrete'!G66,'03-Concrete'!J66="*",'03-Concrete'!I66,'03-Concrete'!L66="*",'03-Concrete'!K66,'03-Concrete'!N66="*",'03-Concrete'!M66,'03-Concrete'!P66="*",'03-Concrete'!O66,'03-Concrete'!R66="*",'03-Concrete'!Q66,'03-Concrete'!T66="*",'03-Concrete'!S66,'03-Concrete'!V66="*",'03-Concrete'!U66),"")} | H200: =G200/'Project Data'!$D$22 -> #VALUE!
A201: ='03-Concrete'!A67 -> 1 | B201: ='03-Concrete'!B67 -> 03 31 00 Structural Concrete | D201: {=_xlfn.IFNA(_xlfn.IFS('03-Concrete'!D67="*",'03-Concrete'!C67,'03-Concrete'!F67="*",'03-Concrete'!E67,'03-Concrete'!H67="*",'03-Concrete'!G67,'03-Concrete'!J67="*",'03-Concrete'!I67,'03-Concrete'!L67="*",'03-Concrete'!K67,'03-Concrete'!N67="*",'03-Concrete'!M67,'03-Concrete'!P67="*",'03-Concrete'!O67,'03-Concrete'!R67="*",'03-Concrete'!Q67,'03-Concrete'!T67="*",'03-Concrete'!S67),"")} -> 2242500 | E201: =D201/'Project Data'!$D$22 -> 25.058386 | F201: 2242500 | G201: {=_xlfn.IFNA(_xlfn.IFS('03-Concrete'!F67="*",'03-Concrete'!E67,'03-Concrete'!H67="*",'03-Concrete'!G67,'03-Concrete'!J67="*",'03-Concrete'!I67,'03-Concrete'!L67="*",'03-Concrete'!K67,'03-Concrete'!N67="*",'03-Concrete'!M67,'03-Concrete'!P67="*",'03-Concrete'!O67,'03-Concrete'!R67="*",'03-Concrete'!Q67,'03-Concrete'!T67="*",'03-Concrete'!S67,'03-Concrete'!V67="*",'03-Concrete'!U67),"")} -> 2242500 | H201: =G201/'Project Data'!$D$22 -> 25.058386 | K201: Allen
A202: ='03-Concrete'!A68 -> 0 | B202: ='03-Concrete'!B68 -> 03 31 13 Heavyweight Structural Concrete | D202: {=_xlfn.IFNA(_xlfn.IFS('03-Concrete'!D68="*",'03-Concrete'!C68,'03-Concrete'!F68="*",'03-Concrete'!E68,'03-Concrete'!H68="*",'03-Concrete'!G68,'03-Concrete'!J68="*",'03-Concrete'!I68,'03-Concrete'!L68="*",'03-Concrete'!K68,'03-Concrete'!N68="*",'03-Concrete'!M68,'03-Concrete'!P68="*",'03-Concrete'!O68,'03-Concrete'!R68="*",'03-Concrete'!Q68,'03-Concrete'!T68="*",'03-Concrete'!S68),"")} | E202: =D202/'Project Data'!$D$22 -> #VALUE! | G202: {=_xlfn.IFNA(_xlfn.IFS('03-Concrete'!F68="*",'03-Concrete'!E68,'03-Concrete'!H68="*",'03-Concrete'!G68,'03-Concrete'!J68="*",'03-Concrete'!I68,'03-Concrete'!L68="*",'03-Concrete'!K68,'03-Concrete'!N68="*",'03-Concrete'!M68,'03-Concrete'!P68="*",'03-Concrete'!O68,'03-Concrete'!R68="*",'03-Concrete'!Q68,'03-Concrete'!T68="*",'03-Concrete'!S68,'03-Concrete'!V68="*",'03-Concrete'!U68),"")} | H202: =G202/'Project Data'!$D$22 -> #VALUE!
...

Sheet Project Data
A2: Prepared By: | B2: CS
B3: Date: | C3: Rev. | D3: 1 | G3: Alexa Sass: PM/Designer
B4: Josephine Apartments (3rd Ave.) | G4: Sinatra Development LLC
B5: 3rd Avenue | G5: asass@sinatraandcompany.com
G6: 716-345-8673
G8: Cole T. Hatley
G9: VP of Construction Management Ops
G10: Sinatra Development LLC
B11: Project SF Items to be broken-out: | C11: Acres | D11: SF | G11: chatley@sinatraandcompany.com
B12: Site
B13: Site in SF (43,560 SF = 1 Acre) | C13: 9 | D13: =C13*43560 -> 392040 | E13: Notes:
B14: Building Footprint | D14: 20117
B15: Asphalt paving | D15: 25000
B16: Concrete paving Include curb and gutter | D16: 10000
B17: Concrete flat work and sidewalk | D17: 4000
B18: Brick pavers | D18: 5000
B19: Landscaped area (Landscape = Site - Bldg. FP - Pavement - Flatwork - Pavers) | D19: =D13-SUM(D14:D18) -> 327923
B21: Building
B22: Building GSF | D22: 89491
B23: Unit Quanity | D23: 99
B24: # Floors including basement | D24: 4
B25: # elevators | D25: 1
B26: Exterior finishes
B27: Masonry | D27: 6000
B28: Metal pannel | D28: 4500
B29: Siding | D29: 1200
B30: Exteior paint | D30: 1200
B31: Storefront | D31: 2600
B32: Windows | D32: 4000
B33: Finishes (GSF)
C37: %
B38: Contractor Contingency | C38: 0.05
B39: GL/PL Insurance: | C39: 0.012
B40: Performance Bond: | C40: 0
B41: GC Fee: | C41: 0.05
B42: Escalation | C42: 0
E5121: =(E5118+E5119+E5120)*#REF! -> #REF!

Sheet GCGR's
A2: STAFF PLAN
A3: SCHEDULE | C3: YEAR | D3: 2026 | E3: 2026 | F3: 2026 | G3: 2026 | H3: 2026 | I3: 2026 | J3: 2026 | K3: 2026 | L3: 2026 | M3: 2027 | N3: 2027 | O3: 2027 | P3: 2027 | Q3: 2027 | R3: 2027 | S3: 2027 | T3: 2027 | U3: 2027 | V3: 2027 | W3: 2027 | X3: 2027 | Y3: 2028 | Z3: 2028 | AA3: 2028 | AB3: 2028 | AC3: 2028
C4: DURATION | D4: {=_xlfn.IFS($B$10,1)} -> 1 | E4: {=_xlfn.IFS($B$10>D4,D4+1,D4<$B$10,0)} -> 2 | F4: {=_xlfn.IFS($B$10>E4,E4+1,E4<$B$10,0)} -> 3 | G4: {=_xlfn.IFS($B$10>F4,F4+1,F4<$B$10,0)} -> 4 | H4: {=_xlfn.IFS($B$10>G4,G4+1,G4<$B$10,0)} -> 5 | I4: {=_xlfn.IFS($B$10>H4,H4+1,H4<$B$10,0)} -> 6 | J4: {=_xlfn.IFS($B$10>I4,I4+1,I4<$B$10,0)} -> 7 | K4: {=_xlfn.IFS($B$10>J4,J4+1,J4<$B$10,0)} -> 8 | L4: {=_xlfn.IFS($B$10>K4,K4+1,K4<$B$10,0)} -> 9 | ... AC4: {=_xlfn.IFS($B$10>AB4,AB4+1,AB4<$B$10,0)} -> #N/A
C5: MONTH | D5: APR | E5: MAY | F5: JUN | G5: JULY | H5: AUG | I5: SEP | J5: OCT | K5: NOV | L5: DEC | M5: JAN | N5: FEB | O5: MAR | P5: APR | Q5: MAY | R5: JUNE | S5: JULY | T5: AUGUST | U5: SEPTEMBER | V5: OCTOBER | W5: NOVEMBER | X5: DECEMBER | Y5: JANUARY | Z5: FEBRUARY | AA5: MARCH | AB5: APRIL | AC5: MAY
A7: Anticipated Notice to Proceed:
A8: Preconstruction Duration (Months) | B8: NA
A9: Construction Start | B9: 46114
A10: Construction Duration (Months) | B10: =(B12-B9)/30.147 -> 11.941487 | D10: =D4 -> 1 | E10: =E4 -> 2 | F10: =F4 -> 3 | G10: =G4 -> 4 | H10: =H4 -> 5 | I10: =I4 -> 6 | J10: =J4 -> 7 | K10: =K4 -> 8 | ... AC10: =AC4 -> #N/A
A11: Building Enclosed | B11: 46327
A12: Substantial Completion / Cert of Occupancy | B12: 46474
A13: Closeout/Punchlist | B13: 46479
A15: STAFF PLAN | D15: =D5 -> APR | E15: =E5 -> MAY | F15: =F5 -> JUN | G15: =G5 -> JULY | H15: =H5 -> AUG | I15: =I5 -> SEP | J15: =J5 -> OCT | K15: =K5 -> NOV | ... AC15: =AC5 -> MAY | AD15: NOTES | AE15: RATES | AG15: DO NOT ENTER RATES HERE
A16: MANAGEMENT | AE16: MANAGEMENT | AF16: TOTAL HOURS | AG16: RATE / HR. | AH16: RATE/MO. | AI16: TOTAL
A17: Project Executive | B17: N&A | D17: 0 | E17: 0 | F17: 0 | G17: 0 | H17: 0 | I17: 0 | J17: 0 | K17: 0 | L17: 0 | M17: 0 | N17: 0 | O17: 0 | AE17: =A17 -> Project Executive | AF17: =SUM(D17:AC17) -> 0 | AG17: 150 | AI17: =AF17*AG17 -> 0
A18: Senior Project Manager | B18: N&A | D18: =(2080/12)*0.05 -> 8.6666667 | E18: =(2080/12)*0.05 -> 8.6666667 | F18: =(2080/12)*0.05 -> 8.6666667 | G18: =(2080/12)*0.05 -> 8.6666667 | H18: =(2080/12)*0.05 -> 8.6666667 | I18: =(2080/12)*0.05 -> 8.6666667 | J18: =(2080/12)*0.05 -> 8.6666667 | K18: =(2080/12)*0.05 -> 8.6666667 | ... O18: =(2080/12)*0.05 -> 8.6666667 | AE18: =A18 -> Senior Project Manager | AF18: =SUM(D18:AC18) -> 104 | AG18: 150 | AI18: =AF18*AG18 -> 15600
A19: Project Manager | B19: N&A | D19: =(2080/12)*0.2 -> 34.666667 | E19: =(2080/12)*0.2 -> 34.666667 | F19: =(2080/12)*0.2 -> 34.666667 | G19: =(2080/12)*0.2 -> 34.666667 | H19: =(2080/12)*0.2 -> 34.666667 | I19: =(2080/12)*0.2 -> 34.666667 | J19: =(2080/12)*0.2 -> 34.666667 | K19: =(2080/12)*0.2 -> 34.666667 | ... O19: =(2080/12)*0.2 -> 34.666667 | AE19: =A19 -> Project Manager | AF19: =SUM(D19:AC19) -> 416 | AG19: 145 | AI19: =AF19*AG19 -> 60320
A20: Project Engineer | B20: N&A | D20: =(2080/12)*0.15 -> 26 | E20: =(2080/12)*0.15 -> 26 | F20: =(2080/12)*0.15 -> 26 | G20: =(2080/12)*0.15 -> 26 | H20: =(2080/12)*0.15 -> 26 | I20: =(2080/12)*0.15 -> 26 | J20: =(2080/12)*0.15 -> 26 | K20: =(2080/12)*0.15 -> 26 | ... O20: =(2080/12)*0.15 -> 26 | AE20: =A20 -> Project Engineer | AF20: =SUM(D20:AC20) -> 312 | AG20: 115 | AI20: =AF20*AG20 -> 35880
A21: FIELD | AE21: =A21 -> FIELD | AF21: =SUM(D21:AC21) -> 0
A22: Senior Superintendent | B22: N&A | D22: =(2080/12)*0.05 -> 8.6666667 | E22: =(2080/12)*0.05 -> 8.6666667 | F22: =(2080/12)*0.05 -> 8.6666667 | G22: =(2080/12)*0.05 -> 8.6666667 | H22: =(2080/12)*0.05 -> 8.6666667 | I22: =(2080/12)*0.05 -> 8.6666667 | J22: =(2080/12)*0.05 -> 8.6666667 | K22: =(2080/12)*0.05 -> 8.6666667 | ... O22: =(2080/12)*0.05 -> 8.6666667 | AE22: =A22 -> Senior Superintendent | AF22: =SUM(D22:AC22) -> 104 | AG22: 140 | AI22: =AF22*AG22 -> 14560
A23: Superintendent | B23: N&A | D23: =(2080/12)*1 -> 173.33333 | E23: =(2080/12)*1 -> 173.33333 | F23: =(2080/12)*1 -> 173.33333 | G23: =(2080/12)*1 -> 173.33333 | H23: =(2080/12)*1 -> 173.33333 | I23: =(2080/12)*1 -> 173.33333 | J23: =(2080/12)*1 -> 173.33333 | K23: =(2080/12)*1 -> 173.33333 | ... O23: =(2080/12)*1 -> 173.33333 | AE23: =A23 -> Superintendent | AF23: =SUM(D23:AC23) -> 2080 | AG23: 135 | AI23: =AF23*AG23 -> 280800
A24: Assistant Superintendent | B24: N&A | D24: =(2080/12)*1 -> 173.33333 | E24: =(2080/12)*1 -> 173.33333 | F24: =(2080/12)*1 -> 173.33333 | G24: =(2080/12)*1 -> 173.33333 | H24: =(2080/12)*1 -> 173.33333 | I24: =(2080/12)*1 -> 173.33333 | J24: =(2080/12)*1 -> 173.33333 | K24: =(2080/12)*1 -> 173.33333 | ... O24: =(2080/12)*1 -> 173.33333 | AE24: =A24 -> Assistant Superintendent | AF24: =SUM(D24:AC24) -> 2080 | AG24: 110 | AI24: =AF24*AG24 -> 228800
A25: Laborer | B25: N&A | D25: =(2080/12)*0.25 -> 43.333333 | E25: =(2080/12)*0.25 -> 43.333333 | F25: =(2080/12)*0.25 -> 43.333333 | G25: =(2080/12)*0.25 -> 43.333333 | H25: =(2080/12)*0.25 -> 43.333333 | I25: =(2080/12)*0.25 -> 43.333333 | J25: =(2080/12)*0.25 -> 43.333333 | K25: =(2080/12)*0.25 -> 43.333333 | ... O25: =(2080/12)*0.25 -> 43.333333 | AE25: =A25 -> Laborer | AF25: =SUM(D25:AC25) -> 520 | AG25: 90 | AI25: =AF25*AG25 -> 46800
A26: SUPPORT | AE26: =A26 -> SUPPORT | AF26: =SUM(D26:AC26) -> 0
A27: Preconstruction Manager | B27: N&A | AE27: =A27 -> Preconstruction Manager | AF27: =SUM(D27:AC27) -> 0 | AG27: 0
A28: Project Administrative Assistant | B28: N&A | D28: =(2080/12)*0.25 -> 43.333333 | E28: =(2080/12)*0.25 -> 43.333333 | F28: =(2080/12)*0.25 -> 43.333333 | G28: =(2080/12)*0.25 -> 43.333333 | H28: =(2080/12)*0.25 -> 43.333333 | I28: =(2080/12)*0.05 -> 8.6666667 | J28: =(2080/12)*0.05 -> 8.6666667 | K28: =(2080/12)*0.05 -> 8.6666667 | L28: =(2080/12)*0.05 -> 8.6666667 | M28: =(2080/12)*0.25 -> 43.333333 | N28: =(2080/12)*0.25 -> 43.333333 | O28: =(2080/12)*0.25 -> 43.333333 | AE28: =A28 -> Project Administrative Assistant | AF28: =SUM(D28:AC28) -> 381.33333 | AG28: 65 | AI28: =AF28*AG28 -> 24786.667
A29: Project Accounting | B29: N&A | D29: 10 | E29: 10 | F29: 10 | G29: 10 | H29: 10 | I29: 10 | J29: 10 | K29: 10 | L29: 10 | M29: 10 | N29: 10 | O29: 10 | AE29: =A29 -> Project Accounting | AF29: =SUM(D29:AC29) -> 120 | AG29: 65 | AI29: =AF29*AG29 -> 7800
A30: TOTAL STAFFING | D30: =SUM(D17:D29) -> 521.33333 | E30: =SUM(E17:E29) -> 521.33333 | F30: =SUM(F17:F29) -> 521.33333 | G30: =SUM(G17:G29) -> 521.33333 | H30: =SUM(H17:H29) -> 521.33333 | I30: =SUM(I17:I29) -> 486.66667 | J30: =SUM(J17:J29) -> 486.66667 | K30: =SUM(K17:K29) -> 486.66667 | ... AC30: =SUM(AC17:AC29) -> 0 | AE30: TOTAL HOURS / MANPOWER COSTS | AF30: =SUM(AF17:AF29) -> 6117.3333 | AG30: TOTAL w/ benefits | AI30: =SUM(AI17:AI29) -> 715346.67
A31: GENERAL CONDITIONS & REIMBURSABLES | AD31: NOTES
D33: =D5 -> APR | E33: =E5 -> MAY | F33: =F5 -> JUN | G33: =G5 -> JULY | H33: =H5 -> AUG | I33: =I5 -> SEP | J33: =J5 -> OCT | K33: =K5 -> NOV | ... AC33: =AC5 -> MAY | AE33: EXPENSES
A34: Safety Director | B34: LS | C34: $400 per Audit | D34: 0 | E34: 0 | F34: 0 | G34: 0 | H34: 0 | I34: 0 | J34: 0 | O34: 0 | AE34: =A34 -> Safety Director | AF34: =SUM(D34:AC34) -> 0
A35: Site cleaning | B35: months | D35: 0 | E35: 0 | F35: 0 | G35: 0 | H35: 0 | I35: 0 | J35: 0 | O35: 0 | AE35: =A35 -> Site cleaning | AF35: =SUM(D35:AC35) -> 0
A36: Printer & Network | B36: months | D36: 200 | E36: 200 | F36: 200 | G36: 200 | H36: 200 | I36: 200 | J36: 200 | K36: 200 | L36: 200 | M36: 200 | N36: 200 | O36: 200 | AE36: =A36 -> Printer & Network | AF36: =SUM(D36:AC36) -> 2400
A37: Computers | B37: months | D37: 125 | E37: 125 | F37: 125 | G37: 125 | H37: 125 | I37: 125 | J37: 125 | K37: 125 | L37: 125 | M37: 125 | N37: 125 | O37: 125 | AE37: =A37 -> Computers | AF37: =SUM(D37:AC37) -> 1500
A38: Copying & Reproduction | B38: months | D38: 250 | E38: 250 | F38: 250 | G38: 250 | H38: 250 | I38: 100 | J38: 100 | K38: 100 | L38: 100 | M38: 100 | N38: 100 | O38: 100 | AE38: =A38 -> Copying & Reproduction | AF38: =SUM(D38:AC38) -> 1950
A39: Dumpsters | B39: months | F39: 1000 | G39: 1000 | H39: 1000 | I39: 1000 | J39: 1000 | K39: 2000 | L39: 2000 | M39: 2000 | N39: 1000 | O39: 1000 | AE39: =A39 -> Dumpsters | AF39: =SUM(D39:AC39) -> 13000
A40: Estimating Services | B40: LS | AE40: =A40 -> Estimating Services | AF40: =SUM(D40:AC40) -> 0
A41: Final Cleaning | B41: LS | N41: 35412 | O41: 35412 | AE41: =A41 -> Final Cleaning | AF41: =SUM(D41:AC41) -> 70824
A42: Miscellaneous General Expense | B42: months | AE42: =A42 -> Miscellaneous General Expense | AF42: =SUM(D42:AC42) -> 0
A43: Office Equipment & Supplies | B43: months | D43: 100 | E43: 100 | F43: 100 | G43: 100 | H43: 100 | I43: 100 | J43: 100 | K43: 100 | L43: 100 | M43: 100 | N43: 100 | O43: 100 | AE43: =A43 -> Office Equipment & Supplies | AF43: =SUM(D43:AC43) -> 1200
A44: Project Signage (General Contractor) | B44: LS | D44: 500 | E44: 500 | N44: 500 | O44: 500 | AE44: =A44 -> Project Signage (General Contractor) | AF44: =SUM(D44:AC44) -> 2000
A45: Safety & Protection - Labor | B45: months | D45: 250 | E45: 250 | F45: 250 | G45: 250 | H45: 250 | I45: 500 | J45: 500 | K45: 500 | L45: 500 | M45: 500 | N45: 500 | O45: 500 | AE45: =A45 -> Safety & Protection - Labor | AF45: =SUM(D45:AC45) -> 4750
A46: Safety & Protection - Material | B46: months | D46: 100 | E46: 100 | F46: 100 | G46: 100 | H46: 100 | I46: 250 | J46: 250 | K46: 250 | L46: 250 | M46: 250 | N46: 250 | O46: 250 | AE46: =A46 -> Safety & Protection - Material | AF46: =SUM(D46:AC46) -> 2250
A47: Site Fencing (In Excavation) | B47: LS | D47: 51353 | AE47: =A47 -> Site Fencing (In Excavation) | AF47: =SUM(D47:AC47) -> 51353
A48: Erosion Control (In Excavating) | B48: LS | AE48: =A48 -> Erosion Control (In Excavating) | AF48: =SUM(D48:AC48) -> 0
A49: Surveying | B49: LS | AE49: =A49 -> Surveying | AF49: =SUM(D49:AC49) -> 0
A50: Street Cleaning/Snow Plowing | B50: LS | D50: 1000 | E50: 1000 | F50: 1000 | G50: 500 | H50: 500 | I50: 500 | J50: 500 | K50: 500 | L50: 1000 | M50: 1000 | N50: 1000 | O50: 1000 | AE50: =A50 -> Street Cleaning/Snow Plowing | AF50: =SUM(D50:AC50) -> 9500
A51: Temp Fire Extinguishers | B51: LS | D51: 300 | I51: 500 | AE51: =A51 -> Temp Fire Extinguishers | AF51: =SUM(D51:AC51) -> 800
A52: Temporary Office Trailer | B52: months | D52: 5000 | E52: 1200 | F52: 1200 | G52: 1200 | H52: 1200 | I52: 1200 | J52: 1200 | K52: 1200 | L52: 1200 | M52: 1200 | N52: 1200 | O52: 1200 | AE52: =A52 -> Temporary Office Trailer | AF52: =SUM(D52:AC52) -> 18200
A53: Temporary Toilets | B53: months | D53: =120*2 -> 240 | E53: =120*2 -> 240 | F53: =120*2 -> 240 | G53: =120*2 -> 240 | H53: =240*4 -> 960 | I53: =240*4 -> 960 | J53: =240*4 -> 960 | K53: =240*4 -> 960 | L53: =240*4 -> 960 | M53: =240*4 -> 960 | N53: =240*4 -> 960 | O53: =240*4 -> 960 | AE53: =A53 -> Temporary Toilets | AF53: =SUM(D53:AC53) -> 8640
A54: Temporary Heat - Equipment | B54: months | J54: 250 | K54: 250 | L54: 250 | M54: 250 | N54: 250 | O54: 250 | AE54: =A54 -> Temporary Heat - Equipment | AF54: =SUM(D54:AC54) -> 1500
A55: Temporary Heat - Propane/Gas | B55: months | J55: 500 | K55: 500 | L55: 500 | M55: 500 | N55: 500 | O55: 500 | AE55: =A55 -> Temporary Heat - Propane/Gas | AF55: =SUM(D55:AC55) -> 3000
A56: Temporary Heat - Materials | B56: months | J56: 100 | K56: 100 | L56: 100 | M56: 100 | N56: 100 | O56: 100 | AE56: =A56 -> Temporary Heat - Materials | AF56: =SUM(D56:AC56) -> 600
A57: Temp Board Up | B57: months | J57: 500 | K57: 500 | L57: 500 | AE57: =A57 -> Temp Board Up | AF57: =SUM(D57:AC57) -> 1500
A58: Temporary Partitions - Materials | B58: months | AE58: =A58 -> Temporary Partitions - Materials | AF58: =SUM(D58:AC58) -> 0
A59: Temporary Electrical for Utilities | B59: months | D59: 5000 | E59: 500 | F59: 500 | G59: 500 | H59: 500 | I59: 500 | J59: 500 | O59: 500 | AE59: =A59 -> Temporary Electrical for Utilities | AF59: =SUM(D59:AC59) -> 8500
A60: Testing and Inspection | B60: months | AE60: =A60 -> Testing and Inspection | AF60: =SUM(D60:AC60) -> 0
A61: Graffiti Removal | B61: Fixed Cost | D61: 5000 | AE61: =A61 -> Graffiti Removal | AF61: =SUM(D61:AC61) -> 5000
A62: Security Cameras | B62: LS | D62: =2000+5000 -> 7000 | E62: 259 | F62: 259 | G62: 259 | H62: 259 | I62: 259 | J62: 259 | K62: 259 | L62: 259 | M62: 259 | N62: 259 | O62: 259 | AE62: =A62 -> Security Cameras | AF62: =SUM(D62:AC62) -> 9849
A63: Winter Conditions | B63: In Trades | AE63: =A63 -> Winter Conditions | AF63: =SUM(D63:AC63) -> 0
A64: Temp Power and Lighting (M&L) | B64: In Trades | AE64: =A64 -> Temp Power and Lighting (M&L) | AF64: =SUM(D64:AC64) -> 0
A65: Flagger | B65: LS | D65: =20*900 -> 18000 | E65: =20*900 -> 18000 | F65: =20*900 -> 18000 | G65: =20*900 -> 18000 | H65: =20*900 -> 18000 | I65: =20*900 -> 18000 | AE65: =A65 -> Flagger | AF65: =SUM(D65:AC65) -> 108000
A66: Initial Fall Protection | B66: In Trades | AE66: =A66 -> Initial Fall Protection | AF66: =SUM(D66:AC66) -> 0
A67: Permits/Fees | B67: Owner | AE67: =A67 -> Permits/Fees | AF67: =SUM(D67:AC67) -> 0
A68: Lane closures (Permit costs) | B68: Owner | AE68: =A68 -> Lane closures (Permit costs) | AF68: =SUM(D68:AC68) -> 0
A69: TOTAL EXPENSES | D69: =SUM(D34:D68) -> 94418 | E69: =SUM(E34:E68) -> 22724 | F69: =SUM(F34:F68) -> 23224 | G69: =SUM(G34:G68) -> 22724 | H69: =SUM(H34:H68) -> 23444 | I69: =SUM(I34:I68) -> 24194 | J69: =SUM(J34:J68) -> 7044 | K69: =SUM(K34:K68) -> 7544 | ... AC69: =SUM(AC34:AC68) -> 0 | AE69: TOTAL EXPENSES | AF69: =SUM(AF34:AF68) -> 326316
A70: NOTES | AE70: TOTAL GENERAL CONDITIONS | AF70: =AF69+AI30+AG70 -> 1301431.7 | AG70: 259769
AF71: MAKE THIS 7% of subtotal

Sheet Historical
E7: DIV | F7: Value | G7: Trade | H7: Subcontractor | I7: Description
E8: 5 | F8: 6380 | G8: Railings | H8: KN Edwards | I8: picket railing

Sheet 02-Existing Conditions
C1: Quantity | D1: Unit Pricing | E1: Nicholas Estimate | F1: *= Use | G1: Final Cleaning | H1: Survey | I1: Final Cleaning | J1: Final Cleaning | K1: Final Cleaning | L1: Final Cleaning | M1: Final Cleaning | N1: Inspections: Do we need this ? | O1: Final Cleaning | P1: Final Cleaning | Q1: Testing | R1: Testing | S1: Testing | T1: Testing | U1: Final Cleaning | V1: *= Use | W1: Survey | X1: Final Cleaning | Z1: Testing | AA1: Surveying | AB1: Final Cleaning | AC1: Final Cleaning | AD1: Surveying | AE1: Testing | AF1: Cleaning | AG1: Cleaning | AH1: Cleaning
A2: Prepared By: | G2: Peak Cleaners | H2: On Point | I2: Britlena Cleaning Services | J2: Florida Construction Cleanup | K2: Florida Construction Cleanup | L2: Rosies | M2: Peak Cleaners | N2: Strategic Engineering | O2: Proline Cleaners | P2: Kirocz Cleaning Services | Q2: Intertek | R2: Deatrick Engineering | S2: Team UES | T2: Pacson | U2: Greta Cleaning Services | W2: Ferguson Land Surveyors | X2: AMAH | Z2: Terracon | AA2: Angleright | AB2: Avi & Park Solutions | AC2: Florida Coast | AD2: American Layout & Land Surveying | AE2: Pacifica | AF2: Polished Perfection Cleaning | AG2: BrightSite Cleaning | AH2: Final Touch
B3: Contact: | G3: Aliya Jay: Dor of Ops | H3: Sashy Fabrelle | I3: Missalena Khan | J3: Irina Kotsyuba | L3: Francine Gomes | M3: Hope Martinez | N3: Kasey Bussey | O3: Timothy Storck | P3: Estimating | Q3: Erika Moreno | R3: Kiara J Torres Lopez | S3: Brian Meikle | T3: Pierre Jeune | U3: Jenny Tovar | W3: Scott Acker | AE3: Martin Verbus
B4: Phone: | G4: 843-252-0605 | H4: 407-989-8178 | I4: 407-595-9121 cell | J4: 239-744-9682 | L4: 561-545-3260 | M4: 931-414-5488 | N4: 813-658-8753 | O4: 727-240-6205 | P4: 813-399-6628 | R4: 407-851-9776 | S4: 407-536-9213 | T4: 813-860-2076 | U4: 941-210-1819 | W4: 727-230-9606 | AE4: 561-419-8460
B5: Email: | G5: aliya@peakcleanersnc.com | H5: marketing@on-pointsurveying.com | I5: missalenakhan@yahoo.com | J5: irina@flconstructioncleanup.com | L5: rosiescleaning21@gmail.com | M5: hope@peakcleanersnc.com | N5: kbussey@strategiceng.com | O5: contact@prolinecleans.com | P5: kiroczcleaningservices@gmail.com | Q5: erika.moreno@intertek.com | R5: deal1@bellsouth.net | S5: bmeikle@teamues.com | T5: pjeune@pacscon.com | U5: gcsoffice@gretacleaningservices.com | W5: scott@flsurveyors.com | AE5: mverbus@pacificaes.com
B6: Date: | H6: 46036 | J6: 46037 | L6: 46037 | N6: 46387 | O6: 46031 | Q6: 46037 | R6: 46037 | T6: 46034 | U6: 46037 | W6: 46038 | AE6: 46042
B7: Base Bid:
B8: Accepted Alternates:
A9: 1= Use | B9: Total: | E9: =SUM(E11:E307) -> 121952 | F9: * | G9: =SUM(G11:G307) -> 0 | H9: =SUM(H10:H48) -> 0 | I9: =SUM(I11:I307) -> 0 | J9: =J45 -> 47900 | K9: 41700 | M9: =SUM(M11:M307) -> 0 | O9: =SUM(O11:O307) -> 0 | Q9: =SUM(Q11:Q307) -> 55749 | S9: =SUM(S11:S307) -> 0 | T9: =T40 -> 21238 | U9: =SUM(U11:U307) -> 0 | W9: =SUM(W11:W307) -> 34900 | X9: =SUM(X11:X307) -> 119990 | Y9: =SUM(Y11:Y307) -> 0 | Z9: =SUM(Z11:Z307) -> 52547 | AA9: =SUM(AA11:AA307) -> 30000 | AB9: =SUM(AB11:AB307) -> 129500 | AC9: =SUM(AC11:AC307) -> 0 | AD9: =SUM(AD11:AD307) -> 20700 | AE9: =AE40 -> 28115 | AF9: =SUM(AF40:AF48) -> 38900 | AG9: =SUM(AG21:AG51) -> 43954 | AH9: =SUM(AH21:AH64) -> 55775 | XFC9: =IF(XFD9="**","ERROR","") | XFD9: =CONCATENATE(F9,H9,J9,L9,N9,P9,R9,T9,V9) -> 021238
A10: Filter
B11: 02 00 00 Existing Conditions | F11: =IF($F$9="*",IF(E11>0,"*",""),"") | H11: =IF($H$9="*",IF(G11>0,"*",""),"") | J11: =IF($J$9="*",IF(I11>0,"*",""),"") | L11: =IF($L$9="*",IF(K11>0,"*",""),"") | N11: =IF($N$9="*",IF(M11>0,"*",""),"") | P11: =IF($P$9="*",IF(O11>0,"*",""),"") | R11: =IF($R$9="*",IF(Q11>0,"*",""),"") | T11: =IF($T$9="*",IF(S11>0,"*",""),"") | V11: =IF($V$9="*",IF(U11>0,"*",""),"")
B12: 02 03 00 Conservation Treatment for Existing Period Conditions | F12: =IF($F$9="*",IF(E12>0,"*",""),"") | H12: =IF($H$9="*",IF(G12>0,"*",""),"") | J12: =IF($J$9="*",IF(I12>0,"*",""),"") | L12: =IF($L$9="*",IF(K12>0,"*",""),"") | N12: =IF($N$9="*",IF(M12>0,"*",""),"") | P12: =IF($P$9="*",IF(O12>0,"*",""),"") | R12: =IF($R$9="*",IF(Q12>0,"*",""),"") | T12: =IF($T$9="*",IF(S12>0,"*",""),"") | V12: =IF($V$9="*",IF(U12>0,"*",""),"")
B13: 02 05 00 Common Work Results for Existing Conditions | F13: =IF($F$9="*",IF(E13>0,"*",""),"") | H13: =IF($H$9="*",IF(G13>0,"*",""),"") | J13: =IF($J$9="*",IF(I13>0,"*",""),"") | L13: =IF($L$9="*",IF(K13>0,"*",""),"") | N13: =IF($N$9="*",IF(M13>0,"*",""),"") | P13: =IF($P$9="*",IF(O13>0,"*",""),"") | R13: =IF($R$9="*",IF(Q13>0,"*",""),"") | T13: =IF($T$9="*",IF(S13>0,"*",""),"") | V13: =IF($V$9="*",IF(U13>0,"*",""),"")
B14: 02 06 00 Schedules for Existing Conditions | F14: =IF($F$9="*",IF(E14>0,"*",""),"") | H14: =IF($H$9="*",IF(G14>0,"*",""),"") | J14: =IF($J$9="*",IF(I14>0,"*",""),"") | L14: =IF($L$9="*",IF(K14>0,"*",""),"") | N14: =IF($N$9="*",IF(M14>0,"*",""),"") | P14: =IF($P$9="*",IF(O14>0,"*",""),"") | R14: =IF($R$9="*",IF(Q14>0,"*",""),"") | T14: =IF($T$9="*",IF(S14>0,"*",""),"") | V14: =IF($V$9="*",IF(U14>0,"*",""),"")
B15: 02 06 30 Schedules for Subsurface Investigations | F15: =IF($F$9="*",IF(E15>0,"*",""),"") | H15: =IF($H$9="*",IF(G15>0,"*",""),"") | J15: =IF($J$9="*",IF(I15>0,"*",""),"") | L15: =IF($L$9="*",IF(K15>0,"*",""),"") | N15: =IF($N$9="*",IF(M15>0,"*",""),"") | P15: =IF($P$9="*",IF(O15>0,"*",""),"") | R15: =IF($R$9="*",IF(Q15>0,"*",""),"") | T15: =IF($T$9="*",IF(S15>0,"*",""),"") | V15: =IF($V$9="*",IF(U15>0,"*",""),"")
B16: 02 06 30.13 Boring or Test Pit Log Schedule | F16: =IF($F$9="*",IF(E16>0,"*",""),"") | H16: =IF($H$9="*",IF(G16>0,"*",""),"") | J16: =IF($J$9="*",IF(I16>0,"*",""),"") | L16: =IF($L$9="*",IF(K16>0,"*",""),"") | N16: =IF($N$9="*",IF(M16>0,"*",""),"") | P16: =IF($P$9="*",IF(O16>0,"*",""),"") | R16: =IF($R$9="*",IF(Q16>0,"*",""),"") | T16: =IF($T$9="*",IF(S16>0,"*",""),"") | V16: =IF($V$9="*",IF(U16>0,"*",""),"")
B17: 02 06 50 Schedules for Site Remediation | F17: =IF($F$9="*",IF(E17>0,"*",""),"") | H17: =IF($H$9="*",IF(G17>0,"*",""),"") | J17: =IF($J$9="*",IF(I17>0,"*",""),"") | L17: =IF($L$9="*",IF(K17>0,"*",""),"") | N17: =IF($N$9="*",IF(M17>0,"*",""),"") | P17: =IF($P$9="*",IF(O17>0,"*",""),"") | R17: =IF($R$9="*",IF(Q17>0,"*",""),"") | T17: =IF($T$9="*",IF(S17>0,"*",""),"") | V17: =IF($V$9="*",IF(U17>0,"*",""),"")
B18: 02 06 65 Schedules for Underground Storage Tank Removal | F18: =IF($F$9="*",IF(E18>0,"*",""),"") | H18: =IF($H$9="*",IF(G18>0,"*",""),"") | J18: =IF($J$9="*",IF(I18>0,"*",""),"") | L18: =IF($L$9="*",IF(K18>0,"*",""),"") | N18: =IF($N$9="*",IF(M18>0,"*",""),"") | P18: =IF($P$9="*",IF(O18>0,"*",""),"") | R18: =IF($R$9="*",IF(Q18>0,"*",""),"") | T18: =IF($T$9="*",IF(S18>0,"*",""),"") | V18: =IF($V$9="*",IF(U18>0,"*",""),"")
B19: 02 06 80 Schedules for Facility Remediation | F19: =IF($F$9="*",IF(E19>0,"*",""),"") | H19: =IF($H$9="*",IF(G19>0,"*",""),"") | J19: =IF($J$9="*",IF(I19>0,"*",""),"") | L19: =IF($L$9="*",IF(K19>0,"*",""),"") | N19: =IF($N$9="*",IF(M19>0,"*",""),"") | P19: =IF($P$9="*",IF(O19>0,"*",""),"") | R19: =IF($R$9="*",IF(Q19>0,"*",""),"") | T19: =IF($T$9="*",IF(S19>0,"*",""),"") | V19: =IF($V$9="*",IF(U19>0,"*",""),"")
B20: 02 06 86 Schedules for Hazardous Waste Drum Handling | F20: =IF($F$9="*",IF(E20>0,"*",""),"") | H20: =IF($H$9="*",IF(G20>0,"*",""),"") | J20: =IF($J$9="*",IF(I20>0,"*",""),"") | L20: =IF($L$9="*",IF(K20>0,"*",""),"") | N20: =IF($N$9="*",IF(M20>0,"*",""),"") | P20: =IF($P$9="*",IF(O20>0,"*",""),"") | R20: =IF($R$9="*",IF(Q20>0,"*",""),"") | T20: =IF($T$9="*",IF(S20>0,"*",""),"") | V20: =IF($V$9="*",IF(U20>0,"*",""),"")
A21: 1 | B21: 02 21 00 Surveys | E21: 30000 | F21: =IF($F$9="*",IF(E21>0,"*",""),"") -> * | H21: =23350 -> 23350 | J21: =IF($J$9="*",IF(I21>0,"*",""),"") | L21: =IF($L$9="*",IF(K21>0,"*",""),"") | N21: =IF($N$9="*",IF(M21>0,"*",""),"") | P21: =IF($P$9="*",IF(O21>0,"*",""),"") | R21: =IF($R$9="*",IF(Q21>0,"*",""),"") | T21: =IF($T$9="*",IF(S21>0,"*",""),"") | V21: =IF($V$9="*",IF(U21>0,"*",""),"") | W21: =15825+12150+4275+2650 -> 34900 | AA21: 30000 | AD21: 20700
A22: 1 | B22: 02 21 13 Construction Security Cameras | E22: 29014 | F22: =IF($F$9="*",IF(E22>0,"*",""),"") -> * | H22: =IF($H$9="*",IF(G22>0,"*",""),"") | J22: =IF($J$9="*",IF(I22>0,"*",""),"") | L22: =IF($L$9="*",IF(K22>0,"*",""),"") | N22: =IF($N$9="*",IF(M22>0,"*",""),"") | P22: =IF($P$9="*",IF(O22>0,"*",""),"") | R22: =IF($R$9="*",IF(Q22>0,"*",""),"") | T22: =IF($T$9="*",IF(S22>0,"*",""),"") | V22: =IF($V$9="*",IF(U22>0,"*",""),"")
B23: 02 21 13.13 Boundary and Survey Markers | F23: =IF($F$9="*",IF(E23>0,"*",""),"") | H23: =IF($H$9="*",IF(G23>0,"*",""),"") | J23: =IF($J$9="*",IF(I23>0,"*",""),"") | L23: =IF($L$9="*",IF(K23>0,"*",""),"") | N23: =IF($N$9="*",IF(M23>0,"*",""),"") | P23: =IF($P$9="*",IF(O23>0,"*",""),"") | R23: =IF($R$9="*",IF(Q23>0,"*",""),"") | T23: =IF($T$9="*",IF(S23>0,"*",""),"") | V23: =IF($V$9="*",IF(U23>0,"*",""),"")
B24: 02 22 00 Existing Conditions Assessment | F24: =IF($F$9="*",IF(E24>0,"*",""),"") | H24: =IF($H$9="*",IF(G24>0,"*",""),"") | J24: =IF($J$9="*",IF(I24>0,"*",""),"") | L24: =IF($L$9="*",IF(K24>0,"*",""),"") | N24: =IF($N$9="*",IF(M24>0,"*",""),"") | P24: =IF($P$9="*",IF(O24>0,"*",""),"") | R24: =IF($R$9="*",IF(Q24>0,"*",""),"") | T24: =IF($T$9="*",IF(S24>0,"*",""),"") | V24: =IF($V$9="*",IF(U24>0,"*",""),"")
B25: 02 22 13 Movement and Vibration Assessment | F25: =IF($F$9="*",IF(E25>0,"*",""),"") | H25: =IF($H$9="*",IF(G25>0,"*",""),"") | J25: =IF($J$9="*",IF(I25>0,"*",""),"") | L25: =IF($L$9="*",IF(K25>0,"*",""),"") | N25: =IF($N$9="*",IF(M25>0,"*",""),"") | P25: =IF($P$9="*",IF(O25>0,"*",""),"") | R25: =IF($R$9="*",IF(Q25>0,"*",""),"") | T25: =IF($T$9="*",IF(S25>0,"*",""),"") | V25: =IF($V$9="*",IF(U25>0,"*",""),"")
B26: 02 22 16 Acoustic Assessment | F26: =IF($F$9="*",IF(E26>0,"*",""),"") | H26: =IF($H$9="*",IF(G26>0,"*",""),"") | J26: =IF($J$9="*",IF(I26>0,"*",""),"") | L26: =IF($L$9="*",IF(K26>0,"*",""),"") | N26: =IF($N$9="*",IF(M26>0,"*",""),"") | P26: =IF($P$9="*",IF(O26>0,"*",""),"") | R26: =IF($R$9="*",IF(Q26>0,"*",""),"") | T26: =IF($T$9="*",IF(S26>0,"*",""),"") | V26: =IF($V$9="*",IF(U26>0,"*",""),"")
B27: 02 22 19 Traffic Assessment | F27: =IF($F$9="*",IF(E27>0,"*",""),"") | H27: =IF($H$9="*",IF(G27>0,"*",""),"") | J27: =IF($J$9="*",IF(I27>0,"*",""),"") | L27: =IF($L$9="*",IF(K27>0,"*",""),"") | N27: =IF($N$9="*",IF(M27>0,"*",""),"") | P27: =IF($P$9="*",IF(O27>0,"*",""),"") | R27: =IF($R$9="*",IF(Q27>0,"*",""),"") | T27: =IF($T$9="*",IF(S27>0,"*",""),"") | V27: =IF($V$9="*",IF(U27>0,"*",""),"")
B28: 02 24 13.13 Air Assessment | F28: =IF($F$9="*",IF(E28>0,"*",""),"") | H28: =IF($H$9="*",IF(G28>0,"*",""),"") | J28: =IF($J$9="*",IF(I28>0,"*",""),"") | L28: =IF($L$9="*",IF(K28>0,"*",""),"") | N28: =IF($N$9="*",IF(M28>0,"*",""),"") | P28: =IF($P$9="*",IF(O28>0,"*",""),"") | R28: =IF($R$9="*",IF(Q28>0,"*",""),"") | T28: =IF($T$9="*",IF(S28>0,"*",""),"") | V28: =IF($V$9="*",IF(U28>0,"*",""),"")
B29: 02 24 13.43 Water Assessment | F29: =IF($F$9="*",IF(E29>0,"*",""),"") | H29: =IF($H$9="*",IF(G29>0,"*",""),"") | J29: =IF($J$9="*",IF(I29>0,"*",""),"") | L29: =IF($L$9="*",IF(K29>0,"*",""),"") | N29: =IF($N$9="*",IF(M29>0,"*",""),"") | P29: =IF($P$9="*",IF(O29>0,"*",""),"") | R29: =IF($R$9="*",IF(Q29>0,"*",""),"") | T29: =IF($T$9="*",IF(S29>0,"*",""),"") | V29: =IF($V$9="*",IF(U29>0,"*",""),"")
B30: 02 24 13.73 Land Assessment | F30: =IF($F$9="*",IF(E30>0,"*",""),"") | H30: =IF($H$9="*",IF(G30>0,"*",""),"") | J30: =IF($J$9="*",IF(I30>0,"*",""),"") | L30: =IF($L$9="*",IF(K30>0,"*",""),"") | N30: =IF($N$9="*",IF(M30>0,"*",""),"") | P30: =IF($P$9="*",IF(O30>0,"*",""),"") | R30: =IF($R$9="*",IF(Q30>0,"*",""),"") | T30: =IF($T$9="*",IF(S30>0,"*",""),"") | V30: =IF($V$9="*",IF(U30>0,"*",""),"")
B31: 02 24 23 Chemical Sampling and Analysis of Soils | F31: =IF($F$9="*",IF(E31>0,"*",""),"") | H31: =IF($H$9="*",IF(G31>0,"*",""),"") | J31: =IF($J$9="*",IF(I31>0,"*",""),"") | L31: =IF($L$9="*",IF(K31>0,"*",""),"") | N31: =IF($N$9="*",IF(M31>0,"*",""),"") | P31: =IF($P$9="*",IF(O31>0,"*",""),"") | R31: =IF($R$9="*",IF(Q31>0,"*",""),"") | T31: =IF($T$9="*",IF(S31>0,"*",""),"") | V31: =IF($V$9="*",IF(U31>0,"*",""),"")
B32: 02 25 00 Existing Material Assessment | F32: =IF($F$9="*",IF(E32>0,"*",""),"") | H32: =IF($H$9="*",IF(G32>0,"*",""),"") | J32: =IF($J$9="*",IF(I32>0,"*",""),"") | L32: =IF($L$9="*",IF(K32>0,"*",""),"") | N32: =IF($N$9="*",IF(M32>0,"*",""),"") | P32: =IF($P$9="*",IF(O32>0,"*",""),"") | R32: =IF($R$9="*",IF(Q32>0,"*",""),"") | T32: =IF($T$9="*",IF(S32>0,"*",""),"") | V32: =IF($V$9="*",IF(U32>0,"*",""),"")
B33: 02 26 00 Hazardous Material Assessment | F33: =IF($F$9="*",IF(E33>0,"*",""),"") | H33: =IF($H$9="*",IF(G33>0,"*",""),"") | J33: =IF($J$9="*",IF(I33>0,"*",""),"") | L33: =IF($L$9="*",IF(K33>0,"*",""),"") | N33: =IF($N$9="*",IF(M33>0,"*",""),"") | P33: =IF($P$9="*",IF(O33>0,"*",""),"") | R33: =IF($R$9="*",IF(Q33>0,"*",""),"") | T33: =IF($T$9="*",IF(S33>0,"*",""),"") | V33: =IF($V$9="*",IF(U33>0,"*",""),"")
B34: 02 26 23 Asbestos Assessment | F34: =IF($F$9="*",IF(E34>0,"*",""),"") | H34: =IF($H$9="*",IF(G34>0,"*",""),"") | J34: =IF($J$9="*",IF(I34>0,"*",""),"") | L34: =IF($L$9="*",IF(K34>0,"*",""),"") | N34: =IF($N$9="*",IF(M34>0,"*",""),"") | P34: =IF($P$9="*",IF(O34>0,"*",""),"") | R34: =IF($R$9="*",IF(Q34>0,"*",""),"") | T34: =IF($T$9="*",IF(S34>0,"*",""),"") | V34: =IF($V$9="*",IF(U34>0,"*",""),"")
B35: 02 26 26 Lead Assessment | F35: =IF($F$9="*",IF(E35>0,"*",""),"") | H35: =IF($H$9="*",IF(G35>0,"*",""),"") | J35: =IF($J$9="*",IF(I35>0,"*",""),"") | L35: =IF($L$9="*",IF(K35>0,"*",""),"") | N35: =IF($N$9="*",IF(M35>0,"*",""),"") | P35: =IF($P$9="*",IF(O35>0,"*",""),"") | R35: =IF($R$9="*",IF(Q35>0,"*",""),"") | T35: =IF($T$9="*",IF(S35>0,"*",""),"") | V35: =IF($V$9="*",IF(U35>0,"*",""),"")
A36: 1 | B36: 02 26 33.13 Final Cleaning | E36: 41700 | F36: =IF($F$9="*",IF(E36>0,"*",""),"") -> * | H36: =IF($H$9="*",IF(G36>0,"*",""),"") | J36: =IF($J$9="*",IF(I36>0,"*",""),"") | L36: =IF($L$9="*",IF(K36>0,"*",""),"") | N36: =IF($N$9="*",IF(M36>0,"*",""),"") | P36: =IF($P$9="*",IF(O36>0,"*",""),"") | R36: =IF($R$9="*",IF(Q36>0,"*",""),"") | T36: =IF($T$9="*",IF(S36>0,"*",""),"") | V36: =IF($V$9="*",IF(U36>0,"*",""),"")
B37: 02 26 36 Hazardous Waste Drum Assessment | F37: =IF($F$9="*",IF(E37>0,"*",""),"") | H37: =IF($H$9="*",IF(G37>0,"*",""),"") | J37: =IF($J$9="*",IF(I37>0,"*",""),"") | L37: =IF($L$9="*",IF(K37>0,"*",""),"") | N37: =IF($N$9="*",IF(M37>0,"*",""),"") | P37: =IF($P$9="*",IF(O37>0,"*",""),"") | R37: =IF($R$9="*",IF(Q37>0,"*",""),"") | T37: =IF($T$9="*",IF(S37>0,"*",""),"") | V37: =IF($V$9="*",IF(U37>0,"*",""),"")
B38: 02 30 00 Subsurface Investigation | F38: =IF($F$9="*",IF(E38>0,"*",""),"") | H38: =IF($H$9="*",IF(G38>0,"*",""),"") | J38: =IF($J$9="*",IF(I38>0,"*",""),"") | L38: =IF($L$9="*",IF(K38>0,"*",""),"") | N38: =IF($N$9="*",IF(M38>0,"*",""),"") | P38: =IF($P$9="*",IF(O38>0,"*",""),"") | R38: =IF($R$9="*",IF(Q38>0,"*",""),"") | T38: =IF($T$9="*",IF(S38>0,"*",""),"") | V38: =IF($V$9="*",IF(U38>0,"*",""),"")
B39: 02 32 13 Subsurface Drilling and Sampling | F39: =IF($F$9="*",IF(E39>0,"*",""),"") | H39: =IF($H$9="*",IF(G39>0,"*",""),"") | J39: =IF($J$9="*",IF(I39>0,"*",""),"") | L39: =IF($L$9="*",IF(K39>0,"*",""),"") | N39: =IF($N$9="*",IF(M39>0,"*",""),"") | P39: =IF($P$9="*",IF(O39>0,"*",""),"") | R39: =IF($R$9="*",IF(Q39>0,"*",""),"") | T39: =IF($T$9="*",IF(S39>0,"*",""),"") | V39: =IF($V$9="*",IF(U39>0,"*",""),"")
A40: 1 | B40: 02 32 16 Material Testing & Threshold Inspections | E40: 21238 | F40: =IF($F$9="*",IF(E40>0,"*",""),"") -> * | H40: =IF($H$9="*",IF(G40>0,"*",""),"") | J40: =IF($J$9="*",IF(I40>0,"*",""),"") | L40: =IF($L$9="*",IF(K40>0,"*",""),"") | N40: =IF($N$9="*",IF(M40>0,"*",""),"") | P40: =IF($P$9="*",IF(O40>0,"*",""),"") | Q40: 55749 | R40: =IF($R$9="*",IF(Q40>0,"*",""),"") | T40: 21238 | V40: =IF($V$9="*",IF(U40>0,"*",""),"") | Z40: 52547 | AE40: 28115
B41: 02 32 19 Exploratory Excavations | F41: =IF($F$9="*",IF(E41>0,"*",""),"") | H41: =IF($H$9="*",IF(G41>0,"*",""),"") | J41: =IF($J$9="*",IF(I41>0,"*",""),"") | L41: =IF($L$9="*",IF(K41>0,"*",""),"") | N41: =IF($N$9="*",IF(M41>0,"*",""),"") | P41: =IF($P$9="*",IF(O41>0,"*",""),"") | R41: =IF($R$9="*",IF(Q41>0,"*",""),"") | T41: =IF($T$9="*",IF(S41>0,"*",""),"") | V41: =IF($V$9="*",IF(U41>0,"*",""),"")
B45: Final Cleaning | J45: 47900 | R45: 78996 | X45: 119990 | AB45: 129500 | AF45: 38900 | AG45: 43954 | AH45: 55775
A46: 1 | B46: RFI Responses | J46: *differing proposals in BC in different
A47: 1 | B47: Insurance | J47: Cleaning sections
A48: 1
A49: 1 | B49: Taxes
A50: 1 | B50: Bond | H50: Scope: | I50: See GC/GR for pricing | J50: See GC/GR for pricing | K50: See GC/GR for pricing | L50: See GC/GR for pricing | N50: Scope: | O50: See GC/GR for pricing
A51: 1 | B51: MBE | H51: Project Control: $2,050 | I51: Breakout: | J51: Breakout: | K51: Breakout: | L51: Breakout | N51: Prj Set Up: $500 | O51: Breakout | Q51: Scope Includes: | R51: Breakout: | T51: Breakout
A52: 1 | B52: WBE | H52: Construction Layout: $16,400 | I52: 1 rough clean, 1 final clean, 2 puff/ | J52: 2 rough cleanings: $39,600 | K52: Rough Cleaning (2) | L52: Int & Ext Windows | N52: 125 inspections ($280ea) $35,000 | O52: Rough Clean: | Q52: Earthwork Sampling & Testing | R52: Std Modified Proctor | T52: Field testing materials $12,638 | U52: Scope: | W52: Scope: | AE52: Includes:
A53: 1 | B53: Residency | H53: As-Built Survey: $4,900 | I53: buff clean of: | J53: Above includes 2 final and 1 punch clean | K53: Final Clean (2) & punch cleaning | L53: 46,512 Sq Ft | N53: 40hrs admin: $2,600 | O53: windows, doors, frames, tracks (inside | Q53: Concrete & Masonry | R53: Organic Content | T53: Lab testing $5,350 | U53: 99 units: $44,611 | W53: Construction layout land: $15,825 | AE53: Material:
A54: 1 | B54: Unit Pricing | H54: Total: $23,350 | I54: Exterior & Interior windows, hallways, | J54: Boom lift rental: $2,100 | K54: Subtotal cleaning $39,600 | L54: 9000 | N54: COC Submittals: $500 | O54: only), sinks, tubs, showers, toilets, | Q54: Pavement Observation | R54: Soils Particle Analysis | T54: Admin: $3,250 | U54: Comon areas | W54: As Builts: $12,150 | AE54: Proctor Test
A55: 1 | B55: Schedule Duration | I55: stairs, office, bathrooms, elevators | J55: Exterior windows: $1,300 | K55: Boom lift rental $2,100 | N55: Partical COC submittals: $250 | Q55: Sitework & Building: $6,618 | R55: Limerock Bearing Ratio | T55: Total: $21,238 | U55: Garages | W55: Construction Layout Buildings: $4,275 | AE55: Limerock
A56: 1 | B56: Mobilizations | I56: General: $49,220 | J56: Power Wash: $4,900 | K56: Does not include exterior window cleaning | N56: Subtotal: $38,850 | O56: Final Cleaning | Q56: Building Testing: $23,011 | R56: Field Compaction Testing | U56: Windows Inc Exterior | W56: Foundation Tie-In Survey: $2,650 | AE56: In-place nuclear density
A57: 1 | B57: Union | I57: Pressure Wash: $2,000 | J57: 66,365 SF 99 units | K57: No pressure washing | O57: Windows inside & out | Q57: Threshold: $26,120 | R57: Concrete field and lab compressive strength | W57: Elevator: $1,875 | AE57: Compressive strength
A59: 1 | B59: VE | I59: Ext Windows $2,500 | J59: TOTAL: $47,900 | K59: Total $41,700 | O59: Tough up cleaning | Q59: total: $55,749 | R59: Asphalt testing | W59: FEMA Elevation Cert: $2,450 | AE59: Concrete & grout samples
A60: 1 | B60: Exclusions: | I60: High reach rental: $3,000 | O60: Total: $90,981 | W60: Final Survey: $8,125 | AE60: 27 hrs Project Eng.
I61: 15 weeks travel from Orlando: $2,300 | O61: Excludes power washing and amenity | AE61: Admin
I62: Mark-up $11,804 | O62: areas. | AE62: subtotal: $18,520
I63: TOTAL $70,824 | AE63: Threshold Inspection
I64: Common area clean once | AE64: Representative
I65: Office space 1 rough & final clean only | AE65: PE 14 hrs
AE66: Admin
AE67: subtotal: $9,595
H240: =IF($H$9="*",IF(G240>0,"*",""),"") | J240: =IF($J$9="*",IF(I240>0,"*",""),"") | L240: =IF($L$9="*",IF(K240>0,"*",""),"") | N240: =IF($N$9="*",IF(M240>0,"*",""),"") | P240: =IF($P$9="*",IF(O240>0,"*",""),"") | R240: =IF($R$9="*",IF(Q240>0,"*",""),"") | T240: =IF($T$9="*",IF(S240>0,"*",""),"") | V240: =IF($V$9="*",IF(U240>0,"*",""),"")
H241: =IF($H$9="*",IF(G241>0,"*",""),"") | J241: =IF($J$9="*",IF(I241>0,"*",""),"") | L241: =IF($L$9="*",IF(K241>0,"*",""),"")

Sheet 02-41-Demolition
C1: Quantity | D1: Unit Pricing | E1: Nicholas Estimate | F1: *= Use | G1: Demo | H1: Demo | I1: Demo | J1: Demolition | K1: Demolition | L1: Demolition | M1: Demolition | N1: *= Use | O1: Demolition | P1: *= Use | Q1: Demolition | R1: *= Use | S1: Demolition | T1: *= Use | U1: Structural Demo | V1: *= Use
A2: Prepared By: | G2: Kimmins Contracting Corp | H2: EMG Floor Removal | I2: Dynamite Demo | J2: Milburn | K2: Handyman Specialists | L2: DHC Construction | M2: PAW Materials | O2: JVS | Q2: D.H. Griffin Wrecking | S2: Paw Materials | U2: ADS
B3: Contact: | G3: Chuck Gray | H3: Manny | J3: Dave Geertz | K3: Emanuel Collado: owner | M3: Brock Haymaker | O3: David Orr | Q3: Dyland Lisowski
B4: Phone: | G4: 813-569-8703 | H4: 727-237-5990 | I4: 727-466-0000 | J4: 312-350-4034 | K4: 347-753-5127 | M4: 727-238-5337 | O4: 813-695-2525
B5: Email: | G5: cgray@kimmins.com | H5: manny@emgfloorremoval.com | I5: info@dynademo.com | J5: daveg@milburn.com | K5: emanuelcollado1@gmail.com | M5: brockh@pawdemo.com | O5: dorr@jvscontracting.com
B6: Date: | G6: 46034 | H6: 46036 | I6: 46038 | J6: 46037 | K6: 46037 | M6: 46037
B7: Base Bid:
B8: Accepted Alternates:
A9: 1= Use | B9: Total: | E9: =SUM(E11:E400) -> 503586 | F9: * | G9: =SUM(G11:G400) -> 382000 | H9: =H17 -> 280500 | I9: =SUM(I11:I400) -> 49000 | J9: =J17 -> 24800 | K9: =SUM(K11:K400) -> 150000 | L9: =35966+74870+42750 -> 153586 | M9: =SUM(M11:M400) -> 36400 | O9: =SUM(O11:O400) -> 25900 | Q9: =SUM(Q11:Q400) -> 1192923 | S9: =SUM(S11:S400) -> 63725 | U9: =SUM(U11:U400) -> 28775
A10: Filter
B11: 02 41 00 Demolition | F11: =IF($F$9="*",IF(E11>0,"*",""),"") | H11: =IF($H$9="*",IF(G11>0,"*",""),"") | J11: =IF($J$9="*",IF(I11>0,"*",""),"") | L11: =IF($L$9="*",IF(K11>0,"*",""),"") | N11: =IF($N$9="*",IF(M11>0,"*",""),"") | P11: =IF($P$9="*",IF(O11>0,"*",""),"") | R11: =IF($R$9="*",IF(Q11>0,"*",""),"") | T11: =IF($T$9="*",IF(S11>0,"*",""),"") | V11: =IF($V$9="*",IF(U11>0,"*",""),"")
A12: 1 | B12: 02 41 13 Selective Site Demolition | E12: =L9 -> 153586 | F12: =IF($F$9="*",IF(E12>0,"*",""),"") -> * | H12: =IF($H$9="*",IF(G12>0,"*",""),"") | I12: 49000 | J12: =IF($J$9="*",IF(I12>0,"*",""),"") | K12: 150000 | L12: 74870 | M12: 36400 | N12: =IF($N$9="*",IF(M12>0,"*",""),"") | O12: 25900 | P12: =IF($P$9="*",IF(O12>0,"*",""),"") | Q12: 792923 | R12: =IF($R$9="*",IF(Q12>0,"*",""),"") | S12: 63725 | T12: =IF($T$9="*",IF(S12>0,"*",""),"") | U12: 28775 | V12: =IF($V$9="*",IF(U12>0,"*",""),"")
B13: 02 41 13.13 Paving Removal | F13: =IF($F$9="*",IF(E13>0,"*",""),"") | H13: =IF($H$9="*",IF(G13>0,"*",""),"") | J13: =IF($J$9="*",IF(I13>0,"*",""),"") | L13: =IF($L$9="*",IF(K13>0,"*",""),"") | N13: =IF($N$9="*",IF(M13>0,"*",""),"") | P13: =IF($P$9="*",IF(O13>0,"*",""),"") | R13: =IF($R$9="*",IF(Q13>0,"*",""),"") | T13: =IF($T$9="*",IF(S13>0,"*",""),"") | V13: =IF($V$9="*",IF(U13>0,"*",""),"")
B14: 02 41 13.23 Utility Line Removal | F14: =IF($F$9="*",IF(E14>0,"*",""),"") | H14: =IF($H$9="*",IF(G14>0,"*",""),"") | J14: =IF($J$9="*",IF(I14>0,"*",""),"") | L14: =IF($L$9="*",IF(K14>0,"*",""),"") | N14: =IF($N$9="*",IF(M14>0,"*",""),"") | P14: =IF($P$9="*",IF(O14>0,"*",""),"") | R14: =IF($R$9="*",IF(Q14>0,"*",""),"") | T14: =IF($T$9="*",IF(S14>0,"*",""),"") | V14: =IF($V$9="*",IF(U14>0,"*",""),"")
A15: 1 | B15: 02 41 13.33 Shoring Allowance | E15: 350000 | F15: =IF($F$9="*",IF(E15>0,"*",""),"") -> * | H15: =IF($H$9="*",IF(G15>0,"*",""),"") | J15: =IF($J$9="*",IF(I15>0,"*",""),"") | L15: =IF($L$9="*",IF(K15>0,"*",""),"") | N15: =IF($N$9="*",IF(M15>0,"*",""),"") | P15: =IF($P$9="*",IF(O15>0,"*",""),"") | Q15: 400000 | R15: =IF($R$9="*",IF(Q15>0,"*",""),"") | T15: =IF($T$9="*",IF(S15>0,"*",""),"") | V15: =IF($V$9="*",IF(U15>0,"*",""),"")
B16: 02 41 16 Structure Demolition | F16: =IF($F$9="*",IF(E16>0,"*",""),"") | H16: =IF($H$9="*",IF(G16>0,"*",""),"") | J16: =IF($J$9="*",IF(I16>0,"*",""),"") | L16: =IF($L$9="*",IF(K16>0,"*",""),"") | N16: =IF($N$9="*",IF(M16>0,"*",""),"") | P16: =IF($P$9="*",IF(O16>0,"*",""),"") | R16: =IF($R$9="*",IF(Q16>0,"*",""),"") | T16: =IF($T$9="*",IF(S16>0,"*",""),"") | V16: =IF($V$9="*",IF(U16>0,"*",""),"")
B17: 02 41 16.13 Building Demolition | F17: =IF($F$9="*",IF(E17>0,"*",""),"") | G17: =315000+67000 -> 382000 | H17: 280500 | J17: 24800 | L17: =IF($L$9="*",IF(K17>0,"*",""),"") | N17: =IF($N$9="*",IF(M17>0,"*",""),"") | P17: =IF($P$9="*",IF(O17>0,"*",""),"") | R17: =IF($R$9="*",IF(Q17>0,"*",""),"") | T17: =IF($T$9="*",IF(S17>0,"*",""),"") | V17: =IF($V$9="*",IF(U17>0,"*",""),"")
B18: 02 41 16.23 Tower Demolition | F18: =IF($F$9="*",IF(E18>0,"*",""),"") | H18: =IF($H$9="*",IF(G18>0,"*",""),"") | J18: =IF($J$9="*",IF(I18>0,"*",""),"") | L18: =IF($L$9="*",IF(K18>0,"*",""),"") | N18: =IF($N$9="*",IF(M18>0,"*",""),"") | P18: =IF($P$9="*",IF(O18>0,"*",""),"") | R18: =IF($R$9="*",IF(Q18>0,"*",""),"") | T18: =IF($T$9="*",IF(S18>0,"*",""),"") | V18: =IF($V$9="*",IF(U18>0,"*",""),"")
B19: 02 41 16.43 Dam Demolition | F19: =IF($F$9="*",IF(E19>0,"*",""),"") | H19: =IF($H$9="*",IF(G19>0,"*",""),"") | J19: =IF($J$9="*",IF(I19>0,"*",""),"") | L19: =IF($L$9="*",IF(K19>0,"*",""),"") | N19: =IF($N$9="*",IF(M19>0,"*",""),"") | P19: =IF($P$9="*",IF(O19>0,"*",""),"") | R19: =IF($R$9="*",IF(Q19>0,"*",""),"") | T19: =IF($T$9="*",IF(S19>0,"*",""),"") | V19: =IF($V$9="*",IF(U19>0,"*",""),"")
B20: 02 41 19 Selective Demolition | F20: =IF($F$9="*",IF(E20>0,"*",""),"") | H20: =IF($H$9="*",IF(G20>0,"*",""),"") | J20: =IF($J$9="*",IF(I20>0,"*",""),"") | L20: =IF($L$9="*",IF(K20>0,"*",""),"") | N20: =IF($N$9="*",IF(M20>0,"*",""),"") | P20: =IF($P$9="*",IF(O20>0,"*",""),"") | R20: =IF($R$9="*",IF(Q20>0,"*",""),"") | T20: =IF($T$9="*",IF(S20>0,"*",""),"") | V20: =IF($V$9="*",IF(U20>0,"*",""),"")
B21: 02 41 19.13 Selective Building Demolition | F21: =IF($F$9="*",IF(E21>0,"*",""),"") | H21: =IF($H$9="*",IF(G21>0,"*",""),"") | J21: =IF($J$9="*",IF(I21>0,"*",""),"") | L21: =IF($L$9="*",IF(K21>0,"*",""),"") | N21: =IF($N$9="*",IF(M21>0,"*",""),"") | P21: =IF($P$9="*",IF(O21>0,"*",""),"") | R21: =IF($R$9="*",IF(Q21>0,"*",""),"") | T21: =IF($T$9="*",IF(S21>0,"*",""),"") | V21: =IF($V$9="*",IF(U21>0,"*",""),"")
B22: 02 41 19.16 Selective Interior Demolition | F22: =IF($F$9="*",IF(E22>0,"*",""),"") | H22: =IF($H$9="*",IF(G22>0,"*",""),"") | J22: =IF($J$9="*",IF(I22>0,"*",""),"") | L22: =IF($L$9="*",IF(K22>0,"*",""),"") | N22: =IF($N$9="*",IF(M22>0,"*",""),"") | P22: =IF($P$9="*",IF(O22>0,"*",""),"") | R22: =IF($R$9="*",IF(Q22>0,"*",""),"") | T22: =IF($T$9="*",IF(S22>0,"*",""),"") | V22: =IF($V$9="*",IF(U22>0,"*",""),"")
B23: 02 42 13 Deconstruction of Structures | F23: =IF($F$9="*",IF(E23>0,"*",""),"") | H23: =IF($H$9="*",IF(G23>0,"*",""),"") | J23: =IF($J$9="*",IF(I23>0,"*",""),"") | L23: =IF($L$9="*",IF(K23>0,"*",""),"") | N23: =IF($N$9="*",IF(M23>0,"*",""),"") | P23: =IF($P$9="*",IF(O23>0,"*",""),"") | R23: =IF($R$9="*",IF(Q23>0,"*",""),"") | T23: =IF($T$9="*",IF(S23>0,"*",""),"") | V23: =IF($V$9="*",IF(U23>0,"*",""),"")
B24: 02 42 19 Recycling of Construction Materials | F24: =IF($F$9="*",IF(E24>0,"*",""),"") | H24: =IF($H$9="*",IF(G24>0,"*",""),"") | J24: =IF($J$9="*",IF(I24>0,"*",""),"") | L24: =IF($L$9="*",IF(K24>0,"*",""),"") | N24: =IF($N$9="*",IF(M24>0,"*",""),"") | P24: =IF($P$9="*",IF(O24>0,"*",""),"") | R24: =IF($R$9="*",IF(Q24>0,"*",""),"") | T24: =IF($T$9="*",IF(S24>0,"*",""),"") | V24: =IF($V$9="*",IF(U24>0,"*",""),"")
B25: 02 42 19.15 Concrete Recycling | F25: =IF($F$9="*",IF(E25>0,"*",""),"") | H25: =IF($H$9="*",IF(G25>0,"*",""),"") | J25: =IF($J$9="*",IF(I25>0,"*",""),"") | L25: =IF($L$9="*",IF(K25>0,"*",""),"") | N25: =IF($N$9="*",IF(M25>0,"*",""),"") | P25: =IF($P$9="*",IF(O25>0,"*",""),"") | R25: =IF($R$9="*",IF(Q25>0,"*",""),"") | T25: =IF($T$9="*",IF(S25>0,"*",""),"") | V25: =IF($V$9="*",IF(U25>0,"*",""),"")
B26: 02 42 19.17 Masonry Recycling | F26: =IF($F$9="*",IF(E26>0,"*",""),"") | H26: =IF($H$9="*",IF(G26>0,"*",""),"") | J26: =IF($J$9="*",IF(I26>0,"*",""),"") | L26: =IF($L$9="*",IF(K26>0,"*",""),"") | N26: =IF($N$9="*",IF(M26>0,"*",""),"") | P26: =IF($P$9="*",IF(O26>0,"*",""),"") | R26: =IF($R$9="*",IF(Q26>0,"*",""),"") | T26: =IF($T$9="*",IF(S26>0,"*",""),"") | V26: =IF($V$9="*",IF(U26>0,"*",""),"")
A27: 1 | B27: 02 42 19 Shoring | F27: =IF($F$9="*",IF(E27>0,"*",""),"") | H27: =IF($H$9="*",IF(G27>0,"*",""),"") | J27: =IF($J$9="*",IF(I27>0,"*",""),"") | L27: =IF($L$9="*",IF(K27>0,"*",""),"") | N27: =IF($N$9="*",IF(M27>0,"*",""),"") | P27: =IF($P$9="*",IF(O27>0,"*",""),"") | R27: =IF($R$9="*",IF(Q27>0,"*",""),"") | T27: =IF($T$9="*",IF(S27>0,"*",""),"") | V27: =IF($V$9="*",IF(U27>0,"*",""),"")
B28: 02 42 19.23 Wood Recycling | F28: =IF($F$9="*",IF(E28>0,"*",""),"") | H28: =IF($H$9="*",IF(G28>0,"*",""),"") | J28: =IF($J$9="*",IF(I28>0,"*",""),"") | L28: =IF($L$9="*",IF(K28>0,"*",""),"") | N28: =IF($N$9="*",IF(M28>0,"*",""),"") | P28: =IF($P$9="*",IF(O28>0,"*",""),"") | R28: =IF($R$9="*",IF(Q28>0,"*",""),"") | T28: =IF($T$9="*",IF(S28>0,"*",""),"") | V28: =IF($V$9="*",IF(U28>0,"*",""),"")
B29: 02 42 19.25 Plastic Recycling | F29: =IF($F$9="*",IF(E29>0,"*",""),"") | H29: =IF($H$9="*",IF(G29>0,"*",""),"") | J29: =IF($J$9="*",IF(I29>0,"*",""),"") | L29: =IF($L$9="*",IF(K29>0,"*",""),"") | N29: =IF($N$9="*",IF(M29>0,"*",""),"") | P29: =IF($P$9="*",IF(O29>0,"*",""),"") | R29: =IF($R$9="*",IF(Q29>0,"*",""),"") | T29: =IF($T$9="*",IF(S29>0,"*",""),"") | V29: =IF($V$9="*",IF(U29>0,"*",""),"")
B30: 02 42 19.29 Solid Surface Recycling | F30: =IF($F$9="*",IF(E30>0,"*",""),"") | H30: =IF($H$9="*",IF(G30>0,"*",""),"") | J30: =IF($J$9="*",IF(I30>0,"*",""),"") | L30: =IF($L$9="*",IF(K30>0,"*",""),"") | N30: =IF($N$9="*",IF(M30>0,"*",""),"") | P30: =IF($P$9="*",IF(O30>0,"*",""),"") | R30: =IF($R$9="*",IF(Q30>0,"*",""),"") | T30: =IF($T$9="*",IF(S30>0,"*",""),"") | V30: =IF($V$9="*",IF(U30>0,"*",""),"")
B31: 02 42 19.31 Insulation Recycling | F31: =IF($F$9="*",IF(E31>0,"*",""),"") | H31: =IF($H$9="*",IF(G31>0,"*",""),"") | J31: =IF($J$9="*",IF(I31>0,"*",""),"") | L31: =IF($L$9="*",IF(K31>0,"*",""),"") | N31: =IF($N$9="*",IF(M31>0,"*",""),"") | P31: =IF($P$9="*",IF(O31>0,"*",""),"") | R31: =IF($R$9="*",IF(Q31>0,"*",""),"") | T31: =IF($T$9="*",IF(S31>0,"*",""),"") | V31: =IF($V$9="*",IF(U31>0,"*",""),"")
B32: 02 42 19.35 Roofing Recycling | F32: =IF($F$9="*",IF(E32>0,"*",""),"") | H32: =IF($H$9="*",IF(G32>0,"*",""),"") | J32: =IF($J$9="*",IF(I32>0,"*",""),"") | L32: =IF($L$9="*",IF(K32>0,"*",""),"") | N32: =IF($N$9="*",IF(M32>0,"*",""),"") | P32: =IF($P$9="*",IF(O32>0,"*",""),"") | R32: =IF($R$9="*",IF(Q32>0,"*",""),"") | T32: =IF($T$9="*",IF(S32>0,"*",""),"") | V32: =IF($V$9="*",IF(U32>0,"*",""),"")
B33: 02 42 19.39 Window Recycling | F33: =IF($F$9="*",IF(E33>0,"*",""),"") | H33: =IF($H$9="*",IF(G33>0,"*",""),"") | J33: =IF($J$9="*",IF(I33>0,"*",""),"") | L33: =IF($L$9="*",IF(K33>0,"*",""),"") | N33: =IF($N$9="*",IF(M33>0,"*",""),"") | P33: =IF($P$9="*",IF(O33>0,"*",""),"") | R33: =IF($R$9="*",IF(Q33>0,"*",""),"") | T33: =IF($T$9="*",IF(S33>0,"*",""),"") | V33: =IF($V$9="*",IF(U33>0,"*",""),"")
B34: 02 42 19.41 Glass Recycling | F34: =IF($F$9="*",IF(E34>0,"*",""),"") | H34: =IF($H$9="*",IF(G34>0,"*",""),"") | J34: =IF($J$9="*",IF(I34>0,"*",""),"") | L34: =IF($L$9="*",IF(K34>0,"*",""),"") | N34: =IF($N$9="*",IF(M34>0,"*",""),"") | P34: =IF($P$9="*",IF(O34>0,"*",""),"") | R34: =IF($R$9="*",IF(Q34>0,"*",""),"") | T34: =IF($T$9="*",IF(S34>0,"*",""),"") | V34: =IF($V$9="*",IF(U34>0,"*",""),"")
B35: 02 42 19.43 Gypsum Board Recycling | F35: =IF($F$9="*",IF(E35>0,"*",""),"") | H35: =IF($H$9="*",IF(G35>0,"*",""),"") | J35: =IF($J$9="*",IF(I35>0,"*",""),"") | L35: =IF($L$9="*",IF(K35>0,"*",""),"") | N35: =IF($N$9="*",IF(M35>0,"*",""),"") | P35: =IF($P$9="*",IF(O35>0,"*",""),"") | R35: =IF($R$9="*",IF(Q35>0,"*",""),"") | T35: =IF($T$9="*",IF(S35>0,"*",""),"") | V35: =IF($V$9="*",IF(U35>0,"*",""),"")
B36: 02 42 19.45 Ceiling Tile Recycling | F36: =IF($F$9="*",IF(E36>0,"*",""),"") | H36: =IF($H$9="*",IF(G36>0,"*",""),"") | J36: =IF($J$9="*",IF(I36>0,"*",""),"") | L36: =IF($L$9="*",IF(K36>0,"*",""),"") | N36: =IF($N$9="*",IF(M36>0,"*",""),"") | P36: =IF($P$9="*",IF(O36>0,"*",""),"") | R36: =IF($R$9="*",IF(Q36>0,"*",""),"") | T36: =IF($T$9="*",IF(S36>0,"*",""),"") | V36: =IF($V$9="*",IF(U36>0,"*",""),"")
B37: 02 42 19.47 Flooring Recycling | F37: =IF($F$9="*",IF(E37>0,"*",""),"") | H37: =IF($H$9="*",IF(G37>0,"*",""),"") | J37: =IF($J$9="*",IF(I37>0,"*",""),"") | L37: =IF($L$9="*",IF(K37>0,"*",""),"") | N37: =IF($N$9="*",IF(M37>0,"*",""),"") | P37: =IF($P$9="*",IF(O37>0,"*",""),"") | R37: =IF($R$9="*",IF(Q37>0,"*",""),"") | T37: =IF($T$9="*",IF(S37>0,"*",""),"") | V37: =IF($V$9="*",IF(U37>0,"*",""),"")
B38: 02 42 19.55 Appliance Recycling | F38: =IF($F$9="*",IF(E38>0,"*",""),"") | H38: =IF($H$9="*",IF(G38>0,"*",""),"") | J38: =IF($J$9="*",IF(I38>0,"*",""),"") | L38: =IF($L$9="*",IF(K38>0,"*",""),"") | N38: =IF($N$9="*",IF(M38>0,"*",""),"") | P38: =IF($P$9="*",IF(O38>0,"*",""),"") | R38: =IF($R$9="*",IF(Q38>0,"*",""),"") | T38: =IF($T$9="*",IF(S38>0,"*",""),"") | V38: =IF($V$9="*",IF(U38>0,"*",""),"")
B39: 02 42 19.57 Mattress Recycling | F39: =IF($F$9="*",IF(E39>0,"*",""),"") | H39: =IF($H$9="*",IF(G39>0,"*",""),"") | J39: =IF($J$9="*",IF(I39>0,"*",""),"") | L39: =IF($L$9="*",IF(K39>0,"*",""),"") | N39: =IF($N$9="*",IF(M39>0,"*",""),"") | P39: =IF($P$9="*",IF(O39>0,"*",""),"") | R39: =IF($R$9="*",IF(Q39>0,"*",""),"") | T39: =IF($T$9="*",IF(S39>0,"*",""),"") | V39: =IF($V$9="*",IF(U39>0,"*",""),"")
... B89: 02 81 00 Transportation and Disposal of Hazardous Materials | F89: =IF($F$9="*",IF(E89>0,"*",""),"") | H89: =IF($H$9="*",IF(G89>0,"*",""),"") | J89: =IF($J$9="*",IF(I89>0,"*",""),"") | L89: =IF($L$9="*",IF(K89>0,"*",""),"") | N89: =IF($N$9="*",IF(M89>0,"*",""),"") | P89: =IF($P$9="*",IF(O89>0,"*",""),"") | R89: =IF($R$9="*",IF(Q89>0,"*",""),"") | T89: =IF($T$9="*",IF(S89>0,"*",""),"") | V89: =IF($V$9="*",IF(U89>0,"*",""),"")
J90: =IF($J$9="*",IF(I90>0,"*",""),"") | L90: =IF($L$9="*",IF(K90>0,"*",""),"") | N90: =IF($N$9="*",IF(M90>0,"*",""),"") | P90: =IF($P$9="*",IF(O90>0,"*",""),"") | R90: =IF($R$9="*",IF(Q90>0,"*",""),"") | T90: =IF($T$9="*",IF(S90>0,"*",""),"") | V90: =IF($V$9="*",IF(U90>0,"*",""),"")
J91: =IF($J$9="*",IF(I91>0,"*",""),"") | L91: =IF($L$9="*",IF(K91>0,"*",""),"") | N91: =IF($N$9="*",IF(M91>0,"*",""),"") | P91: =IF($P$9="*",IF(O91>0,"*",""),"") | R91: =IF($R$9="*",IF(Q91>0,"*",""),"") | T91: =IF($T$9="*",IF(S91>0,"*",""),"") | V91: =IF($V$9="*",IF(U91>0,"*",""),"")
B92: Project Documents | J92: =IF($J$9="*",IF(I92>0,"*",""),"") | L92: =IF($L$9="*",IF(K92>0,"*",""),"") | N92: =IF($N$9="*",IF(M92>0,"*",""),"") | P92: =IF($P$9="*",IF(O92>0,"*",""),"") | R92: =IF($R$9="*",IF(Q92>0,"*",""),"") | T92: =IF($T$9="*",IF(S92>0,"*",""),"") | V92: =IF($V$9="*",IF(U92>0,"*",""),"")
B93: RFI Responses | J93: =IF($J$9="*",IF(I93>0,"*",""),"") | L93: =IF($L$9="*",IF(K93>0,"*",""),"") | N93: =IF($N$9="*",IF(M93>0,"*",""),"") | P93: =IF($P$9="*",IF(O93>0,"*",""),"") | R93: =IF($R$9="*",IF(Q93>0,"*",""),"") | T93: =IF($T$9="*",IF(S93>0,"*",""),"") | V93: =IF($V$9="*",IF(U93>0,"*",""),"")
B94: Insurance | J94: =IF($J$9="*",IF(I94>0,"*",""),"") | L94: =IF($L$9="*",IF(K94>0,"*",""),"") | N94: =IF($N$9="*",IF(M94>0,"*",""),"") | P94: =IF($P$9="*",IF(O94>0,"*",""),"") | R94: =IF($R$9="*",IF(Q94>0,"*",""),"") | T94: =IF($T$9="*",IF(S94>0,"*",""),"") | V94: =IF($V$9="*",IF(U94>0,"*",""),"")
J95: =IF($J$9="*",IF(I95>0,"*",""),"") | L95: =IF($L$9="*",IF(K95>0,"*",""),"") | N95: =IF($N$9="*",IF(M95>0,"*",""),"") | P95: =IF($P$9="*",IF(O95>0,"*",""),"") | R95: =IF($R$9="*",IF(Q95>0,"*",""),"") | T95: =IF($T$9="*",IF(S95>0,"*",""),"") | V95: =IF($V$9="*",IF(U95>0,"*",""),"")
A96: 1 | B96: Taxes | J96: =IF($J$9="*",IF(I96>0,"*",""),"") | L96: =IF($L$9="*",IF(K96>0,"*",""),"") | M96: Includes: | N96: =IF($N$9="*",IF(M96>0,"*",""),"") | P96: =IF($P$9="*",IF(O96>0,"*",""),"") | R96: =IF($R$9="*",IF(Q96>0,"*",""),"") | T96: =IF($T$9="*",IF(S96>0,"*",""),"") | V96: =IF($V$9="*",IF(U96>0,"*",""),"")
A97: 1 | B97: Bond | G97: Includes: | H97: Includes: | I97: Includes: | J97: Includes: | K97: Lump sum propsal on B.C. | L97: Breakout: | M97: NESHAP (10 day notification) | N97: =IF($N$9="*",IF(M97>0,"*",""),"") | P97: =IF($P$9="*",IF(O97>0,"*",""),"") | R97: =IF($R$9="*",IF(Q97>0,"*",""),"") | T97: =IF($T$9="*",IF(S97>0,"*",""),"") | V97: =IF($V$9="*",IF(U97>0,"*",""),"")
A98: 1 | B98: MBE | G98: 2 demo permits, 2 demo notifications | H98: Remove structure & fence | I98: Demo one story 4451 SF bldg | J98: Cut & cap water & sewer | K98: ZERO details | L98: Total Demo $35,966 | M98: Cut & wrap sewer | N98: =IF($N$9="*",IF(M98>0,"*",""),"") | P98: =IF($P$9="*",IF(O98>0,"*",""),"") | Q98: Shoring is needed for demolition | R98: =IF($R$9="*",IF(Q98>0,"*",""),"") | S98: Add Alt: Tree Removal ($11,016) | T98: =IF($T$9="*",IF(S98>0,"*",""),"") | V98: =IF($V$9="*",IF(U98>0,"*",""),"")
A99: 1 | B99: WBE | G99: Freon purge | H99: Remove window, doors, frame, fire escape | I99: Remove concrete as shown | J99: Hydrant meter for dust supression | L99: Selective Demo $74,870 | M99: Install & maintain silt fence | N99: =IF($N$9="*",IF(M99>0,"*",""),"") | P99: =IF($P$9="*",IF(O99>0,"*",""),"") | R99: =IF($R$9="*",IF(Q99>0,"*",""),"") | T99: =IF($T$9="*",IF(S99>0,"*",""),"") | V99: =IF($V$9="*",IF(U99>0,"*",""),"")
A100: 1 | B100: Residency | G100: 1 interior demo and disposal of two story | H100: stairs, metal rails, awning, windows, | I100: Remove 15 palm trees | J100: Remove freon from HVAC | L100: Abatement$42,750 | M100: A/C evac | N100: =IF($N$9="*",IF(M100>0,"*",""),"") | P100: =IF($P$9="*",IF(O100>0,"*",""),"") | R100: =IF($R$9="*",IF(Q100>0,"*",""),"") | T100: =IF($T$9="*",IF(S100>0,"*",""),"") | V100: =IF($V$9="*",IF(U100>0,"*",""),"")
A101: 1 | B101: Unit Pricing | G101: building. | H101: wiring, frywall, interior walls, floors. | I101: Removed 9x7 shed | J101: Demo 1 story building | L101: =IF($L$9="*",IF(K101>0,"*",""),"") | M101: Removal of bulbs & ballasts | N101: =IF($N$9="*",IF(M101>0,"*",""),"") | P101: =IF($P$9="*",IF(O101>0,"*",""),"") | R101: =IF($R$9="*",IF(Q101>0,"*",""),"") | T101: =IF($T$9="*",IF(S101>0,"*",""),"") | V101: =IF($V$9="*",IF(U101>0,"*",""),"")
A102: 1 | B102: Schedule Duration | G102: Demo & disposal of 1ea one story bldg. | H102: Remove 8'8"x36' extent roof | I102: Excludes Oak Trees | J102: Excavate & remove slab foundations | L102: =IF($L$9="*",IF(K102>0,"*",""),"") | M102: Remo & removal of C&D | N102: =IF($N$9="*",IF(M102>0,"*",""),"") | P102: =IF($P$9="*",IF(O102>0,"*",""),"") | R102: =IF($R$9="*",IF(Q102>0,"*",""),"") | T102: =IF($T$9="*",IF(S102>0,"*",""),"") | V102: =IF($V$9="*",IF(U102>0,"*",""),"")
A103: 1 | B103: Mobilizations | G103: Silt Fence | H103: Cut masonry wall | J103: Haul & disposal of all bldg materials | L103: =IF($L$9="*",IF(K103>0,"*",""),"") | M103: Demo & remove all concrete slabs, | N103: =IF($N$9="*",IF(M103>0,"*",""),"") | P103: =IF($P$9="*",IF(O103>0,"*",""),"") | R103: =IF($R$9="*",IF(Q103>0,"*",""),"") | T103: =IF($T$9="*",IF(S103>0,"*",""),"") | V103: =IF($V$9="*",IF(U103>0,"*",""),"")
A104: 1 | B104: Union | G104: Utility cuts | H104: remove balcony metal roof, downspout, | J104: 1ea mobilization | L104: =IF($L$9="*",IF(K104>0,"*",""),"") | M104: footers, & CMU | N104: =IF($N$9="*",IF(M104>0,"*",""),"") | P104: =IF($P$9="*",IF(O104>0,"*",""),"") | R104: =IF($R$9="*",IF(Q104>0,"*",""),"") | T104: =IF($T$9="*",IF(S104>0,"*",""),"") | V104: =IF($V$9="*",IF(U104>0,"*",""),"")
J105: =IF($J$9="*",IF(I105>0,"*",""),"") | L105: =IF($L$9="*",IF(K105>0,"*",""),"") | N105: =IF($N$9="*",IF(M105>0,"*",""),"") | P105: =IF($P$9="*",IF(O105>0,"*",""),"") | R105: =IF($R$9="*",IF(Q105>0,"*",""),"") | T105: =IF($T$9="*",IF(S105>0,"*",""),"") | V105: =IF($V$9="*",IF(U105>0,"*",""),"")
A106: 1 | B106: VE | G106: Rough grade after demo | H106: and parapet. | J106: Rough grade site | L106: =IF($L$9="*",IF(K106>0,"*",""),"") | M106: Demo & recycle of all metals | N106: =IF($N$9="*",IF(M106>0,"*",""),"") | P106: =IF($P$9="*",IF(O106>0,"*",""),"") | R106: =IF($R$9="*",IF(Q106>0,"*",""),"") | T106: =IF($T$9="*",IF(S106>0,"*",""),"") | V106: =IF($V$9="*",IF(U106>0,"*",""),"")
A107: 1 | B107: Exclusions: | G107: See Abatement ofr asbestos survey | J107: Asbestors survey: $1,800 | L107: =IF($L$9="*",IF(K107>0,"*",""),"") | M107: Rough grade disturbed areas | N107: =IF($N$9="*",IF(M107>0,"*",""),"") | P107: =IF($P$9="*",IF(O107>0,"*",""),"") | R107: =IF($R$9="*",IF(Q107>0,"*",""),"") | T107: =IF($T$9="*",IF(S107>0,"*",""),"") | V107: =IF($V$9="*",IF(U107>0,"*",""),"")
J108: =IF($J$9="*",IF(I108>0,"*",""),"") | L108: =IF($L$9="*",IF(K108>0,"*",""),"") | N108: =IF($N$9="*",IF(M108>0,"*",""),"") | P108: =IF($P$9="*",IF(O108>0,"*",""),"") | R108: =IF($R$9="*",IF(Q108>0,"*",""),"") | T108: =IF($T$9="*",IF(S108>0,"*",""),"") | V108: =IF($V$9="*",IF(U108>0,"*",""),"")
B109: Do We Need Shoring??? | M109: Seed & hay disturbed areas
B110: D.H. Griffin Shoring Budget $400,000 | M110: NOTE: Does NOT include selective demo
M111: of historic building on sheets A,01-A.04

Sheet 02-82-Abatement
C1: Quantity | D1: Unit Pricing | E1: Nicholas Estimate | F1: *= Use | G1: Abatement | H1: Abatement | I1: Abatement | J1: Termite Prevention | K1: Asbestos Abatement | L1: *= Use | N1: *= Use | P1: *= Use | R1: *= Use | T1: *= Use | V1: *= Use
A2: Prepared By: | G2: Kimmins Contracting Corp | H2: EE&G | I2: N-terprise Consulting | J2: Diligent | K2: ADS | M2: Sub 4 | O2: Sub 5 | Q2: Sub 6 | S2: Sub 7 | U2: Sub 8
B3: Contact: | G3: Chuck Gray | I3: Nacole Caputo | J3: Samerah Sultan
B4: Phone: | G4: 813-569-8703 | I4: 813-220-3927
B5: Email: | G5: cgray@kimmins.com | I5: nacole@n-terpriseconsulting.com | J5: samerah@mydiligent.com
B6: Date: | G6: 46034 | I6: 46037 | J6: 46034
B7: Base Bid:
B8: Accepted Alternates:
A9: 1= Use | B9: Total: | E9: =SUM(E11:E400) -> 14623.57 | F9: * | G9: =SUM(G11:G400) -> 9400 | I9: =SUM(I11:I400) -> 5000 | J9: =J17 -> 4623.57 | K9: =SUM(K11:K400) -> 37175 | M9: =SUM(M11:M400) -> 0 | O9: =SUM(O11:O400) -> 0 | Q9: =SUM(Q11:Q400) -> 0 | S9: =SUM(S11:S400) -> 0 | U9: =SUM(U11:U400) -> 0
A10: Filter
B11: 02 82 00 Asbestos Remediation | F11: =IF($F$9="*",IF(E11>0,"*",""),"") | H11: 28205 | J11: =IF($J$9="*",IF(I11>0,"*",""),"") | K11: 37175 | L11: =IF($L$9="*",IF(K11>0,"*",""),"") | N11: =IF($N$9="*",IF(M11>0,"*",""),"") | P11: =IF($P$9="*",IF(O11>0,"*",""),"") | R11: =IF($R$9="*",IF(Q11>0,"*",""),"") | T11: =IF($T$9="*",IF(S11>0,"*",""),"") | V11: =IF($V$9="*",IF(U11>0,"*",""),"")
A12: 1 | B12: 02 82 13 Asbestos Abatement | E12: Included in Demo | F12: =IF($F$9="*",IF(E12>0,"*",""),"") -> * | H12: =IF($H$9="*",IF(G12>0,"*",""),"") | J12: =IF($J$9="*",IF(I12>0,"*",""),"") | L12: =IF($L$9="*",IF(K12>0,"*",""),"") | N12: =IF($N$9="*",IF(M12>0,"*",""),"") | P12: =IF($P$9="*",IF(O12>0,"*",""),"") | R12: =IF($R$9="*",IF(Q12>0,"*",""),"") | T12: =IF($T$9="*",IF(S12>0,"*",""),"") | V12: =IF($V$9="*",IF(U12>0,"*",""),"")
B13: 02 82 13.19 Asbestos Floor Tile and Mastic Abatement | F13: =IF($F$9="*",IF(E13>0,"*",""),"") | H13: =IF($H$9="*",IF(G13>0,"*",""),"") | J13: =IF($J$9="*",IF(I13>0,"*",""),"") | L13: =IF($L$9="*",IF(K13>0,"*",""),"") | N13: =IF($N$9="*",IF(M13>0,"*",""),"") | P13: =IF($P$9="*",IF(O13>0,"*",""),"") | R13: =IF($R$9="*",IF(Q13>0,"*",""),"") | T13: =IF($T$9="*",IF(S13>0,"*",""),"") | V13: =IF($V$9="*",IF(U13>0,"*",""),"")
B14: 02 82 13.33 Asbestos Abatement for Utilities | F14: =IF($F$9="*",IF(E14>0,"*",""),"") | H14: =IF($H$9="*",IF(G14>0,"*",""),"") | J14: =IF($J$9="*",IF(I14>0,"*",""),"") | L14: =IF($L$9="*",IF(K14>0,"*",""),"") | N14: =IF($N$9="*",IF(M14>0,"*",""),"") | P14: =IF($P$9="*",IF(O14>0,"*",""),"") | R14: =IF($R$9="*",IF(Q14>0,"*",""),"") | T14: =IF($T$9="*",IF(S14>0,"*",""),"") | V14: =IF($V$9="*",IF(U14>0,"*",""),"")
B15: 02 82 16 Engineering Control of Asbestos Containing Materials | F15: =IF($F$9="*",IF(E15>0,"*",""),"") | H15: =IF($H$9="*",IF(G15>0,"*",""),"") | J15: =IF($J$9="*",IF(I15>0,"*",""),"") | L15: =IF($L$9="*",IF(K15>0,"*",""),"") | N15: =IF($N$9="*",IF(M15>0,"*",""),"") | P15: =IF($P$9="*",IF(O15>0,"*",""),"") | R15: =IF($R$9="*",IF(Q15>0,"*",""),"") | T15: =IF($T$9="*",IF(S15>0,"*",""),"") | V15: =IF($V$9="*",IF(U15>0,"*",""),"")
A16: 1 | B16: 02 82 33 Asbestos Survey | E16: 10000 | F16: =IF($F$9="*",IF(E16>0,"*",""),"") -> * | G16: =4700+4700 -> 9400 | H16: =IF($H$9="*",IF(G16>0,"*",""),"") | I16: 5000 | J16: =IF($J$9="*",IF(I16>0,"*",""),"") | L16: =IF($L$9="*",IF(K16>0,"*",""),"") | N16: =IF($N$9="*",IF(M16>0,"*",""),"") | P16: =IF($P$9="*",IF(O16>0,"*",""),"") | R16: =IF($R$9="*",IF(Q16>0,"*",""),"") | T16: =IF($T$9="*",IF(S16>0,"*",""),"") | V16: =IF($V$9="*",IF(U16>0,"*",""),"")
A17: 1 | B17: 02 83 00 Termite Prevention | E17: =J17 -> 4623.57 | F17: =IF($F$9="*",IF(E17>0,"*",""),"") -> * | H17: =IF($H$9="*",IF(G17>0,"*",""),"") | J17: =(20117*0.21)+399 -> 4623.57 | L17: =IF($L$9="*",IF(K17>0,"*",""),"") | N17: =IF($N$9="*",IF(M17>0,"*",""),"") | P17: =IF($P$9="*",IF(O17>0,"*",""),"") | R17: =IF($R$9="*",IF(Q17>0,"*",""),"") | T17: =IF($T$9="*",IF(S17>0,"*",""),"") | V17: =IF($V$9="*",IF(U17>0,"*",""),"")
B18: 02 83 13 Lead Hazard Control Activities | F18: =IF($F$9="*",IF(E18>0,"*",""),"") | H18: =IF($H$9="*",IF(G18>0,"*",""),"") | J18: =IF($J$9="*",IF(I18>0,"*",""),"") | L18: =IF($L$9="*",IF(K18>0,"*",""),"") | N18: =IF($N$9="*",IF(M18>0,"*",""),"") | P18: =IF($P$9="*",IF(O18>0,"*",""),"") | R18: =IF($R$9="*",IF(Q18>0,"*",""),"") | T18: =IF($T$9="*",IF(S18>0,"*",""),"") | V18: =IF($V$9="*",IF(U18>0,"*",""),"")
B19: 02 83 19 Lead-Based Paint Remediation | F19: =IF($F$9="*",IF(E19>0,"*",""),"") | H19: =IF($H$9="*",IF(G19>0,"*",""),"") | J19: =IF($J$9="*",IF(I19>0,"*",""),"") | L19: =IF($L$9="*",IF(K19>0,"*",""),"") | N19: =IF($N$9="*",IF(M19>0,"*",""),"") | P19: =IF($P$9="*",IF(O19>0,"*",""),"") | R19: =IF($R$9="*",IF(Q19>0,"*",""),"") | T19: =IF($T$9="*",IF(S19>0,"*",""),"") | V19: =IF($V$9="*",IF(U19>0,"*",""),"")
B20: 02 83 19.13 Lead-Based Paint Abatement | F20: =IF($F$9="*",IF(E20>0,"*",""),"") | H20: =IF($H$9="*",IF(G20>0,"*",""),"") | J20: =IF($J$9="*",IF(I20>0,"*",""),"") | L20: =IF($L$9="*",IF(K20>0,"*",""),"") | N20: =IF($N$9="*",IF(M20>0,"*",""),"") | P20: =IF($P$9="*",IF(O20>0,"*",""),"") | R20: =IF($R$9="*",IF(Q20>0,"*",""),"") | T20: =IF($T$9="*",IF(S20>0,"*",""),"") | V20: =IF($V$9="*",IF(U20>0,"*",""),"")
B21: 02 83 33.13 Lead-Based Paint Removal and Disposal | F21: =IF($F$9="*",IF(E21>0,"*",""),"") | H21: =IF($H$9="*",IF(G21>0,"*",""),"") | J21: =IF($J$9="*",IF(I21>0,"*",""),"") | L21: =IF($L$9="*",IF(K21>0,"*",""),"") | N21: =IF($N$9="*",IF(M21>0,"*",""),"") | P21: =IF($P$9="*",IF(O21>0,"*",""),"") | R21: =IF($R$9="*",IF(Q21>0,"*",""),"") | T21: =IF($T$9="*",IF(S21>0,"*",""),"") | V21: =IF($V$9="*",IF(U21>0,"*",""),"")
B22: 02 87 13 Mold Remediation | F22: =IF($F$9="*",IF(E22>0,"*",""),"") | H22: =IF($H$9="*",IF(G22>0,"*",""),"") | J22: =IF($J$9="*",IF(I22>0,"*",""),"") | L22: =IF($L$9="*",IF(K22>0,"*",""),"") | N22: =IF($N$9="*",IF(M22>0,"*",""),"") | P22: =IF($P$9="*",IF(O22>0,"*",""),"") | R22: =IF($R$9="*",IF(Q22>0,"*",""),"") | T22: =IF($T$9="*",IF(S22>0,"*",""),"") | V22: =IF($V$9="*",IF(U22>0,"*",""),"")
B23: 02 87 13.16 Mold Remediation Preparation and Containment | F23: =IF($F$9="*",IF(E23>0,"*",""),"") | H23: =IF($H$9="*",IF(G23>0,"*",""),"") | J23: =IF($J$9="*",IF(I23>0,"*",""),"") | L23: =IF($L$9="*",IF(K23>0,"*",""),"") | N23: =IF($N$9="*",IF(M23>0,"*",""),"") | P23: =IF($P$9="*",IF(O23>0,"*",""),"") | R23: =IF($R$9="*",IF(Q23>0,"*",""),"") | T23: =IF($T$9="*",IF(S23>0,"*",""),"") | V23: =IF($V$9="*",IF(U23>0,"*",""),"")
B24: 02 87 13.19 Mold Remediation Clearance Air Sampling | F24: =IF($F$9="*",IF(E24>0,"*",""),"") | H24: =IF($H$9="*",IF(G24>0,"*",""),"") | J24: =IF($J$9="*",IF(I24>0,"*",""),"") | L24: =IF($L$9="*",IF(K24>0,"*",""),"") | N24: =IF($N$9="*",IF(M24>0,"*",""),"") | P24: =IF($P$9="*",IF(O24>0,"*",""),"") | R24: =IF($R$9="*",IF(Q24>0,"*",""),"") | T24: =IF($T$9="*",IF(S24>0,"*",""),"") | V24: =IF($V$9="*",IF(U24>0,"*",""),"")
I27: Proposal includes: | J27: 21 cents per SF plus $399 trip charge
A28: 1 | B28: Project Documents | I28: Lead Paint Survey
A29: 1 | B29: RFI Responses | I29: Mold & Mositure
A30: 1 | B30: Insurance | I30: Misc Hazards
A31: 1 | I31: Reporting
A32: 1 | B32: Taxes | I32: Asbestos
A33: 1 | B33: Bond | H33: Scope: | I33: Parcel 1: 8,900 SF
A34: 1 | B34: MBE | H34: Removal of asbestos | I34: Parcel 2: 5,493 SF
A35: 1 | B35: WBE
A36: 1 | B36: Residency
A37: 1 | B37: Unit Pricing
A38: 1 | B38: Schedule Duration
A39: 1 | B39: Mobilizations
A40: 1 | B40: Union
A42: 1 | B42: VE
A43: 1 | B43: Exclusions:

Sheet 03-Concrete
C1: Quantity | D1: Unit Pricing | E1: Nicholas Estimate | F1: *= Use | G1: Concrete | H1: Concrete | I1: Concrete | J1: Concrete | K1: Concrete | L1: Gypcrete | M1: Concrete Topping | N1: Gypcrete | O1: Gypcrete | P1: Gypcrete | Q1: Structural Concrete | R1: Concrete | S1: Concrete | T1: *= Use | V1: *= Use
A2: Prepared By: | G2: Galo | H2: Allen Masonry | I2: Ervin Bishop | J2: Liberty Concrete | K2: Restore-FL | L2: Specialty Concrete | M2: Gypsum Express | N2: Gypsum Express | O2: Gyp-tech | P2: Cemplex | Q2: Magnum | R2: Baker Construciton | S2: Matcon | U2: Sub 8
B3: Contact: | G3: Darling Garcia | I3: Jack Anderson | J3: Jerry Johnson: Owner | K3: Todd Andrew | L3: Cole Hord | M3: Ariel Ramos | N3: Ariel Ramos | O3: Mary Carbo
B4: Phone: | G4: 813-409-0066 | I4: 813-996-6560 | J4: 407-864-2325 | K4: 561-679-0321 | L4: 325-650-7054 | M4: 407-878-4243 | N4: 407-878-4243 | O4: 772-223-9380
B5: Email: | G5: estimate@galocorp.com | I5: janderson@ervinbishop.com | J5: jjohnson@libertycfc.com | K5: todd@restore-fl.com | L5: cole@sccot.net | M5: ariel@gypsumexpressservices.com | N5: ariel@gypsumexpressservices.com | O5: gyptechfl@gmail.com
B6: Date: | G6: submitted Jan 9th | J6: 46037 | L6: 46036 | M6: 46037 | N6: 46037 | O6: 46037
B7: Base Bid:
B8: Accepted Alternates:
A9: 1= Use | B9: Total: | E9: =SUM(E11:E400) -> 2397804 | F9: * | G9: =SUM(G11:G400) -> 2735963 | H9: =H67 -> 2242500 | I9: =SUM(I11:I400) -> 2150476 | J9: =J67 -> 2665400 | K9: =SUM(K11:K400) -> 4426453 | L9: =L132 -> 127600 | O9: =SUM(O11:O400) -> 155304 | P9: =P132 -> 118952 | Q9: =SUM(Q11:Q400) -> 4044273 | S9: =SUM(S11:S400) -> 2053000 | U9: =SUM(U11:U400) -> 0 | W9: =IF(X9="**","ERROR","") | X9: =CONCATENATE(F9,H9,J9,L9,N9,P9,R9,T9,V9) -> *22425002665400127600118952 | XFC9: =IF(XFD9="**","ERROR","") | XFD9: =CONCATENATE(F9,H9,J9,L9,N9,P9,R9,T9,V9) -> *22425002665400127600118952
A10: Filter
B11: 03 00 00 Concrete | F11: =IF($F$9="*",IF(E11>0,"*",""),"") | H11: =IF($H$9="*",IF(G11>0,"*",""),"") | J11: =IF($J$9="*",IF(I11>0,"*",""),"") | L11: =IF($L$9="*",IF(K11>0,"*",""),"") | N11: =IF($N$9="*",IF(M11>0,"*",""),"") | P11: =IF($P$9="*",IF(O11>0,"*",""),"") | R11: =IF($R$9="*",IF(Q11>0,"*",""),"") | T11: =IF($T$9="*",IF(S11>0,"*",""),"") | V11: =IF($V$9="*",IF(U11>0,"*",""),"")
B12: 03 01 30.51 Cleaning of Cast-in-Place Concrete | F12: =IF($F$9="*",IF(E12>0,"*",""),"") | H12: =IF($H$9="*",IF(G12>0,"*",""),"") | J12: =IF($J$9="*",IF(I12>0,"*",""),"") | L12: =IF($L$9="*",IF(K12>0,"*",""),"") | N12: =IF($N$9="*",IF(M12>0,"*",""),"") | P12: =IF($P$9="*",IF(O12>0,"*",""),"") | R12: =IF($R$9="*",IF(Q12>0,"*",""),"") | T12: =IF($T$9="*",IF(S12>0,"*",""),"") | V12: =IF($V$9="*",IF(U12>0,"*",""),"")
B13: 03 01 30.61 Resurfacing of Cast-in-Place Concrete | F13: =IF($F$9="*",IF(E13>0,"*",""),"") | H13: =IF($H$9="*",IF(G13>0,"*",""),"") | J13: =IF($J$9="*",IF(I13>0,"*",""),"") | L13: =IF($L$9="*",IF(K13>0,"*",""),"") | M13: 14000 | N13: =IF($N$9="*",IF(M13>0,"*",""),"") | P13: =IF($P$9="*",IF(O13>0,"*",""),"") | R13: =IF($R$9="*",IF(Q13>0,"*",""),"") | T13: =IF($T$9="*",IF(S13>0,"*",""),"") | V13: =IF($V$9="*",IF(U13>0,"*",""),"")
B14: 03 01 30.71 Rehabilitation of Cast-in-Place Concrete | F14: =IF($F$9="*",IF(E14>0,"*",""),"") | H14: =IF($H$9="*",IF(G14>0,"*",""),"") | J14: =IF($J$9="*",IF(I14>0,"*",""),"") | L14: =IF($L$9="*",IF(K14>0,"*",""),"") | N14: =IF($N$9="*",IF(M14>0,"*",""),"") | P14: =IF($P$9="*",IF(O14>0,"*",""),"") | R14: =IF($R$9="*",IF(Q14>0,"*",""),"") | T14: =IF($T$9="*",IF(S14>0,"*",""),"") | V14: =IF($V$9="*",IF(U14>0,"*",""),"")
B15: 03 01 30.72 Strengthening of Cast-in-Place Concrete | F15: =IF($F$9="*",IF(E15>0,"*",""),"") | H15: =IF($H$9="*",IF(G15>0,"*",""),"") | J15: =IF($J$9="*",IF(I15>0,"*",""),"") | L15: =IF($L$9="*",IF(K15>0,"*",""),"") | N15: =IF($N$9="*",IF(M15>0,"*",""),"") | P15: =IF($P$9="*",IF(O15>0,"*",""),"") | R15: =IF($R$9="*",IF(Q15>0,"*",""),"") | T15: =IF($T$9="*",IF(S15>0,"*",""),"") | V15: =IF($V$9="*",IF(U15>0,"*",""),"")
B16: 03 01 50.51 Cleaning Cast Decks and Underlayment | F16: =IF($F$9="*",IF(E16>0,"*",""),"") | H16: =IF($H$9="*",IF(G16>0,"*",""),"") | J16: =IF($J$9="*",IF(I16>0,"*",""),"") | L16: =IF($L$9="*",IF(K16>0,"*",""),"") | N16: =IF($N$9="*",IF(M16>0,"*",""),"") | P16: =IF($P$9="*",IF(O16>0,"*",""),"") | R16: =IF($R$9="*",IF(Q16>0,"*",""),"") | T16: =IF($T$9="*",IF(S16>0,"*",""),"") | V16: =IF($V$9="*",IF(U16>0,"*",""),"")
B17: 03 01 50.61 Resurfacing of Cast Decks and Underlayment | F17: =IF($F$9="*",IF(E17>0,"*",""),"") | H17: =IF($H$9="*",IF(G17>0,"*",""),"") | J17: =IF($J$9="*",IF(I17>0,"*",""),"") | L17: =IF($L$9="*",IF(K17>0,"*",""),"") | N17: =IF($N$9="*",IF(M17>0,"*",""),"") | P17: =IF($P$9="*",IF(O17>0,"*",""),"") | R17: =IF($R$9="*",IF(Q17>0,"*",""),"") | T17: =IF($T$9="*",IF(S17>0,"*",""),"") | V17: =IF($V$9="*",IF(U17>0,"*",""),"")
B18: 03 01 50.71 Rehabilitation of Cast Decks and Underlayment | F18: =IF($F$9="*",IF(E18>0,"*",""),"") | H18: =IF($H$9="*",IF(G18>0,"*",""),"") | J18: =IF($J$9="*",IF(I18>0,"*",""),"") | L18: =IF($L$9="*",IF(K18>0,"*",""),"") | N18: =IF($N$9="*",IF(M18>0,"*",""),"") | P18: =IF($P$9="*",IF(O18>0,"*",""),"") | R18: =IF($R$9="*",IF(Q18>0,"*",""),"") | T18: =IF($T$9="*",IF(S18>0,"*",""),"") | V18: =IF($V$9="*",IF(U18>0,"*",""),"")
B19: 03 01 50.72 Strengthening of Cast Decks and Underlayment | F19: =IF($F$9="*",IF(E19>0,"*",""),"") | H19: =IF($H$9="*",IF(G19>0,"*",""),"") | J19: =IF($J$9="*",IF(I19>0,"*",""),"") | L19: =IF($L$9="*",IF(K19>0,"*",""),"") | N19: =IF($N$9="*",IF(M19>0,"*",""),"") | P19: =IF($P$9="*",IF(O19>0,"*",""),"") | R19: =IF($R$9="*",IF(Q19>0,"*",""),"") | T19: =IF($T$9="*",IF(S19>0,"*",""),"") | V19: =IF($V$9="*",IF(U19>0,"*",""),"")
B20: 03 03 00 Conservation Treatment for Period Concrete | F20: =IF($F$9="*",IF(E20>0,"*",""),"") | H20: =IF($H$9="*",IF(G20>0,"*",""),"") | J20: =IF($J$9="*",IF(I20>0,"*",""),"") | L20: =IF($L$9="*",IF(K20>0,"*",""),"") | N20: =IF($N$9="*",IF(M20>0,"*",""),"") | P20: =IF($P$9="*",IF(O20>0,"*",""),"") | R20: =IF($R$9="*",IF(Q20>0,"*",""),"") | T20: =IF($T$9="*",IF(S20>0,"*",""),"") | V20: =IF($V$9="*",IF(U20>0,"*",""),"")
B21: 03 03 30 Conservation Treatment for Period Cast-in-Place Concrete | F21: =IF($F$9="*",IF(E21>0,"*",""),"") | H21: =IF($H$9="*",IF(G21>0,"*",""),"") | J21: =IF($J$9="*",IF(I21>0,"*",""),"") | L21: =IF($L$9="*",IF(K21>0,"*",""),"") | N21: =IF($N$9="*",IF(M21>0,"*",""),"") | P21: =IF($P$9="*",IF(O21>0,"*",""),"") | R21: =IF($R$9="*",IF(Q21>0,"*",""),"") | T21: =IF($T$9="*",IF(S21>0,"*",""),"") | V21: =IF($V$9="*",IF(U21>0,"*",""),"")
B22: 03 03 31 Conservation Treatment for Period Structural Concrete | F22: =IF($F$9="*",IF(E22>0,"*",""),"") | H22: =IF($H$9="*",IF(G22>0,"*",""),"") | J22: =IF($J$9="*",IF(I22>0,"*",""),"") | L22: =IF($L$9="*",IF(K22>0,"*",""),"") | N22: =IF($N$9="*",IF(M22>0,"*",""),"") | P22: =IF($P$9="*",IF(O22>0,"*",""),"") | R22: =IF($R$9="*",IF(Q22>0,"*",""),"") | T22: =IF($T$9="*",IF(S22>0,"*",""),"") | V22: =IF($V$9="*",IF(U22>0,"*",""),"")
B23: 03 03 33 Conservation Treatment for Period Architectural Concrete | F23: =IF($F$9="*",IF(E23>0,"*",""),"") | H23: =IF($H$9="*",IF(G23>0,"*",""),"") | J23: =IF($J$9="*",IF(I23>0,"*",""),"") | L23: =IF($L$9="*",IF(K23>0,"*",""),"") | M23: Proposal Includes: | N23: =IF($N$9="*",IF(M23>0,"*",""),"") | P23: =IF($P$9="*",IF(O23>0,"*",""),"") | R23: =IF($R$9="*",IF(Q23>0,"*",""),"") | T23: =IF($T$9="*",IF(S23>0,"*",""),"") | V23: =IF($V$9="*",IF(U23>0,"*",""),"")
B24: 03 05 05 Selective Demolition for Concrete | F24: =IF($F$9="*",IF(E24>0,"*",""),"") | H24: =IF($H$9="*",IF(G24>0,"*",""),"") | J24: =IF($J$9="*",IF(I24>0,"*",""),"") | L24: =IF($L$9="*",IF(K24>0,"*",""),"") | M24: 2" max concrete on stair landings and | N24: =IF($N$9="*",IF(M24>0,"*",""),"") | P24: =IF($P$9="*",IF(O24>0,"*",""),"") | R24: =IF($R$9="*",IF(Q24>0,"*",""),"") | T24: =IF($T$9="*",IF(S24>0,"*",""),"") | V24: =IF($V$9="*",IF(U24>0,"*",""),"")
B25: 03 10 00 Concrete Forming and Accessories | F25: =IF($F$9="*",IF(E25>0,"*",""),"") | H25: =IF($H$9="*",IF(G25>0,"*",""),"") | J25: =IF($J$9="*",IF(I25>0,"*",""),"") | L25: =IF($L$9="*",IF(K25>0,"*",""),"") | M25: balconies floors 2-4 on 1 building. | N25: =IF($N$9="*",IF(M25>0,"*",""),"") | P25: =IF($P$9="*",IF(O25>0,"*",""),"") | R25: =IF($R$9="*",IF(Q25>0,"*",""),"") | T25: =IF($T$9="*",IF(S25>0,"*",""),"") | V25: =IF($V$9="*",IF(U25>0,"*",""),"")
B26: 03 11 00 Concrete Forming | F26: =IF($F$9="*",IF(E26>0,"*",""),"") | H26: =IF($H$9="*",IF(G26>0,"*",""),"") | J26: =IF($J$9="*",IF(I26>0,"*",""),"") | L26: =IF($L$9="*",IF(K26>0,"*",""),"") | M26: Fiber reinforced with pea gravel 3000psi | N26: =IF($N$9="*",IF(M26>0,"*",""),"") | P26: =IF($P$9="*",IF(O26>0,"*",""),"") | R26: =IF($R$9="*",IF(Q26>0,"*",""),"") | T26: =IF($T$9="*",IF(S26>0,"*",""),"") | V26: =IF($V$9="*",IF(U26>0,"*",""),"")
B27: 03 11 13 Structural Cast-in-Place Concrete Forming | F27: =IF($F$9="*",IF(E27>0,"*",""),"") | H27: =IF($H$9="*",IF(G27>0,"*",""),"") | J27: =IF($J$9="*",IF(I27>0,"*",""),"") | L27: =IF($L$9="*",IF(K27>0,"*",""),"") | M27: Broomed finish | N27: =IF($N$9="*",IF(M27>0,"*",""),"") | P27: =IF($P$9="*",IF(O27>0,"*",""),"") | R27: =IF($R$9="*",IF(Q27>0,"*",""),"") | T27: =IF($T$9="*",IF(S27>0,"*",""),"") | V27: =IF($V$9="*",IF(U27>0,"*",""),"")
B28: 03 11 13.13 Concrete Slip Forming | F28: =IF($F$9="*",IF(E28>0,"*",""),"") | H28: =IF($H$9="*",IF(G28>0,"*",""),"") | J28: =IF($J$9="*",IF(I28>0,"*",""),"") | L28: =IF($L$9="*",IF(K28>0,"*",""),"") | M28: Flashing and weather proofing included | N28: =IF($N$9="*",IF(M28>0,"*",""),"") | P28: =IF($P$9="*",IF(O28>0,"*",""),"") | R28: =IF($R$9="*",IF(Q28>0,"*",""),"") | T28: =IF($T$9="*",IF(S28>0,"*",""),"") | V28: =IF($V$9="*",IF(U28>0,"*",""),"")
B29: 03 11 13.16 Concrete Shoring | F29: =IF($F$9="*",IF(E29>0,"*",""),"") | H29: =IF($H$9="*",IF(G29>0,"*",""),"") | J29: =IF($J$9="*",IF(I29>0,"*",""),"") | L29: =IF($L$9="*",IF(K29>0,"*",""),"") | M29: Tax included | N29: =IF($N$9="*",IF(M29>0,"*",""),"") | P29: =IF($P$9="*",IF(O29>0,"*",""),"") | R29: =IF($R$9="*",IF(Q29>0,"*",""),"") | T29: =IF($T$9="*",IF(S29>0,"*",""),"") | V29: =IF($V$9="*",IF(U29>0,"*",""),"")
B30: 03 11 13.19 Falsework | F30: =IF($F$9="*",IF(E30>0,"*",""),"") | H30: =IF($H$9="*",IF(G30>0,"*",""),"") | J30: =IF($J$9="*",IF(I30>0,"*",""),"") | L30: =IF($L$9="*",IF(K30>0,"*",""),"") | N30: =IF($N$9="*",IF(M30>0,"*",""),"") | P30: =IF($P$9="*",IF(O30>0,"*",""),"") | R30: =IF($R$9="*",IF(Q30>0,"*",""),"") | T30: =IF($T$9="*",IF(S30>0,"*",""),"") | V30: =IF($V$9="*",IF(U30>0,"*",""),"")
B31: 03 11 16 Architectural Cast-in Place Concrete Forming | F31: =IF($F$9="*",IF(E31>0,"*",""),"") | H31: =IF($H$9="*",IF(G31>0,"*",""),"") | J31: =IF($J$9="*",IF(I31>0,"*",""),"") | L31: =IF($L$9="*",IF(K31>0,"*",""),"") | N31: =IF($N$9="*",IF(M31>0,"*",""),"") | P31: =IF($P$9="*",IF(O31>0,"*",""),"") | R31: =IF($R$9="*",IF(Q31>0,"*",""),"") | T31: =IF($T$9="*",IF(S31>0,"*",""),"") | V31: =IF($V$9="*",IF(U31>0,"*",""),"")
B32: 03 11 16.13 Concrete Form Liners | F32: =IF($F$9="*",IF(E32>0,"*",""),"") | H32: =IF($H$9="*",IF(G32>0,"*",""),"") | J32: =IF($J$9="*",IF(I32>0,"*",""),"") | L32: =IF($L$9="*",IF(K32>0,"*",""),"") | N32: =IF($N$9="*",IF(M32>0,"*",""),"") | P32: =IF($P$9="*",IF(O32>0,"*",""),"") | R32: =IF($R$9="*",IF(Q32>0,"*",""),"") | T32: =IF($T$9="*",IF(S32>0,"*",""),"") | V32: =IF($V$9="*",IF(U32>0,"*",""),"")
B33: 03 11 19 Insulating Concrete Forming | F33: =IF($F$9="*",IF(E33>0,"*",""),"") | H33: =IF($H$9="*",IF(G33>0,"*",""),"") | J33: =IF($J$9="*",IF(I33>0,"*",""),"") | L33: =IF($L$9="*",IF(K33>0,"*",""),"") | N33: =IF($N$9="*",IF(M33>0,"*",""),"") | P33: =IF($P$9="*",IF(O33>0,"*",""),"") | R33: =IF($R$9="*",IF(Q33>0,"*",""),"") | T33: =IF($T$9="*",IF(S33>0,"*",""),"") | V33: =IF($V$9="*",IF(U33>0,"*",""),"")
B34: 03 11 23 Permanent Stair Forming | F34: =IF($F$9="*",IF(E34>0,"*",""),"") | H34: =IF($H$9="*",IF(G34>0,"*",""),"") | J34: =IF($J$9="*",IF(I34>0,"*",""),"") | L34: =IF($L$9="*",IF(K34>0,"*",""),"") | N34: =IF($N$9="*",IF(M34>0,"*",""),"") | P34: =IF($P$9="*",IF(O34>0,"*",""),"") | R34: =IF($R$9="*",IF(Q34>0,"*",""),"") | T34: =IF($T$9="*",IF(S34>0,"*",""),"") | V34: =IF($V$9="*",IF(U34>0,"*",""),"")
B35: 03 11 26 Permanent Tier Forming | F35: =IF($F$9="*",IF(E35>0,"*",""),"") | H35: =IF($H$9="*",IF(G35>0,"*",""),"") | J35: =IF($J$9="*",IF(I35>0,"*",""),"") | L35: =IF($L$9="*",IF(K35>0,"*",""),"") | N35: =IF($N$9="*",IF(M35>0,"*",""),"") | P35: =IF($P$9="*",IF(O35>0,"*",""),"") | R35: =IF($R$9="*",IF(Q35>0,"*",""),"") | T35: =IF($T$9="*",IF(S35>0,"*",""),"") | V35: =IF($V$9="*",IF(U35>0,"*",""),"")
B36: 03 15 00 Concrete Accessories | F36: =IF($F$9="*",IF(E36>0,"*",""),"") | H36: =IF($H$9="*",IF(G36>0,"*",""),"") | J36: =IF($J$9="*",IF(I36>0,"*",""),"") | L36: =IF($L$9="*",IF(K36>0,"*",""),"") | N36: =IF($N$9="*",IF(M36>0,"*",""),"") | P36: =IF($P$9="*",IF(O36>0,"*",""),"") | R36: =IF($R$9="*",IF(Q36>0,"*",""),"") | T36: =IF($T$9="*",IF(S36>0,"*",""),"") | V36: =IF($V$9="*",IF(U36>0,"*",""),"")
B37: 03 15 13 Waterstops | F37: =IF($F$9="*",IF(E37>0,"*",""),"") | H37: =IF($H$9="*",IF(G37>0,"*",""),"") | J37: =IF($J$9="*",IF(I37>0,"*",""),"") | L37: =IF($L$9="*",IF(K37>0,"*",""),"") | N37: =IF($N$9="*",IF(M37>0,"*",""),"") | P37: =IF($P$9="*",IF(O37>0,"*",""),"") | R37: =IF($R$9="*",IF(Q37>0,"*",""),"") | T37: =IF($T$9="*",IF(S37>0,"*",""),"") | V37: =IF($V$9="*",IF(U37>0,"*",""),"")
B38: 03 15 13.13 Non-Expanding Waterstops | F38: =IF($F$9="*",IF(E38>0,"*",""),"") | H38: =IF($H$9="*",IF(G38>0,"*",""),"") | J38: =IF($J$9="*",IF(I38>0,"*",""),"") | L38: =IF($L$9="*",IF(K38>0,"*",""),"") | N38: =IF($N$9="*",IF(M38>0,"*",""),"") | P38: =IF($P$9="*",IF(O38>0,"*",""),"") | R38: =IF($R$9="*",IF(Q38>0,"*",""),"") | T38: =IF($T$9="*",IF(S38>0,"*",""),"") | V38: =IF($V$9="*",IF(U38>0,"*",""),"")
B39: 03 15 13.16 Expanding Waterstops | F39: =IF($F$9="*",IF(E39>0,"*",""),"") | H39: =IF($H$9="*",IF(G39>0,"*",""),"") | J39: =IF($J$9="*",IF(I39>0,"*",""),"") | L39: =IF($L$9="*",IF(K39>0,"*",""),"") | N39: =IF($N$9="*",IF(M39>0,"*",""),"") | P39: =IF($P$9="*",IF(O39>0,"*",""),"") | R39: =IF($R$9="*",IF(Q39>0,"*",""),"") | T39: =IF($T$9="*",IF(S39>0,"*",""),"") | V39: =IF($V$9="*",IF(U39>0,"*",""),"")
B40: 03 15 13.19 Combination Expanding and Injection Hose Waterstops | F40: =IF($F$9="*",IF(E40>0,"*",""),"") | H40: =IF($H$9="*",IF(G40>0,"*",""),"") | J40: =IF($J$9="*",IF(I40>0,"*",""),"") | L40: =IF($L$9="*",IF(K40>0,"*",""),"") | N40: =IF($N$9="*",IF(M40>0,"*",""),"") | P40: =IF($P$9="*",IF(O40>0,"*",""),"") | R40: =IF($R$9="*",IF(Q40>0,"*",""),"") | T40: =IF($T$9="*",IF(S40>0,"*",""),"") | V40: =IF($V$9="*",IF(U40>0,"*",""),"")
B41: 03 15 13.21 Injection Hose Waterstops | F41: =IF($F$9="*",IF(E41>0,"*",""),"") | H41: =IF($H$9="*",IF(G41>0,"*",""),"") | J41: =IF($J$9="*",IF(I41>0,"*",""),"") | L41: =IF($L$9="*",IF(K41>0,"*",""),"") | N41: =IF($N$9="*",IF(M41>0,"*",""),"") | P41: =IF($P$9="*",IF(O41>0,"*",""),"") | R41: =IF($R$9="*",IF(Q41>0,"*",""),"") | T41: =IF($T$9="*",IF(S41>0,"*",""),"") | V41: =IF($V$9="*",IF(U41>0,"*",""),"")
... B66: 03 30 53 Miscellaneous Cast-in-Place Concrete | F66: =IF($F$9="*",IF(E66>0,"*",""),"") | H66: =IF($H$9="*",IF(G66>0,"*",""),"") | J66: =IF($J$9="*",IF(I66>0,"*",""),"") | L66: =IF($L$9="*",IF(K66>0,"*",""),"") | N66: =IF($N$9="*",IF(M66>0,"*",""),"") | P66: =IF($P$9="*",IF(O66>0,"*",""),"") | R66: =IF($R$9="*",IF(Q66>0,"*",""),"") | T66: =IF($T$9="*",IF(S66>0,"*",""),"") | V66: =IF($V$9="*",IF(U66>0,"*",""),"")
A67: 1 | B67: 03 31 00 Structural Concrete | E67: =H67 -> 2242500 | F67: =IF($F$9="*",IF(E67>0,"*",""),"") -> * | G67: =443621+169796+1965719+20000 -> 2599136 | H67: 2242500 | I67: 2150476 | J67: =2632900+32500 -> 2665400 | K67: =1880190+243000+82549+24975+72549 -> 2303263 | L67: =IF($L$9="*",IF(K67>0,"*",""),"") | N67: =IF($N$9="*",IF(M67>0,"*",""),"") | P67: =IF($P$9="*",IF(O67>0,"*",""),"") | Q67: 4044273 | R67: 2295265 | S67: 1976530 | T67: =IF($T$9="*",IF(S67>0,"*",""),"") | V67: =IF($V$9="*",IF(U67>0,"*",""),"")
B68: 03 31 13 Heavyweight Structural Concrete | F68: =IF($F$9="*",IF(E68>0,"*",""),"") | H68: =IF($H$9="*",IF(G68>0,"*",""),"") | J68: =IF($J$9="*",IF(I68>0,"*",""),"") | L68: =IF($L$9="*",IF(K68>0,"*",""),"") | N68: =IF($N$9="*",IF(M68>0,"*",""),"") | P68: =IF($P$9="*",IF(O68>0,"*",""),"") | R68: =IF($R$9="*",IF(Q68>0,"*",""),"") | T68: =IF($T$9="*",IF(S68>0,"*",""),"") | V68: =IF($V$9="*",IF(U68>0,"*",""),"")
B69: 03 31 16 Lightweight Structural Concrete | F69: =IF($F$9="*",IF(E69>0,"*",""),"") | H69: =IF($H$9="*",IF(G69>0,"*",""),"") | J69: =IF($J$9="*",IF(I69>0,"*",""),"") | L69: =IF($L$9="*",IF(K69>0,"*",""),"") | N69: =IF($N$9="*",IF(M69>0,"*",""),"") | P69: =IF($P$9="*",IF(O69>0,"*",""),"") | R69: =IF($R$9="*",IF(Q69>0,"*",""),"") | T69: =IF($T$9="*",IF(S69>0,"*",""),"") | V69: =IF($V$9="*",IF(U69>0,"*",""),"")
B70: 03 31 19 Shrinkage-Compensating Structural Concrete | F70: =IF($F$9="*",IF(E70>0,"*",""),"") | H70: =IF($H$9="*",IF(G70>0,"*",""),"") | J70: =IF($J$9="*",IF(I70>0,"*",""),"") | L70: =IF($L$9="*",IF(K70>0,"*",""),"") | N70: =IF($N$9="*",IF(M70>0,"*",""),"") | P70: =IF($P$9="*",IF(O70>0,"*",""),"") | R70: =IF($R$9="*",IF(Q70>0,"*",""),"") | T70: =IF($T$9="*",IF(S70>0,"*",""),"") | V70: =IF($V$9="*",IF(U70>0,"*",""),"")
B71: 03 31 23 High-Performance Structural Concrete | F71: =IF($F$9="*",IF(E71>0,"*",""),"") | H71: =IF($H$9="*",IF(G71>0,"*",""),"") | J71: =IF($J$9="*",IF(I71>0,"*",""),"") | L71: =IF($L$9="*",IF(K71>0,"*",""),"") | N71: =IF($N$9="*",IF(M71>0,"*",""),"") | P71: =IF($P$9="*",IF(O71>0,"*",""),"") | R71: =IF($R$9="*",IF(Q71>0,"*",""),"") | T71: =IF($T$9="*",IF(S71>0,"*",""),"") | V71: =IF($V$9="*",IF(U71>0,"*",""),"")
B72: 03 31 24 Ultra High-Performance Structural Concrete | F72: =IF($F$9="*",IF(E72>0,"*",""),"") | H72: =IF($H$9="*",IF(G72>0,"*",""),"") | J72: =IF($J$9="*",IF(I72>0,"*",""),"") | L72: =IF($L$9="*",IF(K72>0,"*",""),"") | N72: =IF($N$9="*",IF(M72>0,"*",""),"") | P72: =IF($P$9="*",IF(O72>0,"*",""),"") | R72: =IF($R$9="*",IF(Q72>0,"*",""),"") | T72: =IF($T$9="*",IF(S72>0,"*",""),"") | V72: =IF($V$9="*",IF(U72>0,"*",""),"")
B73: 03 31 26 Self-Compacting Concrete | F73: =IF($F$9="*",IF(E73>0,"*",""),"") | H73: =IF($H$9="*",IF(G73>0,"*",""),"") | J73: =IF($J$9="*",IF(I73>0,"*",""),"") | L73: =IF($L$9="*",IF(K73>0,"*",""),"") | N73: =IF($N$9="*",IF(M73>0,"*",""),"") | P73: =IF($P$9="*",IF(O73>0,"*",""),"") | R73: =IF($R$9="*",IF(Q73>0,"*",""),"") | T73: =IF($T$9="*",IF(S73>0,"*",""),"") | V73: =IF($V$9="*",IF(U73>0,"*",""),"")
B74: 03 33 00 Architectural Concrete | F74: =IF($F$9="*",IF(E74>0,"*",""),"") | H74: =IF($H$9="*",IF(G74>0,"*",""),"") | J74: =IF($J$9="*",IF(I74>0,"*",""),"") | L74: =IF($L$9="*",IF(K74>0,"*",""),"") | N74: =IF($N$9="*",IF(M74>0,"*",""),"") | P74: =IF($P$9="*",IF(O74>0,"*",""),"") | R74: =IF($R$9="*",IF(Q74>0,"*",""),"") | T74: =IF($T$9="*",IF(S74>0,"*",""),"") | V74: =IF($V$9="*",IF(U74>0,"*",""),"")
B75: 03 33 13 Heavyweight Architectural Concrete | F75: =IF($F$9="*",IF(E75>0,"*",""),"") | H75: =IF($H$9="*",IF(G75>0,"*",""),"") | J75: =IF($J$9="*",IF(I75>0,"*",""),"") | L75: =IF($L$9="*",IF(K75>0,"*",""),"") | N75: =IF($N$9="*",IF(M75>0,"*",""),"") | P75: =IF($P$9="*",IF(O75>0,"*",""),"") | R75: =IF($R$9="*",IF(Q75>0,"*",""),"") | T75: =IF($T$9="*",IF(S75>0,"*",""),"") | V75: =IF($V$9="*",IF(U75>0,"*",""),"")
B76: 03 33 16 Lightweight Architectural Concrete | F76: =IF($F$9="*",IF(E76>0,"*",""),"") | H76: =IF($H$9="*",IF(G76>0,"*",""),"") | J76: =IF($J$9="*",IF(I76>0,"*",""),"") | L76: =IF($L$9="*",IF(K76>0,"*",""),"") | N76: =IF($N$9="*",IF(M76>0,"*",""),"") | P76: =IF($P$9="*",IF(O76>0,"*",""),"") | R76: =IF($R$9="*",IF(Q76>0,"*",""),"") | T76: =IF($T$9="*",IF(S76>0,"*",""),"") | V76: =IF($V$9="*",IF(U76>0,"*",""),"")
B77: 03 34 00 Low Density Concrete | F77: =IF($F$9="*",IF(E77>0,"*",""),"") | H77: =IF($H$9="*",IF(G77>0,"*",""),"") | J77: =IF($J$9="*",IF(I77>0,"*",""),"") | L77: =IF($L$9="*",IF(K77>0,"*",""),"") | N77: =IF($N$9="*",IF(M77>0,"*",""),"") | P77: =IF($P$9="*",IF(O77>0,"*",""),"") | R77: =IF($R$9="*",IF(Q77>0,"*",""),"") | T77: =IF($T$9="*",IF(S77>0,"*",""),"") | V77: =IF($V$9="*",IF(U77>0,"*",""),"")
B78: 03 35 00 Concrete Finishing | F78: =IF($F$9="*",IF(E78>0,"*",""),"") | H78: =IF($H$9="*",IF(G78>0,"*",""),"") | J78: =IF($J$9="*",IF(I78>0,"*",""),"") | L78: =IF($L$9="*",IF(K78>0,"*",""),"") | N78: =IF($N$9="*",IF(M78>0,"*",""),"") | P78: =IF($P$9="*",IF(O78>0,"*",""),"") | R78: =IF($R$9="*",IF(Q78>0,"*",""),"") | T78: =IF($T$9="*",IF(S78>0,"*",""),"") | V78: =IF($V$9="*",IF(U78>0,"*",""),"")
B79: 03 35 13 High-Tolerance Concrete Floor Finishing | F79: =IF($F$9="*",IF(E79>0,"*",""),"") | H79: =IF($H$9="*",IF(G79>0,"*",""),"") | J79: =IF($J$9="*",IF(I79>0,"*",""),"") | L79: =IF($L$9="*",IF(K79>0,"*",""),"") | N79: =IF($N$9="*",IF(M79>0,"*",""),"") | P79: =IF($P$9="*",IF(O79>0,"*",""),"") | R79: =IF($R$9="*",IF(Q79>0,"*",""),"") | T79: =IF($T$9="*",IF(S79>0,"*",""),"") | V79: =IF($V$9="*",IF(U79>0,"*",""),"")
... B105: 03 39 23.23 Sheet Membrane Concrete Curing | F105: =IF($F$9="*",IF(E105>0,"*",""),"") | H105: =IF($H$9="*",IF(G105>0,"*",""),"") | J105: =IF($J$9="*",IF(I105>0,"*",""),"") | L105: =IF($L$9="*",IF(K105>0,"*",""),"") | N105: =IF($N$9="*",IF(M105>0,"*",""),"") | P105: =IF($P$9="*",IF(O105>0,"*",""),"") | R105: =IF($R$9="*",IF(Q105>0,"*",""),"") | T105: =IF($T$9="*",IF(S105>0,"*",""),"") | V105: =IF($V$9="*",IF(U105>0,"*",""),"")
